Workbook

Sheet Projects
C1: RD Projects | BN1: 26 | BP1: 27
B2: # | C2: Projects | E2: PM | F2: TASK COMPLETE | G2: Status | I2: Note | J2: Month 2025 - 2026 | BF2: Month 2026 - 2027
B3: 1 | C3: Features | J3: April | N3: May | R3: June | V3: July | Z3: August | AD3: September | AH3: October | AL3: November | AP3: December | AT3: January | AX3: February | BB3: March | BF3: April | BJ3: May | BN3: June | BR3: July | BV3: August | BZ3: September | CD3: October | CH3: November | CL3: December | CP3: January | CT3: February | CX3: March
C4: Adjust | D4: Zan | E4: Mean | F4: 1 | G4: Done
C5: CleverTap | D5: Jack | E5: Mean | F5: 1 | G5: Done
C6: Ecommerce Shopify | D6: Aek | E6: Mean | F6: 1 | G6: Done
C7: AWS Migration | D7: A | E7: Win | F7: 0.3 | G7: In Progress | H7: Timeline | I7: Dev 85%, UAT 0%, Prod 0%
C8: Thana Datamart API (New Datamart) | D8: Zan | E8: Win | F8: 0.8 | G8: In Progress | H8: Timeline | I8: - Token Light Speed (Dev sp21) Lightspeed Token [5P] Create OM API Connect [5P] Integrate new token flow to light speed service and retest send data - [3P] Update mapping light speed enhancement (Dev sp21) - API send to CT (SA est sp21, Dev sp22) | BB8: dev env
C9: Thana City (Out of Scope OM) | D9: Zan, Aek | E9: Win | F9: 0.6 | G9: In Progress | H9: Timeline | I9: - POS transaction API ของ Light Speed - POS Master data (End of Feb TBC) - Shopify webhook and View tables | BE9: sa, dev
C10: Vimi Termination | D10: Zan, Aek | E10: Mean | F10: 0.6 | G10: In Progress | H10: Timeline | I10: https://docs.google.com/spreadsheets/d/1HlvYW4TgA-JaRO8mMb0kbMwip2YzqJ738MSP5CJ1sls/edit?gid=1729294108#gid=1729294108 | BC10: api 13 | BF10: submit app 30/31 Mar , Release 3 April
C11: New Point Engine | D11: Aom, Jack | E11: Mook | F11: 0.15 | G11: In Progress | H11: Timeline
C12: Subscription Short-Distance (Support App, A920) | D12: Aek, Zan | E12: Mean | F12: 1 | G12: Done | I12: RR App and A920 (ไม่ต้องทำแล้ว รอ confirm) | BF12: monitoring 1 - 3 apr
C13: Pay with Point | D13: Aom, Zan | E13: P'Pop | F13: 0.9 | G13: In Progress | H13: Timeline
C14: Turtle Plus member tier upgrade & downgrade | D14: Zan | E14: Mean | F14: 0.1 | G14: In Progress | I14: Upgrade ใช้ solution เดิม(ตอนนี้), Downgrade -> ทำไฟล์ run script
C15: PayPoint (Point Marketplace) integration | D15: Zan, Aek | E15: Mean | F15: 0 | G15: In Progress | I15: Provided spec
C16: SSO Migration | D16: A | E16: Win | F16: 0 | G16: To Do
C17: Cloud Samsung | F17: 0 | G17: In Progress
C18: Review App Handover document | F18: 0 | G18: Done
C19: Unified App | F19: 0 | G19: In Progress
C20: Rcash PLoan | F20: 0 | G20: In Progress
C21: Tech Debt | F21: 0 | G21: In Progress

Sheet Sprint Resource
B1: Total Manhour/Sprint
A2: Sprint | B2: Date | C2: Aek | D2: Aom | E2: Zan | F2: Jack | G2: A | H2: Mai | I2: Mac | J2: Mos | K2: Nim | L2: Arm | O2: Total All | P2: Total Dev | Q2: Stories Point : Dev | R2: Remark
A3: 6 | B3: 25 Aug - 5 Sep | C3: 6.5 | D3: 6.5 | E3: 6.5 | F3: 6.5 | G3: 6.5 | H3: 6.5 | I3: 6.5 | J3: 6.5 | S3: 1 -> 2h -> 7200
B4: day | C4: 7.5 | D4: 7.5 | E4: 7.5 | F4: 8 | G4: 7.5 | H4: 8 | I4: 8 | J4: 7 | R4: มีวันหยุด 0 วัน | S4: 2 -> 4h -> 14400
B5: hour | C5: =C3*C4 -> 48.75 | D5: =D3*D4 -> 48.75 | E5: =E3*E4 -> 48.75 | F5: =F3*F4 -> 52 | G5: =G3*G4 -> 48.75 | H5: =H3*H4 -> 52 | I5: =I3*I4 -> 52 | J5: =J3*J4 -> 45.5 | O5: =SUM(C5:N5) -> 396.5 | R5: Aom 0.5, Zan 0.5, Aek 0.5, A 0.5, Mos 1 | S5: 3 -> 1d -> 28800
A6: 7 | B6: 8 Sep - 19 Sep | C6: 6.5 | D6: 6.5 | E6: 6.5 | F6: 6.5 | G6: 6.5 | H6: 6.5 | I6: 6.5 | J6: 6.5 | K6: 6.5 | S6: 5 -> 2d -> 57600
B7: day | C7: 8 | D7: 7.5 | E7: 8 | F7: 8 | G7: 8 | H7: 8 | I7: 8 | J7: 7.5 | K7: 7 | R7: มีวันหยุด 0 วัน | S7: 8 -> 3d -> 86400
B8: hour | C8: =C6*C7 -> 52 | D8: =D6*D7 -> 48.75 | E8: =E6*E7 -> 52 | F8: =F6*F7 -> 52 | G8: =G6*G7 -> 52 | H8: =H6*H7 -> 52 | I8: =I6*I7 -> 52 | J8: =J6*J7 -> 48.75 | K8: =K6*K7 -> 45.5 | O8: =SUM(C8:N8) -> 455 | R8: Aom 0.5, Mos 0.5, Nim 1
A9: 8 | B9: 22 Sep - 3 Oct | C9: 6.5 | D9: 6.5 | E9: 6.5 | F9: 6.5 | G9: 6.5 | H9: 6.5 | I9: 6.5 | J9: 6.5 | K9: 6.5 | S9: Mos 7.5
B10: day | C10: 7 | D10: 7 | E10: 8 | F10: 7 | G10: 8 | H10: 7 | I10: 8 | J10: 8 | K10: 8 | R10: มีวันหยุด 0 วัน | S10: Nim 5
B11: hour | C11: =C9*C10 -> 45.5 | D11: =D9*D10 -> 45.5 | E11: =E9*E10 -> 52 | F11: =F9*F10 -> 45.5 | G11: =G9*G10 -> 52 | H11: =H9*H10 -> 45.5 | I11: =I9*I10 -> 52 | J11: =J9*J10 -> 52 | K11: =K9*K10 -> 52 | O11: =SUM(C11:N11) -> 442 | R11: Aek 1, Aom 1, Mai 1, Jack 1 | S11: Arm 4
A12: 9 | B12: 6 Oct - 17 Oct | C12: 6.5 | D12: 6.5 | E12: 6.5 | F12: 6.5 | G12: 6.5 | H12: 6.5 | I12: 6.5 | J12: 6.5 | K12: 6.5
B13: day | C13: 4.5 | D13: 7 | E13: 5 | F13: 6 | G13: 7 | H13: 3 | I13: 7 | J13: 6.5 | K13: 7 | R13: มีวันหยุด 1 วัน
B14: hour | C14: =C12*C13 -> 29.25 | D14: =D12*D13 -> 45.5 | E14: =E12*E13 -> 32.5 | F14: =F12*F13 -> 39 | G14: =G12*G13 -> 45.5 | H14: =H12*H13 -> 19.5 | I14: =I12*I13 -> 45.5 | J14: =J12*J13 -> 42.25 | K14: =K12*K13 -> 45.5 | O14: =SUM(C14:N14) -> 344.5 | R14: Aek 2.5, Zan 2, Mai 4, Jack 1, Mos 0.5
B15: point | C15: =FLOOR((C14/8)*3,1) -> 10 | D15: =FLOOR((D14/8)*3,1) -> 17 | E15: =FLOOR((E14/8)*3,1) -> 12 | F15: =FLOOR((F14/8)*3,1) -> 14 | G15: =FLOOR((G14/8)*3,1) -> 17 | H15: =FLOOR((H14/8)*3,1) -> 7 | I15: =FLOOR((I14/8)*3,1) -> 17 | J15: =FLOOR((J14/8)*3,1) -> 15 | K15: =FLOOR((K14/8)*3,1) -> 17
A16: 10 | B16: 20 Oct - 31 Oct | C16: 6.5 | D16: 6.5 | E16: 6.5 | F16: 6.5 | G16: 6.5 | H16: 6.5 | I16: 6.5 | J16: 6.5 | K16: 6.5
B17: day | C17: 6 | D17: 7 | E17: 7 | F17: 5 | G17: 6 | H17: 7 | I17: 7 | J17: 7 | K17: 7 | R17: มีวันหยุด 1 วัน
B18: hour | C18: =C16*C17 -> 39 | D18: =D16*D17 -> 45.5 | E18: =E16*E17 -> 45.5 | F18: =F16*F17 -> 32.5 | G18: =G16*G17 -> 39 | H18: =H16*H17 -> 45.5 | I18: =I16*I17 -> 45.5 | J18: =J16*J17 -> 45.5 | K18: =K16*K17 -> 45.5 | O18: =SUM(C18:N18) -> 383.5 | R18: Aek 1, Jack 2, A 1
B19: point | C19: =FLOOR((C18/8)*3,1) -> 14 | D19: =FLOOR((D18/8)*3,1) -> 17 | E19: =FLOOR((E18/8)*3,1) -> 17 | F19: =FLOOR((F18/8)*3,1) -> 12 | G19: =FLOOR((G18/8)*3,1) -> 14 | H19: =FLOOR((H18/8)*3,1) -> 17 | I19: =FLOOR((I18/8)*3,1) -> 17 | J19: =FLOOR((J18/8)*3,1) -> 17 | K19: =FLOOR((K18/8)*3,1) -> 17
A20: 11 | B20: 3 Nov - 14 Nov | C20: 6.5 | D20: 6.5 | E20: 6.5 | F20: 6.5 | G20: 6.5 | H20: 6.5 | I20: 6.5 | J20: 6.5 | K20: 6.5 | L20: 6.5
B21: day | C21: 7 | D21: 7 | E21: 8 | F21: 7 | G21: 7.5 | H21: 8 | I21: 6 | J21: 6.5 | K21: 7 | L21: 7 | R21: มีวันหยุด 0 วัน
B22: hour | C22: =C20*C21 -> 45.5 | D22: =D20*D21 -> 45.5 | E22: =E20*E21 -> 52 | F22: =F20*F21 -> 45.5 | G22: =G20*G21 -> 48.75 | H22: =H20*H21 -> 52 | I22: =I20*I21 -> 39 | J22: =J20*J21 -> 42.25 | ... L22: =L20*L21 -> 45.5 | O22: =SUM(C22:N22) -> 461.5 | R22: Jack 1, Nim 1, Mac 2, Aek 1, Aom 1, Arm 1, A 0.5, Mos 1.5
B23: point | C23: =FLOOR((C22/8)*3,1) -> 17 | D23: =FLOOR((D22/8)*3,1) -> 17 | E23: =FLOOR((E22/8)*3,1) -> 19 | F23: =FLOOR((F22/8)*3,1) -> 17 | G23: =FLOOR((G22/8)*3,1) -> 18 | H23: =FLOOR((H22/8)*3,1) -> 19 | I23: =FLOOR((I22/8)*3,1) -> 14 | J23: =FLOOR((J22/8)*3,1) -> 15 | ... L23: =FLOOR((L22/8)*3,1) -> 17
A24: 12 | B24: 17 Nov - 28 Nov | C24: 6.5 | D24: 6.5 | E24: 6.5 | F24: 6.5 | G24: 6.5 | H24: 6.5 | I24: 6.5 | J24: 6.5 | K24: 6.5 | L24: 6.5
B25: day | C25: 8 | D25: 6 | E25: 7 | F25: 8 | G25: 7.5 | H25: 8 | I25: 8 | J25: 6 | K25: 8 | L25: 6 | R25: มีวันหยุด 0 วัน
B26: hour | C26: =C24*C25 -> 52 | D26: =D24*D25 -> 39 | E26: =E24*E25 -> 45.5 | F26: =F24*F25 -> 52 | G26: =G24*G25 -> 48.75 | H26: =H24*H25 -> 52 | I26: =I24*I25 -> 52 | J26: =J24*J25 -> 39 | ... L26: =L24*L25 -> 39 | O26: =SUM(C26:N26) -> 471.25 | R26: Zan 1, Aom 2, Mos 2, A 0.5, Arm 2
B27: point | C27: =FLOOR((C26/8)*3,1) -> 19 | D27: =FLOOR((D26/8)*3,1) -> 14 | E27: =FLOOR((E26/8)*3,1) -> 17 | F27: =FLOOR((F26/8)*3,1) -> 19 | G27: =FLOOR((G26/8)*3,1) -> 18 | H27: =FLOOR((H26/8)*3,1) -> 19 | I27: =FLOOR((I26/8)*3,1) -> 19 | J27: =FLOOR((J26/8)*3,1) -> 14 | ... L27: =FLOOR((L26/8)*3,1) -> 14
A28: 13 | B28: 1 Dec - 12 Dec | C28: 6.5 | D28: 6.5 | E28: 6.5 | F28: 6.5 | G28: 6.5 | H28: 6.5 | I28: 6.5 | J28: 6.5 | K28: 6.5 | L28: 6.5
B29: day | C29: 6 | D29: 3 | E29: 7 | F29: 7 | G29: 7 | H29: 5 | I29: 7 | J29: 6.5 | K29: 5 | L29: 7 | R29: มีวันหยุด 1 วัน
B30: hour | C30: =C28*C29 -> 39 | D30: =D28*D29 -> 19.5 | E30: =E28*E29 -> 45.5 | F30: =F28*F29 -> 45.5 | G30: =G28*G29 -> 45.5 | H30: =H28*H29 -> 32.5 | I30: =I28*I29 -> 45.5 | J30: =J28*J29 -> 42.25 | ... L30: =L28*L29 -> 45.5 | O30: =SUM(C30:N30) -> 393.25 | R30: Aom 4, Mai 2, Nim 2, Aek 1, Mos 0.5
C31: =FLOOR((C30/8)*3,1) -> 14 | D31: =FLOOR((D30/8)*3,1) -> 7 | E31: =FLOOR((E30/8)*3,1) -> 17 | F31: =FLOOR((F30/8)*3,1) -> 17 | G31: =FLOOR((G30/8)*3,1) -> 17 | H31: =FLOOR((H30/8)*3,1) -> 12 | I31: =FLOOR((I30/8)*3,1) -> 17 | J31: =FLOOR((J30/8)*3,1) -> 15 | ... L31: =FLOOR((L30/8)*3,1) -> 17
A32: 14 | B32: 15 Dec - 26 Dec | C32: 6.5 | D32: 6.5 | E32: 6.5 | F32: 6.5 | G32: 6.5 | H32: 6.5 | I32: 6.5 | J32: 6.5 | K32: 6.5 | L32: 6.5
B33: day | C33: 6 | D33: 6 | E33: 8 | F33: 7 | G33: 7 | H33: 8 | I33: 8 | J33: 7 | K33: 7 | L33: 7.5 | R33: มีวันหยุด 0 วัน
B34: hour | C34: =C32*C33 -> 39 | D34: =D32*D33 -> 39 | E34: =E32*E33 -> 52 | F34: =F32*F33 -> 45.5 | G34: =G32*G33 -> 45.5 | H34: =H32*H33 -> 52 | I34: =I32*I33 -> 52 | J34: =J32*J33 -> 45.5 | ... L34: =L32*L33 -> 48.75 | O34: =SUM(C34:N34) -> 464.75 | R34: Nim 1, A 1, Aek 2, Aom 2, Jack 1, Arm 0.5, Mos 1
B35: point | C35: =FLOOR((C34/8)*3,1) -> 14 | D35: =FLOOR((D34/8)*3,1) -> 14 | E35: =FLOOR((E34/8)*3,1) -> 19 | F35: =FLOOR((F34/8)*3,1) -> 17 | G35: =FLOOR((G34/8)*3,1) -> 17 | H35: =FLOOR((H34/8)*3,1) -> 19 | I35: =FLOOR((I34/8)*3,1) -> 19 | J35: =FLOOR((J34/8)*3,1) -> 17 | ... L35: =FLOOR((L34/8)*3,1) -> 18
A36: 15 | B36: 29 Dec - 9 Jan | C36: 6.5 | D36: 6.5 | E36: 6.5 | F36: 6.5 | G36: 6.5 | H36: 6.5 | I36: 6.5 | J36: 6.5 | K36: 6.5 | L36: 6.5
B37: day | C37: 2.5 | D37: 5 | E37: 4.5 | F37: 4 | G37: 4.5 | H37: 5 | I37: 6 | J37: 5.5 | K37: 5 | L37: 6 | R37: มีวันหยุด 2 วัน + ลาสิ้นปี-ปีใหม่กันเยอะ
B38: hour | C38: =C36*C37 -> 16.25 | D38: =D36*D37 -> 32.5 | E38: =E36*E37 -> 29.25 | F38: =F36*F37 -> 26 | G38: =G36*G37 -> 29.25 | H38: =H36*H37 -> 32.5 | I38: =I36*I37 -> 39 | J38: =J36*J37 -> 35.75 | ... L38: =L36*L37 -> 39 | O38: =SUM(C38:N38) -> 312 | R38: Jack 2, A 1.5, Aek 3.5, Aom 1, Zan 1.5, Mai 1, Nim 1, Mos 0.5
B39: point | C39: =FLOOR((C38/8)*3,1) -> 6 | D39: =FLOOR((D38/8)*3,1) -> 12 | E39: =FLOOR((E38/8)*3,1) -> 10 | F39: =FLOOR((F38/8)*3,1) -> 9 | G39: =FLOOR((G38/8)*3,1) -> 10 | H39: =FLOOR((H38/8)*3,1) -> 12 | I39: =FLOOR((I38/8)*3,1) -> 14 | J39: =FLOOR((J38/8)*3,1) -> 13 | ... L39: =FLOOR((L38/8)*3,1) -> 14
A40: 16 | B40: 12 Jan - 23 Jan | C40: 6.5 | D40: 6.5 | E40: 6.5 | F40: 6.5 | G40: 6.5 | H40: 6.5 | I40: 6.5 | J40: 6.5 | K40: 6.5 | L40: 6.5
B41: day | C41: 7 | D41: 6 | E41: 6.5 | F41: 7 | G41: 5.5 | H41: 6 | I41: 7 | J41: 7 | K41: 7 | L41: 5 | R41: มี Team Building 1 วัน
B42: hour | C42: =C40*C41 -> 45.5 | D42: =D40*D41 -> 39 | E42: =E40*E41 -> 42.25 | F42: =F40*F41 -> 45.5 | G42: =G40*G41 -> 35.75 | H42: =H40*H41 -> 39 | I42: =I40*I41 -> 45.5 | J42: =J40*J41 -> 45.5 | ... L42: =L40*L41 -> 32.5 | O42: =SUM(C42:N42) -> 416 | R42: A 1.5, Arm 2, Aom 1, Zan 0.5, Mai 1
B43: point | C43: =FLOOR((C42/8)*3,1) -> 17 | D43: =FLOOR((D42/8)*3,1) -> 14 | E43: =FLOOR((E42/8)*3,1) -> 15 | F43: =FLOOR((F42/8)*3,1) -> 17 | G43: =FLOOR((G42/8)*3,1) -> 13 | H43: =FLOOR((H42/8)*3,1) -> 14 | I43: =FLOOR((I42/8)*3,1) -> 17 | J43: =FLOOR((J42/8)*3,1) -> 17 | ... L43: =FLOOR((L42/8)*3,1) -> 12
A44: 17 | B44: 26 Jan - 6 Feb | C44: 6.5 | D44: 6.5 | E44: 6.5 | F44: 6.5 | G44: 6.5 | H44: 6.5 | I44: 6.5 | J44: 6.5 | K44: 6.5 | L44: 6.5
B45: day | C45: 8 | D45: 8 | E45: 7 | F45: 5 | G45: 8 | H45: 8 | I45: 8 | J45: 8 | K45: 6 | L45: 2 | R45: มีวันหยุด 0 วัน
B46: hour | C46: =C44*C45 -> 52 | D46: =D44*D45 -> 52 | E46: =E44*E45 -> 45.5 | F46: =F44*F45 -> 32.5 | G46: =G44*G45 -> 52 | H46: =H44*H45 -> 52 | I46: =I44*I45 -> 52 | J46: =J44*J45 -> 52 | ... L46: =L44*L45 -> 13 | O46: =SUM(E46:N46) -> 338 | R46: Nim 2, Arm 1, Arm 5, Jack 3, Zan 1
B47: point | C47: =FLOOR((C46/8)*3,1) -> 19 | D47: =FLOOR((D46/8)*3,1) -> 19 | E47: =FLOOR((E46/8)*3,1) -> 17 | F47: =FLOOR((F46/8)*3,1) -> 12 | G47: =FLOOR((G46/8)*3,1) -> 19 | H47: =FLOOR((H46/8)*3,1) -> 19 | I47: =FLOOR((I46/8)*3,1) -> 19 | J47: =FLOOR((J46/8)*3,1) -> 19 | ... L47: =FLOOR((L46/8)*3,1) -> 4
A48: 18 | B48: 9 Feb - 20 Feb | C48: 7 | D48: 7 | E48: 7 | F48: 7 | G48: 7 | H48: 7 | I48: 7 | J48: 7 | K48: 7 | L48: 7
B49: day | C49: 7 | D49: 4.5 | E49: 5 | F49: 7 | G49: 6.5 | H49: 6 | I49: 6 | J49: 6.5 | K49: 7 | L49: 0 | R49: มีวันหยุด 1 วัน ตรุษจีน
B50: hour | C50: =C48*C49 -> 49 | D50: =D48*D49 -> 31.5 | E50: =E48*E49 -> 35 | F50: =F48*F49 -> 49 | G50: =G48*G49 -> 45.5 | H50: =H48*H49 -> 42 | I50: =I48*I49 -> 42 | J50: =J48*J49 -> 45.5 | ... L50: =L48*L49 -> 0 | O50: =SUM(C50:N50) -> 388.5 | P50: =SUM(G50:L50) -> 224 | R50: Aom 2.5, Zan 2, Mai 1, Mac 1, Arm 9, Mos 0.5, A 0.5
B51: point | C51: =FLOOR(C49*3,1) -> 21 | D51: =FLOOR(D49*3,1) -> 13 | E51: =FLOOR(E49*3,1) -> 15 | F51: =FLOOR(F49*3,1) -> 21 | G51: =FLOOR(G49*3,1) -> 19 | H51: =FLOOR(H49*3,1) -> 18 | I51: =FLOOR(I49*3,1) -> 18 | J51: =FLOOR(J49*3,1) -> 19 | ... L51: =FLOOR(L49*3,1) -> 0 | O51: =SUM(C51:N51) -> 165 | P51: =SUM(G51:L51) -> 95 | Q51: 21
A52: 19 | B52: 23 Feb - 6 Mar | C52: 7 | D52: 7 | E52: 7 | F52: 7 | G52: 7 | H52: 7 | I52: 7 | J52: 7 | K52: 7 | L52: 7
B53: day | C53: 6 | D53: 5 | E53: 6 | F53: 7 | G53: 7 | H53: 6 | I53: 6 | J53: 7 | K53: 7 | L53: 6.5 | R53: มีวันหยุด 1 วัน มาฆบูชา
B54: hour | C54: =C52*C53 -> 42 | D54: =D52*D53 -> 35 | E54: =E52*E53 -> 42 | F54: =F52*F53 -> 49 | G54: =G52*G53 -> 49 | H54: =H52*H53 -> 42 | I54: =I52*I53 -> 42 | J54: =J52*J53 -> 49 | ... L54: =L52*L53 -> 45.5 | O54: =SUM(C54:N54) -> 444.5 | P54: =SUM(G54:L54) -> 276.5 | R54: Aek 1, Aom 2, Zan 1, Mac 1, Mai 1, Arm 0.5
B55: point | C55: =FLOOR(C53*3,1) -> 18 | D55: =FLOOR(D53*3,1) -> 15 | E55: =FLOOR(E53*3,1) -> 18 | F55: =FLOOR(F53*3,1) -> 21 | G55: =FLOOR(G53*3,1) -> 21 | H55: =FLOOR(H53*3,1) -> 18 | I55: =FLOOR(I53*3,1) -> 18 | J55: =FLOOR(J53*3,1) -> 21 | ... L55: =FLOOR(L53*3,1) -> 19 | O55: =SUM(C55:N55) -> 190 | P55: =SUM(G55:L55) -> 118 | Q55: 21
A56: 20 | B56: 9 Mar - 20 Mar | C56: 7 | D56: 7 | E56: 7 | F56: 7 | G56: 7 | H56: 7 | I56: 7 | J56: 7 | K56: 7 | L56: 7
B57: day | C57: 8 | D57: 7 | E57: 7.5 | F57: 8 | G57: 7 | H57: 7 | I57: 7.5 | J57: 7 | K57: 7 | L57: 8 | R57: มีวันหยุด 0 วัน
B58: hour | C58: =C56*C57 -> 56 | D58: =D56*D57 -> 49 | E58: =E56*E57 -> 52.5 | F58: =F56*F57 -> 56 | G58: =G56*G57 -> 49 | H58: =H56*H57 -> 49 | I58: =I56*I57 -> 52.5 | J58: =J56*J57 -> 49 | ... L58: =L56*L57 -> 56 | O58: =SUM(C58:N58) -> 518 | P58: =SUM(G58:L58) -> 304.5 | R58: Aom 1, A 1, Mai 1, Mos 1, Nim 1, Zan 0.5, Mac 0.5
B59: point | C59: =FLOOR(C57*3,1) -> 24 | D59: =FLOOR(D57*3,1) -> 21 | E59: =FLOOR(E57*3,1) -> 22 | F59: =FLOOR(F57*3,1) -> 24 | G59: =FLOOR(G57*3,1) -> 21 | H59: =FLOOR(H57*3,1) -> 21 | I59: =FLOOR(I57*3,1) -> 22 | J59: =FLOOR(J57*3,1) -> 21 | ... L59: =FLOOR(L57*3,1) -> 24 | O59: =SUM(C59:N59) -> 221 | P59: =SUM(G59:L59) -> 130 | Q59: 24
A60: 21 | B60: 23 Mar - 3 Apr | C60: 7 | D60: 7 | E60: 7 | F60: 7 | G60: 7 | H60: 7 | I60: 7 | J60: 7 | K60: 7 | L60: 7
B61: day | C61: 7 | D61: 7 | E61: 8 | F61: 8 | G61: 7 | H61: 8 | I61: 8 | J61: 8 | K61: 7 | L61: 7.5 | R61: มีวันหยุด 0 วัน
B62: hour | C62: =C60*C61 -> 49 | D62: =D60*D61 -> 49 | E62: =E60*E61 -> 56 | F62: =F60*F61 -> 56 | G62: =G60*G61 -> 49 | H62: =H60*H61 -> 56 | I62: =I60*I61 -> 56 | J62: =J60*J61 -> 56 | ... L62: =L60*L61 -> 52.5 | O62: =SUM(C62:N62) -> 528.5 | P62: =SUM(G62:L62) -> 318.5 | R62: A 1, Aom 1, Aek 2, Nim 1, Arm 0.5
B63: point | C63: =FLOOR(C61*3,1) -> 21 | D63: =FLOOR(D61*3,1) -> 21 | E63: =FLOOR(E61*3,1) -> 24 | F63: =FLOOR(F61*3,1) -> 24 | G63: =FLOOR(G61*3,1) -> 21 | H63: =FLOOR(H61*3,1) -> 24 | I63: =FLOOR(I61*3,1) -> 24 | J63: =FLOOR(J61*3,1) -> 24 | ... L63: =FLOOR(L61*3,1) -> 22 | O63: =SUM(C63:N63) -> 226 | P63: =SUM(G63:L63) -> 136 | Q63: 24
A64: 22 | B64: 6 Apr - 17 Apr | C64: 7 | D64: 7 | E64: 7 | F64: 7 | G64: 7 | H64: 7 | I64: 7 | J64: 7 | K64: 7 | L64: 7
B65: day | C65: 3 | D65: 0 | E65: 3 | F65: 3 | G65: 4 | H65: 4 | I65: 3 | J65: 4 | K65: 4 | L65: 4 | R65: มีวันหยุด 4 วัน : วันจักรี 1 (SP), สงกรานต์ 3
B66: hour | C66: =C64*C65 -> 21 | D66: =D64*D65 -> 0 | E66: =E64*E65 -> 21 | F66: =F64*F65 -> 21 | G66: =G64*G65 -> 28 | H66: =H64*H65 -> 28 | I66: =I64*I65 -> 21 | J66: =J64*J65 -> 28 | ... L66: =L64*L65 -> 28 | O66: =SUM(C66:N66) -> 224 | P66: =SUM(G66:L66) -> 161 | R66: Aom 5, Aek 3, Zan 2, Mac 2, Jack 1
B67: point | C67: =FLOOR(C65*3,1) -> 9 | D67: =FLOOR(D65*3,1) -> 0 | E67: =FLOOR(E65*3,1) -> 9 | F67: =FLOOR(F65*3,1) -> 9 | G67: =FLOOR(G65*3,1) -> 12 | H67: =FLOOR(H65*3,1) -> 12 | I67: =FLOOR(I65*3,1) -> 9 | J67: =FLOOR(J65*3,1) -> 12 | ... L67: =FLOOR(L65*3,1) -> 12 | O67: =SUM(C67:N67) -> 96 | P67: =SUM(G67:L67) -> 69 | Q67: 12
A68: 23 | B68: 20 Apr - 1 May | C68: 7 | D68: 7 | E68: 7 | F68: 7 | G68: 7 | H68: 7 | I68: 7 | J68: 7 | K68: 7 | L68: 7
B69: day | C69: 7 | D69: 7 | E69: 7 | F69: 7 | G69: 7 | H69: 7 | I69: 7 | J69: 6 | K69: 7 | L69: 6 | R69: มีวันหยุด 1 วัน วันแรงงาน (SR)
B70: hour | C70: =C68*C69 -> 49 | D70: =D68*D69 -> 49 | E70: =E68*E69 -> 49 | F70: =F68*F69 -> 49 | G70: =G68*G69 -> 49 | H70: =H68*H69 -> 49 | I70: =I68*I69 -> 49 | J70: =J68*J69 -> 42 | ... L70: =L68*L69 -> 42 | O70: =SUM(C70:N70) -> 476 | P70: =SUM(G70:L70) -> 280 | R70: A 1 (SP), Mos 1, Arm 1
B71: point | C71: =FLOOR(C69*3,1) -> 21 | D71: =FLOOR(D69*3,1) -> 21 | E71: =FLOOR(E69*3,1) -> 21 | F71: =FLOOR(F69*3,1) -> 21 | G71: =FLOOR(G69*3,1) -> 21 | H71: =FLOOR(H69*3,1) -> 21 | I71: =FLOOR(I69*3,1) -> 21 | J71: =FLOOR(J69*3,1) -> 18 | ... L71: =FLOOR(L69*3,1) -> 18 | O71: =SUM(C71:N71) -> 204 | P71: =SUM(G71:L71) -> 120 | Q71: 21
A72: 24 | B72: 4 May - 15 May | C72: 7 | D72: 7 | E72: 7 | F72: 7 | G72: 7 | H72: 7 | I72: 7 | J72: 7 | K72: 7 | L72: 7
B73: day | C73: 7 | D73: 5 | E73: 6 | F73: 7 | G73: 6 | H73: 7 | I73: 7 | J73: 7 | K73: 7 | L73: 7 | R73: มีวันหยุด 1 วัน วันฉัตรมงคล (SP)
B74: hour | C74: =C72*C73 -> 49 | D74: =D72*D73 -> 35 | E74: =E72*E73 -> 42 | F74: =F72*F73 -> 49 | G74: =G72*G73 -> 42 | H74: =H72*H73 -> 49 | I74: =I72*I73 -> 49 | J74: =J72*J73 -> 49 | ... L74: =L72*L73 -> 49 | O74: =SUM(C74:N74) -> 462 | P74: =SUM(G74:L74) -> 287 | R74: Aom 2, Zan 1, A 1
B75: point | C75: =FLOOR(C73*3,1) -> 21 | D75: =FLOOR(D73*3,1) -> 15 | E75: =FLOOR(E73*3,1) -> 18 | F75: =FLOOR(F73*3,1) -> 21 | G75: =FLOOR(G73*3,1) -> 18 | H75: =FLOOR(H73*3,1) -> 21 | I75: =FLOOR(I73*3,1) -> 21 | J75: =FLOOR(J73*3,1) -> 21 | ... L75: =FLOOR(L73*3,1) -> 21 | O75: =SUM(C75:N75) -> 198 | P75: =SUM(G75:L75) -> 123 | Q75: 21
A76: 25 | B76: 18 May - 29 May | C76: 7 | D76: 7 | E76: 7 | F76: 7 | G76: 7 | H76: 7 | I76: 7 | J76: 7 | K76: 7 | L76: 7
B77: day | C77: 8 | D77: 7 | E77: 8 | F77: 8 | G77: 7 | H77: 4 | I77: 8 | J77: 8 | K77: 8 | L77: 8 | R77: มีวันหยุด 0 วัน
B78: hour | C78: =C76*C77 -> 56 | D78: =D76*D77 -> 49 | E78: =E76*E77 -> 56 | F78: =F76*F77 -> 56 | G78: =G76*G77 -> 49 | H78: =H76*H77 -> 28 | I78: =I76*I77 -> 56 | J78: =J76*J77 -> 56 | ... L78: =L76*L77 -> 56 | O78: =SUM(C78:N78) -> 518 | P78: =SUM(G78:L78) -> 301 | R78: Mai 5, A 1, Aom 2
B79: point | C79: =FLOOR(C77*3,1) -> 24 | D79: =FLOOR(D77*3,1) -> 21 | E79: =FLOOR(E77*3,1) -> 24 | F79: =FLOOR(F77*3,1) -> 24 | G79: =FLOOR(G77*3,1) -> 21 | H79: =FLOOR(H77*3,1) -> 12 | I79: =FLOOR(I77*3,1) -> 24 | J79: =FLOOR(J77*3,1) -> 24 | ... L79: =FLOOR(L77*3,1) -> 24 | O79: =SUM(C79:N79) -> 222 | P79: =SUM(G79:L79) -> 129 | Q79: 24
A80: 26 | B80: 1 Jun - 12 Jun | C80: 7 | D80: 7 | E80: 7 | F80: 7 | G80: 7 | H80: 7 | I80: 7 | J80: 7 | K80: 7 | L80: 7
B81: day | C81: 5 | D81: 5.5 | E81: 4.5 | F81: 5 | G81: 7 | H81: 6 | I81: 7 | J81: 7 | K81: 7 | L81: 7 | R81: มีวันหยุด 1 วัน วันเฉลิมพระราชินี
B82: hour | C82: =C80*C81 -> 35 | D82: =D80*D81 -> 38.5 | E82: =E80*E81 -> 31.5 | F82: =F80*F81 -> 35 | G82: =G80*G81 -> 49 | H82: =H80*H81 -> 42 | I82: =I80*I81 -> 49 | J82: =J80*J81 -> 49 | ... L82: =L80*L81 -> 49 | O82: =SUM(C82:N82) -> 427 | P82: =SUM(G82:L82) -> 287 | R82: Aek 2, Jack 2, Zan 2.5, Aom 1.5, Mai 1
B83: point | C83: =FLOOR(C81*3,1) -> 15 | D83: =FLOOR(D81*3,1) -> 16 | E83: =FLOOR(E81*3,1) -> 13 | F83: =FLOOR(F81*3,1) -> 15 | G83: =FLOOR(G81*3,1) -> 21 | H83: =FLOOR(H81*3,1) -> 18 | I83: =FLOOR(I81*3,1) -> 21 | J83: =FLOOR(J81*3,1) -> 21 | ... L83: =FLOOR(L81*3,1) -> 21 | O83: =SUM(C83:N83) -> 182 | P83: =SUM(G83:L83) -> 123 | Q83: 21
A84: 27 | B84: 15 Jun - 26 Jun | C84: 7 | D84: 7 | E84: 7 | F84: 7 | G84: 7 | H84: 7 | I84: 7 | J84: 7 | K84: 7 | L84: 7
B85: day | C85: 7 | D85: 8 | E85: 8 | F85: 8 | G85: 7 | H85: 8 | I85: 8 | J85: 8 | K85: 7 | L85: 8 | R85: มีวันหยุด 0 วัน
B86: hour | C86: =C84*C85 -> 49 | D86: =D84*D85 -> 56 | E86: =E84*E85 -> 56 | F86: =F84*F85 -> 56 | G86: =G84*G85 -> 49 | H86: =H84*H85 -> 56 | I86: =I84*I85 -> 56 | J86: =J84*J85 -> 56 | ... L86: =L84*L85 -> 56 | O86: =SUM(C86:N86) -> 539 | P86: =SUM(G86:L86) -> 322 | R86: Aek 1, Nim 1, A 1
B87: point | C87: =FLOOR(C85*3,1) -> 21 | D87: =FLOOR(D85*3,1) -> 24 | E87: =FLOOR(E85*3,1) -> 24 | F87: =FLOOR(F85*3,1) -> 24 | G87: =FLOOR(G85*3,1) -> 21 | H87: =FLOOR(H85*3,1) -> 24 | I87: =FLOOR(I85*3,1) -> 24 | J87: =FLOOR(J85*3,1) -> 24 | ... L87: =FLOOR(L85*3,1) -> 24 | O87: =SUM(C87:N87) -> 231 | P87: =SUM(G87:L87) -> 138 | Q87: 24
A88: 28 | B88: 29 Jun - 10 Jul | C88: 7 | D88: 7 | E88: 7 | F88: 7 | G88: 7 | H88: 7 | I88: 7 | J88: 7 | K88: 7 | L88: 7
B89: day | C89: 8 | D89: 8 | E89: 8 | F89: 8 | G89: 8 | H89: 8 | I89: 8 | J89: 8 | K89: 7 | L89: 8 | R89: มีวันหยุด 0 วัน
B90: hour | C90: =C88*C89 -> 56 | D90: =D88*D89 -> 56 | E90: =E88*E89 -> 56 | F90: =F88*F89 -> 56 | G90: =G88*G89 -> 56 | H90: =H88*H89 -> 56 | I90: =I88*I89 -> 56 | J90: =J88*J89 -> 56 | ... L90: =L88*L89 -> 56 | O90: =SUM(C90:N90) -> 553 | P90: =SUM(G90:L90) -> 329 | R90: Nim 1, Mac 1
B91: point | C91: =FLOOR(C89*3,1) -> 24 | D91: =FLOOR(D89*3,1) -> 24 | E91: =FLOOR(E89*3,1) -> 24 | F91: =FLOOR(F89*3,1) -> 24 | G91: =FLOOR(G89*3,1) -> 24 | H91: =FLOOR(H89*3,1) -> 24 | I91: =FLOOR(I89*3,1) -> 24 | J91: =FLOOR(J89*3,1) -> 24 | ... L91: =FLOOR(L89*3,1) -> 24 | O91: =SUM(C91:N91) -> 237 | P91: =SUM(G91:L91) -> 141 | Q91: 24
G135: P000078
G137: P000100

Sheet Resource Allocate
A2: Resource Plan – Sprint 19 23 Feb - 6 Mar
A3: ="Capacity รวมทั้งทีม "&SUM(C14:C19)&" SP" -> Capacity รวมทั้งทีม 118.5 SP | B3: =SUM(C14:C19) -> 118.5
A4: Allocation each project (exclude PE) | B4: =SUM(F20,G20,I20,J20, K20) -> #REF!
A5: Allocation PE | B5: =B3-B4 -> #REF!
A6: New Point Engine | B6: =E20 -> #REF! | C6: 3
A7: Vimi Termination | B7: =F20 -> #REF! | C7: 1
A8: Thana | B8: =G20 -> #REF! | C8: 2
A9: Datamart | B9: =I20 -> #REF! | C9: 1
A10: AWS | B10: =J20 -> #REF! | C10: 1
A11: Dev Support | B11: =K20 -> #REF!
A12: Remaining | B12: =C20-D20 -> #REF!
A13: Name | B13: Availability | C13: Capacity | D13: Total Workload | E13: PE (SP) | F13: VIMI (SP) | G13: Thana (SP) | I13: Datamart (SP) | J13: AWS (SP) | K13: Dev Support (SP)
A14: A | B14: 7 | C14: =3*B14 -> 21 | D14: =SUM(E14,F14,G14,I14,J14,K14) -> #REF! | E14: =3*#REF! -> #REF! | F14: =3*#REF! -> #REF! | G14: =3*#REF! -> #REF! | I14: =3*#REF! -> #REF! | J14: =3*#REF! -> #REF! | K14: 2
A15: Mac | B15: 6 | C15: =3*B15 -> 18 | D15: =SUM(E15,F15,G15,I15,J15,K15) -> #REF! | E15: =3*#REF! -> #REF! | F15: =3*#REF! -> #REF! | G15: =3*#REF! -> #REF! | I15: =3*#REF! -> #REF! | J15: =3*#REF! -> #REF! | K15: =3*#REF! -> #REF!
A16: Mai | B16: 6 | C16: =3*B16 -> 18 | D16: =SUM(E16,F16,G16,I16,J16,K16) -> #REF! | E16: =3*#REF! -> #REF! | F16: =3*#REF! -> #REF! | G16: =3*#REF! -> #REF! | I16: =3*#REF! -> #REF! | K16: =3*#REF! -> #REF!
A17: Mos | B17: 7 | C17: =3*B17 -> 21 | D17: =SUM(E17,F17,G17,I17,J17,K17) -> #REF! | E17: =3*#REF! -> #REF! | F17: =3*#REF! -> #REF! | I17: =3*#REF! -> #REF! | K17: =3*#REF! -> #REF!
A18: Nim | B18: 7 | C18: =3*B18 -> 21 | D18: =SUM(E18,F18,G18,I18,J18,K18) -> #REF! | E18: =3*#REF! -> #REF! | F18: =3*#REF! -> #REF! | I18: =3*#REF! -> #REF! | K18: 2
A19: Arm | B19: 6.5 | C19: =3*B19 -> 19.5 | D19: =SUM(E19,F19,G19,I19,J19,K19) -> #REF! | E19: =3*#REF! -> #REF! | F19: =3*#REF! -> #REF! | I19: =3*#REF! -> #REF! | K19: 3
A20: Total | C20: =SUM(C14:C19) -> 118.5 | D20: =SUM(D14:D19) -> #REF! | E20: =3*#REF! -> #REF! | F20: =3*#REF! -> #REF! | G20: =SUM(G14:G19) -> #REF! | I20: =SUM(I14:I19) -> #REF! | J20: =SUM(J14:J19) -> #REF! | K20: =SUM(K14:K19) -> #REF!
A22: Resource Plan – Sprint 20 9 Mar - 20 Mar
A23: ="Capacity รวม "&SUM(C34:C39)&" SP" -> Capacity รวม 130.5 SP | B23: =SUM(C34:C39) -> 130.5
A24: Allocation each project (exclude PE) | B24: =SUM(F40,G40,I40,J40, K40) -> #REF!
A25: Allocation PE | B25: =B23-B24 -> #REF!
A26: New Point Engine | B26: =E40 -> #REF! | C26: 4
A27: Vimi Termination | B27: =F40 -> #REF! | C27: 1
A28: Thana | B28: =G40 -> #REF! | C28: 2
A29: Datamart | B29: =I40 -> #REF! | C29: 0
A30: AWS | B30: =I40 -> #REF! | C30: 0
A31: Dev Support | B31: =K40 -> #REF! | C31: 1
A32: Remaining | B32: =C40-D40 -> #REF!
A33: Name | B33: Availability | C33: Capacity | D33: Total Workload | E33: PE (SP) | F33: VIMI (SP) | G33: Thana (SP) | I33: AWS (SP) | J33: Adhoc (SP) | K33: Dev Support (SP)
A34: A | B34: 7 | C34: =3*B34 -> 21 | D34: =SUM(E34,F34,G34,I34,J34,K34) -> #REF! | E34: =3*#REF! -> #REF! | F34: =3*#REF! -> #REF! | G34: =3*#REF! -> #REF! | I34: =3*#REF! -> #REF! | J34: =3*#REF! -> #REF! | K34: 1
A35: Mac | B35: 7.5 | C35: =3*B35 -> 22.5 | D35: =SUM(E35,F35,G35,I35,J35,K35) -> #REF! | E35: =3*#REF! -> #REF! | F35: =3*#REF! -> #REF! | G35: =3*#REF! -> #REF! | I35: =3*#REF! -> #REF! | K35: =3*#REF! -> #REF!
A36: Mai | B36: 7 | C36: =3*B36 -> 21 | D36: =SUM(E36,F36,G36,I36,J36,K36) -> #REF! | E36: =3*#REF! -> #REF! | F36: =3*#REF! -> #REF! | G36: =3*#REF! -> #REF! | I36: =3*#REF! -> #REF! | K36: =3*#REF! -> #REF!
A37: Mos | B37: 7 | C37: =3*B37 -> 21 | D37: =SUM(E37,F37,G37,I37,J37,K37) -> #REF! | E37: =3*#REF! -> #REF! | F37: =3*#REF! -> #REF! | G37: =3*#REF! -> #REF! | I37: =3*#REF! -> #REF! | K37: =3*#REF! -> #REF!
A38: Nim | B38: 7 | C38: =3*B38 -> 21 | D38: =SUM(E38,F38,G38,I38,J38,K38) -> #REF! | E38: =3*#REF! -> #REF! | F38: =3*#REF! -> #REF! | G38: =3*#REF! -> #REF! | I38: =3*#REF! -> #REF! | K38: =3*#REF! -> #REF!
A39: Arm | B39: 8 | C39: =3*B39 -> 24 | D39: =SUM(E39,F39,G39,I39,J39,K39) -> #REF! | E39: =3*#REF! -> #REF! | F39: =3*#REF! -> #REF! | G39: =3*#REF! -> #REF! | I39: =3*#REF! -> #REF! | K39: =3*#REF! -> #REF!
A40: Total | C40: =SUM(C34:C39) -> 130.5 | D40: =SUM(D34:D39) -> #REF! | E40: =3*#REF! -> #REF! | F40: =3*#REF! -> #REF! | G40: =SUM(G34:G39) -> #REF! | I40: =SUM(I34:I39) -> #REF! | J40: =SUM(J34:J39) -> #REF! | K40: =SUM(K34:K39) -> #REF!
A42: Resource Plan – Sprint 21 23 Mar - 3 Apr | B42: =SUM(B43:B44) -> 226.5
A43: ="Capacity SA รวม "&SUM(C55:C58)&" SP" -> Capacity SA รวม 90 SP | B43: =SUM(C55:C58) -> 90
A44: ="Capacity DEV รวม "&SUM(C60:C65)&" SP" -> Capacity DEV รวม 136.5 SP | B44: =SUM(C60:C65) -> 136.5
A45: Allocation each project (exclude PE) | B45: =SUM(F66:K66) -> 24
A46: Allocation PE | B46: =B44-B45 -> 112.5 | C46: =SUM(E60:E65) -> 110
A47: New Point Engine | B47: =E66 -> 110 | C47: 6
A48: Vimi Termination | B48: =F66 -> 3 | C48: 1
A49: Thana | B49: =G66 -> 11 | C49: 1
A50: Datamart | B50: =H66 -> 4 | C50: 1
A51: AWS | B51: =I66 -> 0 | C51: 0
A52: Adhoc | B52: =J66 -> 0
A53: Dev Support | B53: =K66 -> 6
A54: Name | B54: Availability | C54: Capacity | D54: Total Workload | E54: New PE | F54: VIMI | G54: Thana | H54: Datamart | I54: AWS | J54: Adhoc | K54: Dev Support
A55: Aek | B55: 7 | C55: =3*B55 -> 21 | D55: =SUM(E55:K55) -> 23 | E55: 3 | J55: 17 | K55: 3
A56: Aom | B56: 7 | C56: =3*B56 -> 21 | D56: =SUM(E56:K56) -> 31 | E56: 23 | K56: 8
A57: Zan | B57: 8 | C57: =3*B57 -> 24 | D57: =SUM(E57:K57) -> 33 | G57: 8 | H57: 3 | J57: 21 | K57: 1
A58: Jack | B58: 8 | C58: =3*B58 -> 24 | D58: =SUM(E58:K58) -> 15 | E58: 15
C59: =SUM(C55:C58) -> 90 | D59: =SUM(D55:D58) -> 102
A60: A | B60: 7 | C60: =3*B60 -> 21 | D60: =SUM(E60:K60) -> 21 | E60: 21
A61: Mac | B61: 8 | C61: =3*B61 -> 24 | D61: =SUM(E61:K61) -> 23 | E61: 8 | G61: 11 | H61: 4
A62: Mai | B62: 8 | C62: =3*B62 -> 24 | D62: =SUM(E62:K62) -> 21 | E62: 18 | K62: 3
A63: Mos | B63: 8 | C63: =3*B63 -> 24 | D63: =SUM(E63:K63) -> 23 | E63: 23
A64: Nim | B64: 7 | C64: =3*B64 -> 21 | D64: =SUM(E64:K64) -> 20 | E64: 17 | F64: 3
A65: Arm | B65: 7.5 | C65: =3*B65 -> 22.5 | D65: =SUM(E65:K65) -> 26 | E65: 23 | K65: 3
A66: Total | C66: =SUM(C60:C65) -> 136.5 | D66: =SUM(D60:D65) -> 134 | E66: =SUM(E60:E65) -> 110 | F66: =SUM(F60:F65) -> 3 | G66: =SUM(G60:G65) -> 11 | H66: =SUM(H60:H65) -> 4 | I66: =SUM(I60:I65) -> 0 | J66: =SUM(J60:J65) -> 0 | K66: =SUM(K60:K65) -> 6
C67: =SUM(C59,C66) -> 226.5 | D67: =SUM(D59,D66) -> 236 | E67: =SUM(E55:E65) -> 151 | F67: =SUM(F55:F65) -> 3 | G67: =SUM(G55:G65) -> 19 | H67: =SUM(H55:H65) -> 7 | I67: =SUM(I55:I65) -> 0 | J67: =SUM(J55:J65) -> 38 | K67: =SUM(K55:K65) -> 18
A69: Resource Plan – Sprint 22 *Long weekend 6 Apr - 17 Apr | B69: =SUM(B70:B71) -> 96
A70: ="Capacity SA รวม "&SUM(C88:C91)&" SP" -> Capacity SA รวม 45 SP | B70: =SUM(C82:C85) -> 27
A71: ="Capacity รวม "&SUM(C86:C91)&" SP" -> Capacity รวม 84 SP | B71: =SUM(C87:C92) -> 69
A72: Allocation each project (exclude PE) | B72: =SUM(F93:K93) -> 19
A73: Allocation PE | B73: =B71-B72 -> 50 | C73: =SUM(E87:E92) -> 41
A74: New Point Engine | B74: =E92 -> 10 | C74: 0
A75: Vimi Termination | B75: =F92 | C75: 0
A76: Thana | B76: =G92 | C76: 0
A77: Datamart | B77: =I92 | C77: 0
A78: AWS | B78: =K92 | C78: 0
A79: Adhoc
A80: Dev Support | B80: =C92-D92 -> 2
A81: Name | B81: Availability | C81: Capacity | D81: Total Workload | E81: New PE | F81: VIMI | G81: Thana | H81: Datamart | I81: AWS | J81: Adhoc | K81: Dev Support | L81: Ecom
A82: Aek | B82: 3 | C82: =3*B82 -> 9 | D82: =SUM(E82:L82) -> 14 | E82: 2 | J82: 6 | L82: 6
A83: Aom | B83: 0 | C83: =3*B83 -> 0 | D83: =SUM(E83:L83) -> 0
A84: Zan | B84: 3 | C84: =3*B84 -> 9 | D84: =SUM(E84:L84) -> 0
A85: Jack | B85: 3 | C85: =3*B85 -> 9 | D85: =SUM(E85:L85) -> 0
C86: =SUM(C82:C85) -> 27 | D86: =SUM(D82:D85) -> 14
A87: A | B87: 4 | C87: =3*B87 -> 12 | D87: =SUM(E87:L87) -> 10 | E87: 5 | J87: 5
A88: Mac | B88: 3 | C88: =3*B88 -> 9 | D88: =SUM(E88:L88) -> 9 | F88: 3 | G88: 6
A89: Mai | B89: 4 | C89: =3*B89 -> 12 | D89: =SUM(E89:L89) -> 12 | E89: 12
A90: Mos | B90: 4 | C90: =3*B90 -> 12 | D90: =SUM(E90:L90) -> 8 | E90: 8
A91: Nim | B91: 4 | C91: =3*B91 -> 12 | D91: =SUM(E91:L91) -> 11 | E91: 6 | F91: 5
A92: Arm | B92: 4 | C92: =3*B92 -> 12 | D92: =SUM(E92:L92) -> 10 | E92: 10
A93: Total | C93: =SUM(C87:C92) -> 69 | D93: =SUM(D87:D92) -> 60 | E93: =SUM(E87:E92) -> 41 | F93: =SUM(F87:F92) -> 8 | G93: =SUM(G87:G92) -> 6 | H93: =SUM(H87:H92) -> 0 | I93: =SUM(I87:I92) -> 0 | J93: =SUM(J87:J92) -> 5 | ... L93: =SUM(L87:L92) -> 0
C94: =SUM(C86,C93) -> 96 | D94: =SUM(D86,D93) -> 74 | E94: =SUM(E82:E92) -> 43 | F94: =SUM(F82:F92) -> 8 | G94: =SUM(G82:G92) -> 6 | H94: =SUM(H82:H92) -> 0 | I94: =SUM(I82:I92) -> 0 | J94: =SUM(J82:J92) -> 11 | K94: =SUM(K82:K92) -> 0 | L94: =SUM(L82:L92) -> 6
A96: Resource Plan – Sprint 23 20 Apr - 1 May | B96: =SUM(B97:B98) -> 204
A97: ="Capacity SA รวม "&SUM(C115:C118)&" SP" -> Capacity SA รวม 81 SP | B97: =SUM(C109:C112) -> 84
A98: ="Capacity รวม "&SUM(C113:C118)&" SP" -> Capacity รวม 186 SP | B98: =SUM(C114:C119) -> 120
A99: Allocation each project (exclude PE) | B99: =SUM(F120:K120) -> 44
A100: Allocation PE | B100: =B98-B99 -> 76 | C100: =SUM(E114:E119) -> 80
A101: New Point Engine | C101: 0
A102: Vimi Termination | B102: =F119 | C102: 0
A103: Thana | B103: =G119 | C103: 0
A104: Datamart | B104: =I119 | C104: 0
A105: AWS | B105: =K119 | C105: 0
...

Sheet Billing 2025
A1: Service | B1: Period | C1: Date | D1: Status | E1: Billing | F1: Billing Account | G1: License | H1: Jan | I1: Feb | J1: Mar | K1: Apr | L1: May | M1: Jun | N1: Jul | O1: Aug | P1: Sep | Q1: Oct | R1: Nov | S1: Dec | T1: Jan | U1: Feb | V1: Mar
A2: Miro | B2: Yearly | C2: 46291 | D2: Active | E2: Link | F2: Aek | G2: 5 Accounts | H2: - | I2: - | J2: - | K2: - | L2: - | M2: 60.99 | N2: - | O2: - | P2: 960 | Q2: 182.61 | R2: - | S2: - | T2: - | U2: - | V2: -
A3: Mailchimp | B3: Monthly | C3: 12 | D3: Active | E3: Link | F3: P'Tong, Aek, P'Su | G3: 41 blocks | H3: 520 | I3: 560 | J3: 620 | K3: 620 | L3: 700 | M3: 780 | N3: 896 | O3: 676 | P3: 676 | Q3: 676 | R3: 676 | S3: 676 | T3: 676 | U3: 676 | V3: 676
A4: Github | B4: Monthly | C4: 21 | D4: Active | E4: Link | F4: Aek, A, Pui, Neung, P'Su | H4: 150.99 | I4: 131.18 | J4: 120.39 | K4: 96.09 | L4: 149.76 | M4: 105.12 | N4: 103.78 | O4: 110.78 | P4: 97.66 | Q4: 129.79 | R4: 125.91 | S4: 123.63 | T4: 119.64 | U4: 139.68 | V4: 151.29
A5: Atlassian (Jira) | B5: Monthly | C5: 10 | D5: Active | E5: Link | F5: P'Tong, Aek, A, P'Su | H5: 424.4 | I5: 414.8 | J5: 414.8 | K5: 391.4 | L5: 408.4 | M5: 440.06 | N5: 906.36 | O5: 1028.84 | P5: 994.25 | Q5: 1006.66 | R5: 1269.14 | S5: 1391.2 | T5: 1435.21 | U5: 1179.92 | V5: 1320.71
A6: Uptime_robot | B6: Yearly | C6: 46283 | D6: Active | F6: Pui, Neung | H6: - | I6: - | J6: - | K6: - | L6: - | M6: - | N6: - | O6: - | P6: 648 | Q6: - | R6: - | S6: - | T6: - | U6: - | V6: -
A7: Bitly | B7: Yearly | C7: 46202 | D7: Active | E7: Link | F7: Aek, A | H7: - | I7: - | J7: - | K7: - | L7: - | M7: 96 | N7: - | O7: - | P7: - | Q7: - | R7: - | S7: - | T7: - | U7: - | V7: -
A8: 101domain.com (rbt.one) | B8: Yearly | C8: 46368 | D8: Active | E8: Link | F8: P'Tong, Aek, A, P'Su | H8: - | I8: - | J8: - | K8: - | L8: - | M8: - | N8: - | O8: - | P8: - | Q8: 38.19 | R8: - | S8: - | T8: - | U8: - | V8: -
A9: Cypress | B9: Yearly | C9: 46082 | D9: Cancelled | F9: Aek, A | H9: - | I9: - | J9: 799 | K9: - | L9: - | M9: - | N9: - | O9: - | P9: - | Q9: - | R9: - | S9: - | T9: - | U9: - | V9: -
A10: Smartsheet | B10: Monthly | C10: 4 | D10: Cancelled | F10: P'Hym | G10: - | H10: 27 | I10: 27 | J10: 36 | K10: 36 | L10: 36 | M10: 36 | N10: 36 | O10: 36 | P10: 36 | Q10: 36 | R10: 36 | S10: 36 | T10: - | U10: - | V10: -
A11: LINE OA | B11: Monthly | C11: 1 | D11: Cancelled | F11: P'Hym, Zan | H11: - | I11: - | J11: - | K11: - | L11: - | M11: - | N11: 40 | O11: 40 | P11: - | Q11: - | R11: - | S11: - | T11: - | U11: - | V11: -
A13: Buffer Jira + 50% | H13: =H5*1.5-H5 -> 212.2 | I13: =I5*1.5-I5 -> 207.4 | J13: =J5*1.5-J5 -> 207.4 | K13: =K5*1.5-K5 -> 195.7 | L13: =L5*1.5-L5 -> 204.2 | M13: =M5*1.5-M5 -> 220.03 | N13: =N5*1.5-N5 -> 453.18 | O13: =O5*1.5-O5 -> 514.42 | ... V13: =V5*1.5-V5 -> 660.355
G14: THB | H14: =SUM(H2:H13)*35 -> 46710.65 | I14: =SUM(I2:I13)*35 -> 46913.3 | J14: =SUM(J2:J13)*35 -> 76915.65 | K14: =SUM(K2:K13)*35 -> 46871.65 | L14: =SUM(L2:L13)*35 -> 52442.6 | M14: =SUM(M2:M13)*35 -> 60837 | N14: =SUM(N2:N13)*35 -> 85236.2 | O14: =SUM(O2:O13)*35 -> 84211.4 | ... V14: =SUM(V2:V13)*35 -> 98292.425
A15: JIra Users | K15: 17 | L15: 18 | M15: 24 | N15: 42 | O15: 42 | P15: 39 | Q15: 35 | R15: 40 | S15: 45 | T15: 46 | U15: 41 | V15: 42
A18: Year 2025 | B18: =SUM(K14:V14) -> 1046680.1
A30: GCloud | B30: Monthly | C30: 1 | D30: Active | F30: P'Yo, A | H30: 7567.47 | I30: 7037.99 | J30: 7699.45 | K30: 7753.38 | L30: 9103.31 | M30: 8970.96 | N30: 9092.62 | O30: 13186.36 | P30: 22225.59 | Q30: 10667.12 | R30: 10406.61 | S30: 10888.43 | T30: 11336.8 | U30: 10323.53
A31: GCloud | G31: THB | H31: =H30*35 -> 264861.45 | I31: =I30*35 -> 246329.65 | J31: =J30*35 -> 269480.75 | K31: =K30*35 -> 271368.3 | L31: =L30*35 -> 318615.85 | M31: =M30*35 -> 313983.6 | N31: =N30*35 -> 318241.7 | O31: =O30*35 -> 461522.6 | ... U31: =U30*35 -> 361323.55

Sheet Forecast Billing 2026
A1: Service | B1: Period | C1: Date | D1: Status | E1: Billing Account | F1: License | G1: Apr | H1: May | I1: Jun | J1: Jul | K1: Aug | L1: Sep | M1: Oct | N1: Nov | O1: Dec | P1: Jan | Q1: Feb | R1: Mar
A2: Miro | B2: Yearly | C2: 46291 | D2: Active | E2: Aek | F2: 5 Accounts | G2: - | H2: - | I2: 60.99 | J2: - | K2: - | L2: 960 | M2: 182.61 | N2: - | O2: - | P2: - | Q2: -
A3: Mailchimp | B3: Monthly | C3: 12 | D3: Active | E3: P'Tong, Aek, P'Su | F3: 41 blocks | G3: 676 | H3: 676 | I3: 676 | J3: 676 | K3: 676 | L3: 676 | M3: 676 | N3: 676 | O3: 676 | P3: 676 | Q3: 676 | R3: 676
A4: Github | B4: Monthly | C4: 21 | D4: Active | E4: Aek, A, Pui, Neung | G4: 150 | H4: 150 | I4: 150 | J4: 150 | K4: 150 | L4: 150 | M4: 150 | N4: 150 | O4: 150 | P4: 150 | Q4: 150 | R4: 150
A5: Atlassian | B5: Monthly | C5: 10 | D5: Active | E5: P'Tong, Aek, A, P'Su | F5: 41 users | G5: 1500 | H5: 1500 | I5: 1500 | J5: 1500 | K5: 1500 | L5: 1500 | M5: 1500 | N5: 1500 | O5: 1500 | P5: 1500 | Q5: 1500 | R5: 1500
A6: Uptime_robot | B6: Yearly | C6: 46283 | D6: Active | E6: Pui, Neung | G6: - | H6: - | I6: - | J6: - | K6: - | L6: 648 | M6: - | N6: - | O6: - | P6: - | Q6: - | R6: -
A7: Bitly | B7: Yearly | C7: 46202 | D7: Active | E7: Aek, A | G7: - | H7: - | I7: 96 | J7: - | K7: - | L7: - | M7: - | N7: - | O7: - | P7: - | Q7: - | R7: -
A8: 101domain.com (rbt.one) | B8: Yearly | C8: 46368 | D8: Active | E8: P'Tong, Aek, A, P'Su | G8: - | H8: - | I8: - | J8: - | K8: - | L8: - | M8: 38.19 | N8: - | O8: - | P8: - | Q8: - | R8: -
A9: AIS | B9: Monthly | C9: 23 | D9: Active | E9: 7200 | F9: • 062-308-5741 • 062-308-5731 • 062-308-5725
A10: Cursor AI | B10: Monthly | D10: To Do | F10: 16 | G10: 640 | H10: 640 | I10: 640 | J10: 640 | K10: 640 | L10: 640 | M10: 640 | N10: 640 | O10: 640 | P10: 640 | Q10: 640 | R10: 640
A12: Buffer Jira + 50% | G12: =G5*1.5-G5 -> 750 | H12: =H5*1.5-H5 -> 750 | I12: =I5*1.5-I5 -> 750 | J12: =J5*1.5-J5 -> 750 | K12: =K5*1.5-K5 -> 750 | L12: =L5*1.5-L5 -> 750 | M12: =M5*1.5-M5 -> 750 | N12: =N5*1.5-N5 -> 750 | ... R12: =R5*1.5-R5 -> 750
F13: THB | G13: =SUM(G2:G12)*35 -> 130060 | H13: =SUM(H2:H12)*35 -> 130060 | I13: =SUM(I2:I12)*35 -> 135554.65 | J13: =SUM(J2:J12)*35 -> 130060 | K13: =SUM(K2:K12)*35 -> 130060 | L13: =SUM(L2:L12)*35 -> 186340 | M13: =SUM(M2:M12)*35 -> 137788 | N13: =SUM(N2:N12)*35 -> 130060 | ... R13: =SUM(R2:R12)*35 -> 130060
A14: JIra Users | G14: 50 | H14: 50 | I14: 50 | J14: 50 | K14: 50 | L14: 50 | M14: 50 | N14: 50 | O14: 50 | P14: 50 | Q14: 50 | R14: 50 | T14: 41
A17: Year 2026 | B17: =SUM(G13:R13)+E9 -> 1637422.6
A29: GCloud | B29: Monthly | C29: 1 | D29: Active | E29: P'Yo, A | G29: 7753.38 | H29: 9103.31 | I29: 8970.96 | J29: 9092.62 | K29: 13186.36 | L29: 22225.59 | M29: 10667.12 | N29: 10406.61 | O29: 10888.43 | P29: 11336.8 | Q29: 10323.53
A30: GCloud | F30: THB | G30: =G29*35 -> 271368.3 | H30: =H29*35 -> 318615.85 | I30: =I29*35 -> 313983.6 | J30: =J29*35 -> 318241.7 | K30: =K29*35 -> 461522.6 | L30: =L29*35 -> 777895.65 | M30: =M29*35 -> 373349.2 | N30: =N29*35 -> 364231.35 | ... Q30: =Q29*35 -> 361323.55

Sheet Summarize Sprint 26
A1: Column 1 | B1: Total Stories Point | C1: Total Manhour | D1: Point Done | E1: Manhour Done | F1: Note
A2: 18 May - 29 May
A3: Dev Resource Available | B3: 21 | C3: 427
A4: Meeting Planned | F4: Ref
A5: Additional Meeting | F5: Ref
A6: Deployment | C6: 2 | F6: 2 ครั้ง 1. 3 คน 2. 1 คน
A7: Development Sprint Total | B7: =SUM('Sprint 26'!O:O) -> 425 | C7: =ROUND(SUM('Sprint 26'!U:U)/3600,2) -> 472.17 | D7: =SUMIF('Sprint 26'!J:J, "Done", 'Sprint 26'!O:O) -> 121 | E7: =ROUND(SUMIF('Sprint 26'!J:J, "Done", 'Sprint 26'!U:U)/3600,2) -> 136.17
A9: Ad-hoc Mid Sprint | B9: 0 | C9: =IFERROR(__xludf.DUMMYFUNCTION("ROUND(IFERROR(SUM(FILTER('Sprint 26'!U:U, ('Sprint 26'!Q:Q = ""mid-sprint"")))/3600,0),2)"),0.0) -> 0 | D9: =IFERROR(__xludf.DUMMYFUNCTION("IFERROR(SUM(FILTER('Sprint 26'!O:O, (('Sprint 26'!J:J = ""Done"")) * ('Sprint 26'!Q:Q = ""mid-sprint""))),0)"),0.0) -> 0 | E9: =IFERROR(__xludf.DUMMYFUNCTION("ROUND(IFERROR(SUM(FILTER('Sprint 26'!U:U, (('Sprint 26'!J:J = ""Done"")) * ('Sprint 26'!P:P = ""mid-sprint"")))/3600,0),2)"),0.0) -> 0 | F9: 2 tasks
A10: Requirement changes after refinement? | B10: =IFERROR(__xludf.DUMMYFUNCTION("ROUND(IFERROR(SUM(FILTER('Sprint 26'!U:U, ('Sprint 26'!Q:Q = ""change-request"")))/3600,0),2)"),0.0) -> 0 | D10: =IFERROR(__xludf.DUMMYFUNCTION("IFERROR(SUM(FILTER('Sprint 26'!O:O, (('Sprint 26'!J:J = ""Done"")) * ('Sprint 26'!Q:Q = ""change-request""))),0)"),0.0) -> 0 | E10: =IFERROR(__xludf.DUMMYFUNCTION("ROUND(IFERROR(SUM(FILTER('Sprint 26'!U:U, (('Sprint 26'!J:J = ""Done"")) * ('Sprint 26'!Q:Q = ""change-request"")))/3600,0),2)"),0.0) -> 0 | F10: 0 tasks
A12: Aek | B12: =IFERROR(__xludf.DUMMYFUNCTION("IFERROR(SUM(FILTER('Sprint 26'!O:O, ('Sprint 26'!E:E = ""Aek:Atiphat Nanthachitvanich""))),0)"),33.0) -> 33 | C12: =IFERROR(__xludf.DUMMYFUNCTION("ROUND(IFERROR(SUM(FILTER('Sprint 26'!U:U, ('Sprint 26'!E:E = ""Aek:Atiphat Nanthachitvanich"")))/3600,0),2)"),47.5) -> 47.5 | D12: =IFERROR(__xludf.DUMMYFUNCTION("IFERROR(SUM(FILTER('Sprint 26'!O:O, (('Sprint 26'!J:J = ""Done"")) * ('Sprint 26'!E:E = ""Aek:Atiphat Nanthachitvanich""))),0)"),13.0) -> 13 | E12: =IFERROR(__xludf.DUMMYFUNCTION("ROUND(IFERROR(SUM(FILTER('Sprint 26'!U:U, (('Sprint 26'!J:J = ""Done"")) * ('Sprint 26'!E:E = ""Aek:Atiphat Nanthachitvanich"")))/3600,0),2)"),15.5) -> 15.5
A13: A | B13: =IFERROR(__xludf.DUMMYFUNCTION("IFERROR(SUM(FILTER('Sprint 26'!O:O, ('Sprint 26'!E:E = ""A:Phongthorn""))),0)"),83.0) -> 83 | C13: =IFERROR(__xludf.DUMMYFUNCTION("ROUND(IFERROR(SUM(FILTER('Sprint 26'!U:U, ('Sprint 26'!E:E = ""A:Phongthorn"")))/3600,0),2)"),220.0) -> 220 | D13: =IFERROR(__xludf.DUMMYFUNCTION("IFERROR(SUM(FILTER('Sprint 26'!O:O, (('Sprint 26'!J:J = ""Done"")) * ('Sprint 26'!E:E = ""A:Phongthorn""))),0)"),4.0) -> 4 | E13: =IFERROR(__xludf.DUMMYFUNCTION("ROUND(IFERROR(SUM(FILTER('Sprint 26'!U:U, (('Sprint 26'!J:J = ""Done"")) * ('Sprint 26'!E:E = ""A:Phongthorn"")))/3600,0),2)"),8.0) -> 8
A14: Aom | B14: =IFERROR(__xludf.DUMMYFUNCTION("IFERROR(SUM(FILTER('Sprint 26'!O:O, ('Sprint 26'!E:E = ""Aom: Pornsawan Polnyiem""))),0)"),35.0) -> 35 | C14: =IFERROR(__xludf.DUMMYFUNCTION("ROUND(IFERROR(SUM(FILTER('Sprint 26'!U:U, ('Sprint 26'!E:E = ""Aom: Pornsawan Polnyiem"")))/3600,0),2)"),0.67) -> 0.67 | D14: =IFERROR(__xludf.DUMMYFUNCTION("IFERROR(SUM(FILTER('Sprint 26'!O:O, (('Sprint 26'!J:J = ""Done"")) * ('Sprint 26'!E:E = ""Aom: Pornsawan Polnyiem""))),0)"),17.0) -> 17 | E14: =IFERROR(__xludf.DUMMYFUNCTION("ROUND(IFERROR(SUM(FILTER('Sprint 26'!U:U, (('Sprint 26'!J:J = ""Done"")) * ('Sprint 26'!E:E = ""Aom: Pornsawan Polnyiem"")))/3600,0),2)"),0.67) -> 0.67
A15: Zan | B15: =IFERROR(__xludf.DUMMYFUNCTION("IFERROR(SUM(FILTER('Sprint 26'!O:O, ('Sprint 26'!E:E = ""Zan : Isarapong Bulan""))),0)"),17.0) -> 17 | C15: =IFERROR(__xludf.DUMMYFUNCTION("ROUND(IFERROR(SUM(FILTER('Sprint 26'!U:U, ('Sprint 26'!E:E = ""Zan : Isarapong Bulan"")))/3600,0),2)"),0.0) -> 0 | D15: =IFERROR(__xludf.DUMMYFUNCTION("IFERROR(SUM(FILTER('Sprint 26'!O:O, (('Sprint 26'!J:J = ""Done"")) * ('Sprint 26'!E:E = ""Zan : Isarapong Bulan""))),0)"),0.0) -> 0 | E15: =IFERROR(__xludf.DUMMYFUNCTION("ROUND(IFERROR(SUM(FILTER('Sprint 26'!U:U, (('Sprint 26'!J:J = ""Done"")) * ('Sprint 26'!E:E = ""Zan : Isarapong Bulan"")))/3600,0),2)"),0.0) -> 0
A16: Mai | B16: =IFERROR(__xludf.DUMMYFUNCTION("IFERROR(SUM(FILTER('Sprint 26'!O:O, ('Sprint 26'!E:E = ""Mai:Sateta Abvanawong""))),0)"),32.0) -> 32 | C16: =IFERROR(__xludf.DUMMYFUNCTION("ROUND(IFERROR(SUM(FILTER('Sprint 26'!U:U, ('Sprint 26'!E:E = ""Mai:Sateta Abvanawong"")))/3600,0),2)"),52.0) -> 52 | D16: =IFERROR(__xludf.DUMMYFUNCTION("IFERROR(SUM(FILTER('Sprint 26'!O:O, (('Sprint 26'!J:J = ""Done"")) * ('Sprint 26'!E:E = ""Mai:Sateta Abvanawong""))),0)"),11.0) -> 11 | E16: =IFERROR(__xludf.DUMMYFUNCTION("ROUND(IFERROR(SUM(FILTER('Sprint 26'!U:U, (('Sprint 26'!J:J = ""Done"")) * ('Sprint 26'!E:E = ""Mai:Sateta Abvanawong""))),0)/3600,2)"),28.0) -> 28
A17: Mac | B17: =IFERROR(__xludf.DUMMYFUNCTION("IFERROR(SUM(FILTER('Sprint 26'!O:O, ('Sprint 26'!E:E = ""Mac: Jarupong Pawichpongkul""))),0)"),56.0) -> 56 | C17: =IFERROR(__xludf.DUMMYFUNCTION("ROUND(IFERROR(SUM(FILTER('Sprint 26'!U:U, ('Sprint 26'!E:E = ""Mac: Jarupong Pawichpongkul"")))/3600,0),2)"),56.0) -> 56 | D17: =IFERROR(__xludf.DUMMYFUNCTION("IFERROR(SUM(FILTER('Sprint 26'!O:O, (('Sprint 26'!J:J = ""Done"")) * ('Sprint 26'!E:E = ""Mac: Jarupong Pawichpongkul""))),0)"),5.0) -> 5 | E17: =IFERROR(__xludf.DUMMYFUNCTION("ROUND(IFERROR(SUM(FILTER('Sprint 26'!U:U, (('Sprint 26'!J:J = ""Done"")) * ('Sprint 26'!E:E = ""Mac: Jarupong Pawichpongkul"")))/3600,0),2)"),0.0) -> 0
A18: Mos | B18: =IFERROR(__xludf.DUMMYFUNCTION("IFERROR(SUM(FILTER('Sprint 26'!O:O, ('Sprint 26'!E:E = ""Moss : Kittapath Sangvikukit""))),0)"),51.0) -> 51 | C18: =IFERROR(__xludf.DUMMYFUNCTION("ROUND(IFERROR(SUM(FILTER('Sprint 26'!U:U, ('Sprint 26'!E:E = ""Moss : Kittapath Sangvikukit"")))/3600,0),2)"),86.0) -> 86 | D18: =IFERROR(__xludf.DUMMYFUNCTION("IFERROR(SUM(FILTER('Sprint 26'!O:O, (('Sprint 26'!J:J = ""Done"")) * ('Sprint 26'!E:E = ""Moss : Kittapath Sangvikukit""))),0)"),39.0) -> 39 | E18: =IFERROR(__xludf.DUMMYFUNCTION("ROUND(IFERROR(SUM(FILTER('Sprint 26'!U:U, (('Sprint 26'!J:J = ""Done"")) * ('Sprint 26'!E:E = ""Moss : Kittapath Sangvikukit"")))/3600,0),2)"),74.0) -> 74
A19: Jack | B19: =IFERROR(__xludf.DUMMYFUNCTION("IFERROR(SUM(FILTER('Sprint 26'!O:O, ('Sprint 26'!E:E = ""Jack: Warin Kesorn""))),0)"),12.0) -> 12 | C19: =IFERROR(__xludf.DUMMYFUNCTION("ROUND(IFERROR(SUM(FILTER('Sprint 26'!U:U, ('Sprint 26'!E:E = ""Jack: Warin Kesorn"")))/3600,0),2)"),0.0) -> 0 | D19: =IFERROR(__xludf.DUMMYFUNCTION("IFERROR(SUM(FILTER('Sprint 26'!O:O, (('Sprint 26'!J:J = ""Done"")) * ('Sprint 26'!E:E = ""Jack: Warin Kesorn""))),0)"),9.0) -> 9 | E19: =IFERROR(__xludf.DUMMYFUNCTION("ROUND(IFERROR(SUM(FILTER('Sprint 26'!U:U, (('Sprint 26'!J:J = ""Done"")) * ('Sprint 26'!E:E = ""Jack: Warin Kesorn"")))/3600,0),2)"),0.0) -> 0
A20: Nim | B20: =IFERROR(__xludf.DUMMYFUNCTION("IFERROR(SUM(FILTER('Sprint 26'!O:O, ('Sprint 26'!E:E = ""Nim : muthita munmueang""))),0)"),41.0) -> 41 | C20: =IFERROR(__xludf.DUMMYFUNCTION("ROUND(IFERROR(SUM(FILTER('Sprint 26'!U:U, ('Sprint 26'!E:E = ""Nim : muthita munmueang"")))/3600,0),2)"),8.0) -> 8 | D20: =IFERROR(__xludf.DUMMYFUNCTION("IFERROR(SUM(FILTER('Sprint 26'!O:O, (('Sprint 26'!J:J = ""Done"")) * ('Sprint 26'!E:E = ""Nim : muthita munmueang""))),0)"),12.0) -> 12 | E20: =IFERROR(__xludf.DUMMYFUNCTION("ROUND(IFERROR(SUM(FILTER('Sprint 26'!U:U, (('Sprint 26'!J:J = ""Done"")) * ('Sprint 26'!E:E = ""Nim : muthita munmueang"")))/3600,0),2)"),8.0) -> 8
A21: Arm | B21: =IFERROR(__xludf.DUMMYFUNCTION("IFERROR(SUM(FILTER('Sprint 26'!O:O, ('Sprint 26'!E:E = ""Arm:Worawat Chotipongchoawalit""))),0)"),64.0) -> 64 | C21: =IFERROR(__xludf.DUMMYFUNCTION("ROUND(IFERROR(SUM(FILTER('Sprint 26'!U:U, ('Sprint 26'!E:E = ""Arm:Worawat Chotipongchoawalit"")))/3600,0),2)"),0.0) -> 0 | D21: =IFERROR(__xludf.DUMMYFUNCTION("IFERROR(SUM(FILTER('Sprint 26'!O:O, (('Sprint 26'!J:J = ""Done"")) * ('Sprint 26'!E:E = ""Arm:Worawat Chotipongchoawalit""))),0)"),10.0) -> 10 | E21: =IFERROR(__xludf.DUMMYFUNCTION("ROUND(IFERROR(SUM(FILTER('Sprint 26'!U:U, (('Sprint 26'!J:J = ""Done"")) * ('Sprint 26'!E:E = ""Arm:Worawat Chotipongchoawalit"")))/3600,0),2)"),0.0) -> 0

Sheet Sprint 26
A1: Issue Type | B1: Issue key | C1: Issue id | D1: Summary | E1: Assignee | F1: Assignee Id | G1: Reporter | H1: Reporter Id | I1: Priority | J1: Status | K1: Resolution | L1: Created | M1: Updated | N1: Due date | O1: Custom field (Story Points) | P1: Labels | Q1: Labels | R1: Labels | S1: Labels | T1: Labels | U1: Original estimate | V1: Sprint | W1: Sprint | X1: Sprint | Y1: Sprint | Z1: Sprint | AA1: Sprint | AB1: Sprint | AC1: Sprint | AD1: Sprint | AE1: Sprint | AF1: Sprint | AG1: Sprint | AH1: Sprint
A2: Sub-task | B2: DPE-700 | C2: 54668 | D2: Test execution | E2: Plai Thanaporn Rimnong-ang | F2: 62c2a5acefb17d6ce62e41bf | G2: Aom: Pornsawan Polnyiem | H2: 5d2ed694a666040c85096e17 | I2: Medium | J2: To Do | L2: 12/Jun/26 4:33 PM | M2: 12/Jun/26 4:33 PM | V2: [Dev][RD][New PE] Sprint 24 | W2: [Dev][RD][New PE] Sprint 25 | X2: [Dev][RD][New PE] Sprint 26
A3: Sub-task | B3: DPE-699 | C3: 54667 | D3: Create test case | E3: Plai Thanaporn Rimnong-ang | F3: 62c2a5acefb17d6ce62e41bf | G3: Aom: Pornsawan Polnyiem | H3: 5d2ed694a666040c85096e17 | I3: Medium | J3: To Do | L3: 12/Jun/26 4:33 PM | M3: 12/Jun/26 4:33 PM | V3: [Dev][RD][New PE] Sprint 24 | W3: [Dev][RD][New PE] Sprint 25 | X3: [Dev][RD][New PE] Sprint 26
A4: Sub-task | B4: DPE-698 | C4: 54666 | D4: Test execution | E4: Plai Thanaporn Rimnong-ang | F4: 62c2a5acefb17d6ce62e41bf | G4: Aom: Pornsawan Polnyiem | H4: 5d2ed694a666040c85096e17 | I4: Medium | J4: To Do | L4: 12/Jun/26 4:33 PM | M4: 12/Jun/26 4:33 PM | V4: [Dev][RD][New PE] Sprint 24 | W4: [Dev][RD][New PE] Sprint 25 | X4: [Dev][RD][New PE] Sprint 26
A5: Sub-task | B5: DPE-697 | C5: 54665 | D5: Create test case | E5: Plai Thanaporn Rimnong-ang | F5: 62c2a5acefb17d6ce62e41bf | G5: Aom: Pornsawan Polnyiem | H5: 5d2ed694a666040c85096e17 | I5: Medium | J5: To Do | L5: 12/Jun/26 4:33 PM | M5: 12/Jun/26 4:33 PM | V5: [Dev][RD][New PE] Sprint 24 | W5: [Dev][RD][New PE] Sprint 25 | X5: [Dev][RD][New PE] Sprint 26
A6: Sub-task | B6: DPE-696 | C6: 54664 | D6: Test execution | E6: Plai Thanaporn Rimnong-ang | F6: 62c2a5acefb17d6ce62e41bf | G6: Aom: Pornsawan Polnyiem | H6: 5d2ed694a666040c85096e17 | I6: Medium | J6: To Do | L6: 12/Jun/26 4:33 PM | M6: 12/Jun/26 4:33 PM | V6: [Dev][RD][New PE] Sprint 22 | W6: [Dev][RD][New PE] Sprint 23 | X6: [Dev][RD][New PE] Sprint 24 | Y6: [Dev][RD][New PE] Sprint 25 | Z6: [Dev][RD][New PE] Sprint 26
A7: Sub-task | B7: DPE-695 | C7: 54663 | D7: Create test case | E7: Plai Thanaporn Rimnong-ang | F7: 62c2a5acefb17d6ce62e41bf | G7: Aom: Pornsawan Polnyiem | H7: 5d2ed694a666040c85096e17 | I7: Medium | J7: To Do | L7: 12/Jun/26 4:33 PM | M7: 12/Jun/26 4:33 PM | V7: [Dev][RD][New PE] Sprint 22 | W7: [Dev][RD][New PE] Sprint 23 | X7: [Dev][RD][New PE] Sprint 24 | Y7: [Dev][RD][New PE] Sprint 25 | Z7: [Dev][RD][New PE] Sprint 26
A8: Sub-task | B8: DPE-694 | C8: 54662 | D8: Test execution | E8: Plai Thanaporn Rimnong-ang | F8: 62c2a5acefb17d6ce62e41bf | G8: Jack: Warin Kesorn | H8: 61a98e8e744c4d00693281d1 | I8: Medium | J8: Done | L8: 12/Jun/26 4:17 PM | M8: 12/Jun/26 4:18 PM | V8: [Dev][RD][New PE] Sprint 26
A9: Sub-task | B9: DPE-693 | C9: 54661 | D9: Create test case | E9: Plai Thanaporn Rimnong-ang | F9: 62c2a5acefb17d6ce62e41bf | G9: Jack: Warin Kesorn | H9: 61a98e8e744c4d00693281d1 | I9: Medium | J9: Done | L9: 12/Jun/26 4:17 PM | M9: 12/Jun/26 4:18 PM | V9: [Dev][RD][New PE] Sprint 26
A10: Story | B10: DEVRDSUP-638 | C10: 54659 | D10: [SUP-734][Need support] ดึง Point จาก User คืน | E10: Aek:Atiphat Nanthachitvanich | F10: 5d48155f5b8ea70c7e4f1b0f | G10: Abhinaf Singh | H10: 712020:a81c99dd-d5cd-44bd-950a-32f4ff7d56ac | I10: Highest | J10: Done | L10: 12/Jun/26 3:41 PM | M10: 12/Jun/26 4:28 PM | N10: 12/Jun/26 12:00 AM | O10: 1 | P10: hop | Q10: reverseTXN | U10: 1800 | V10: [Dev][All Project] Sprint 26
A11: Story | B11: DPE-692 | C11: 54648 | D11: [Dev][RD][PE Middleware] Enhance Get Offer List - Add Offer Type Filter | E11: Arm:Worawat Chotipongchoawalit | F11: 712020:2195d849-5cdb-4ec8-866f-e82a3528bff7 | G11: Jack: Warin Kesorn | H11: 61a98e8e744c4d00693281d1 | I11: Medium | J11: Done | L11: 12/Jun/26 10:49 AM | M11: 12/Jun/26 4:18 PM | P11: point-engine-proxy | V11: [Dev][RD][New PE] Sprint 26
A12: Bug | B12: DPE-689 | C12: 54599 | D12: [S4][RR BOF] Offer name is updated when update the general details | E12: Arm:Worawat Chotipongchoawalit | F12: 712020:2195d849-5cdb-4ec8-866f-e82a3528bff7 | G12: Plai Thanaporn Rimnong-ang | H12: 62c2a5acefb17d6ce62e41bf | I12: Medium | J12: Closed | L12: 10/Jun/26 5:05 PM | M12: 11/Jun/26 1:34 PM | V12: [Dev][RD][New PE] Sprint 26
A13: Sub-task | B13: DPE-688 | C13: 54595 | D13: Test execution | E13: Plai Thanaporn Rimnong-ang | F13: 62c2a5acefb17d6ce62e41bf | G13: Aom: Pornsawan Polnyiem | H13: 5d2ed694a666040c85096e17 | I13: Medium | J13: Done | L13: 10/Jun/26 4:33 PM | M13: 11/Jun/26 1:34 PM | V13: [Dev][RD][New PE] Sprint 26
A14: Sub-task | B14: DPE-687 | C14: 54594 | D14: Create test case | E14: Plai Thanaporn Rimnong-ang | F14: 62c2a5acefb17d6ce62e41bf | G14: Aom: Pornsawan Polnyiem | H14: 5d2ed694a666040c85096e17 | I14: Medium | J14: Done | L14: 10/Jun/26 4:33 PM | M14: 10/Jun/26 4:48 PM | V14: [Dev][RD][New PE] Sprint 26
A15: Sub-task | B15: DPE-686 | C15: 54582 | D15: [QA] Test execution | E15: Plai Thanaporn Rimnong-ang | F15: 62c2a5acefb17d6ce62e41bf | G15: Plai Thanaporn Rimnong-ang | H15: 62c2a5acefb17d6ce62e41bf | I15: Medium | J15: Done | L15: 10/Jun/26 3:48 PM | M15: 11/Jun/26 2:59 PM | V15: [Dev][RD][New PE] Sprint 22 | W15: [Dev][RD][New PE] Sprint 23 | X15: [Dev][RD][New PE] Sprint 24 | Y15: [Dev][RD][New PE] Sprint 25 | Z15: [Dev][RD][New PE] Sprint 26
A16: Story | B16: RDTHANA-518 | C16: 54577 | D16: [SA][RD][TDM] Prepare access control callback request example | E16: Zan : Isarapong Bulan | F16: 5d4814e9da0c4d0c789a4bb7 | G16: Zan : Isarapong Bulan | H16: 5d4814e9da0c4d0c789a4bb7 | I16: Medium | J16: In Review | L16: 10/Jun/26 1:46 PM | M16: 10/Jun/26 1:47 PM | O16: 1 | V16: [Dev][RD][Thana] Sprint 26
A17: Story | B17: DEVRDSUP-633 | C17: 54566 | D17: [SUP-726][SUB] รบกวนออกแพ็กเกจ ปรับเป็น PAID(Confirmed) เรียบร้อย // Order ID: 20260608-0004808 | E17: Aom: Pornsawan Polnyiem | F17: 5d2ed694a666040c85096e17 | G17: Thanakrit Chanthaworn | H17: 712020:3fc982cb-c268-4f1d-9265-d3dd8fb08304 | I17: Medium | J17: Done | L17: 09/Jun/26 6:03 PM | M17: 12/Jun/26 2:00 PM | N17: 12/Jun/26 12:00 AM | O17: 1 | P17: bts | Q17: prod-issue | R17: sub | U17: 600 | V17: [Dev][All Project] Sprint 26
A18: Story | B18: RDAPS-494 | C18: 54557 | D18: [SA][RD] Prepare Callback payload | G18: Zan : Isarapong Bulan | H18: 5d4814e9da0c4d0c789a4bb7 | I18: Medium | J18: To Do | L18: 09/Jun/26 2:52 PM | M18: 09/Jun/26 2:52 PM | V18: [Dev][All Project] Sprint 26
A19: Story | B19: RDAPS-493 | C19: 54556 | D19: [SA][RD] Prepare task sprint #27 - Zan | E19: Zan : Isarapong Bulan | F19: 5d4814e9da0c4d0c789a4bb7 | G19: Zan : Isarapong Bulan | H19: 5d4814e9da0c4d0c789a4bb7 | I19: Medium | J19: In Progress | L19: 09/Jun/26 2:50 PM | M19: 11/Jun/26 9:46 AM | O19: 8 | V19: [Dev][All Project] Sprint 26
A20: Story | B20: DEV-16 | C20: 54555 | D20: [SA][RD][Tech Debt][HRS][DB] Coordinate Staging DB Instance Type Upgrade for Pre-Production Validation | E20: Zan : Isarapong Bulan | F20: 5d4814e9da0c4d0c789a4bb7 | G20: Aek:Atiphat Nanthachitvanich | H20: 5d48155f5b8ea70c7e4f1b0f | I20: Medium | J20: To Do | L20: 09/Jun/26 2:37 PM | M20: 09/Jun/26 3:11 PM | P20: DB | Q20: HRS | R20: Staging | S20: TechDebt | V20: [Dev][RD][TechDebt] Sprint 26
A21: Sub-task | B21: DEV-15 | C21: 54542 | D21: [QA] Test Execution - UAT | E21: Max (QA) : Surawut Sae-nim | F21: 62d4e007098e73c4e5ee0d8d | G21: Max (QA) : Surawut Sae-nim | H21: 62d4e007098e73c4e5ee0d8d | I21: Medium | J21: In Progress | L21: 08/Jun/26 6:11 PM | M21: 08/Jun/26 6:11 PM | V21: [Dev][All Project] Sprint 24 | W21: [Dev][RD][TechDebt] Sprint 25 | X21: [Dev][RD][TechDebt] Sprint 26
A22: Sub-task | B22: DEV-14 | C22: 54540 | D22: [QA] Test Execution - STG | E22: Max (QA) : Surawut Sae-nim | F22: 62d4e007098e73c4e5ee0d8d | G22: Max (QA) : Surawut Sae-nim | H22: 62d4e007098e73c4e5ee0d8d | I22: Medium | J22: Done | L22: 08/Jun/26 6:03 PM | M22: 08/Jun/26 6:10 PM | V22: [Dev][All Project] Sprint 24 | W22: [Dev][RD][TechDebt] Sprint 25 | X22: [Dev][RD][TechDebt] Sprint 26
A23: Sub-task | B23: DPE-680 | C23: 54539 | D23: Test execution | E23: Plai Thanaporn Rimnong-ang | F23: 62c2a5acefb17d6ce62e41bf | G23: Aom: Pornsawan Polnyiem | H23: 5d2ed694a666040c85096e17 | I23: Medium | J23: Done | L23: 08/Jun/26 6:01 PM | M23: 09/Jun/26 4:28 PM | V23: [Dev][RD][New PE] Sprint 24 | W23: [Dev][RD][New PE] Sprint 25 | X23: [Dev][RD][New PE] Sprint 26
A24: Sub-task | B24: DPE-679 | C24: 54538 | D24: Create test case | E24: Plai Thanaporn Rimnong-ang | F24: 62c2a5acefb17d6ce62e41bf | G24: Aom: Pornsawan Polnyiem | H24: 5d2ed694a666040c85096e17 | I24: Medium | J24: Done | L24: 08/Jun/26 6:01 PM | M24: 08/Jun/26 6:01 PM | V24: [Dev][RD][New PE] Sprint 24 | W24: [Dev][RD][New PE] Sprint 25 | X24: [Dev][RD][New PE] Sprint 26
A25: Sub-task | B25: DPE-678 | C25: 54537 | D25: Test execution | E25: Plai Thanaporn Rimnong-ang | F25: 62c2a5acefb17d6ce62e41bf | G25: Aom: Pornsawan Polnyiem | H25: 5d2ed694a666040c85096e17 | I25: Medium | J25: Done | L25: 08/Jun/26 6:01 PM | M25: 09/Jun/26 3:37 PM | V25: [Dev][RD][New PE] Sprint 24 | W25: [Dev][RD][New PE] Sprint 25 | X25: [Dev][RD][New PE] Sprint 26
A26: Sub-task | B26: DPE-677 | C26: 54536 | D26: Create test case | E26: Plai Thanaporn Rimnong-ang | F26: 62c2a5acefb17d6ce62e41bf | G26: Aom: Pornsawan Polnyiem | H26: 5d2ed694a666040c85096e17 | I26: Medium | J26: Done | L26: 08/Jun/26 6:01 PM | M26: 08/Jun/26 6:01 PM | V26: [Dev][RD][New PE] Sprint 24 | W26: [Dev][RD][New PE] Sprint 25 | X26: [Dev][RD][New PE] Sprint 26
A27: Sub-task | B27: DEVRDSUP-631 | C27: 54535 | D27: [QA] Retest - STG | G27: Max (QA) : Surawut Sae-nim | H27: 62d4e007098e73c4e5ee0d8d | I27: Medium | J27: To Do | L27: 08/Jun/26 5:58 PM | M27: 08/Jun/26 6:02 PM | V27: [Dev][All Project] Sprint 24 | W27: [Dev][All Project] Sprint 25 | X27: [Dev][All Project] Sprint 26
A28: Sub-task | B28: DPE-676 | C28: 54534 | D28: Test execution | E28: Plai Thanaporn Rimnong-ang | F28: 62c2a5acefb17d6ce62e41bf | G28: Aom: Pornsawan Polnyiem | H28: 5d2ed694a666040c85096e17 | I28: Medium | J28: Done | L28: 08/Jun/26 5:32 PM | M28: 08/Jun/26 5:32 PM | V28: [Dev][RD][New PE] Sprint 22 | W28: [Dev][RD][New PE] Sprint 23 | X28: [Dev][RD][New PE] Sprint 24 | Y28: [Dev][RD][New PE] Sprint 25 | Z28: [Dev][RD][New PE] Sprint 26
A29: Sub-task | B29: DPE-675 | C29: 54533 | D29: Create test case | E29: Plai Thanaporn Rimnong-ang | F29: 62c2a5acefb17d6ce62e41bf | G29: Aom: Pornsawan Polnyiem | H29: 5d2ed694a666040c85096e17 | I29: Medium | J29: Done | L29: 08/Jun/26 5:32 PM | M29: 08/Jun/26 5:32 PM | V29: [Dev][RD][New PE] Sprint 22 | W29: [Dev][RD][New PE] Sprint 23 | X29: [Dev][RD][New PE] Sprint 24 | Y29: [Dev][RD][New PE] Sprint 25 | Z29: [Dev][RD][New PE] Sprint 26
A30: Story | B30: DEVRDSUP-630 | C30: 54527 | D30: [SUP-722]0880069567996 Line Pay (บัตรใหม่) แต่ระบบหลังบ้านเป็น RC ค่ะ จึงทำให้ลูกค้าไม่สามารถเติมเที่ยวเข้าบัตรได้ | E30: Aek:Atiphat Nanthachitvanich | F30: 5d48155f5b8ea70c7e4f1b0f | G30: Thanakrit Chanthaworn | H30: 712020:3fc982cb-c268-4f1d-9265-d3dd8fb08304 | I30: Medium | J30: Done | L30: 08/Jun/26 5:21 PM | M30: 12/Jun/26 2:00 PM | N30: 11/Jun/26 12:00 AM | O30: 1 | P30: prod-issue | Q30: sub | U30: 1800 | V30: [Dev][All Project] Sprint 26
A31: Story | B31: DEVRDSUP-629 | C31: 54520 | D31: [SUP-721][Access SSO backoffice] Request to create new user N'Nampheung | E31: Aek:Atiphat Nanthachitvanich | F31: 5d48155f5b8ea70c7e4f1b0f | G31: Thanakrit Chanthaworn | H31: 712020:3fc982cb-c268-4f1d-9265-d3dd8fb08304 | I31: Highest | J31: Done | L31: 08/Jun/26 2:35 PM | M31: 12/Jun/26 2:00 PM | N31: 08/Jun/26 12:00 AM | O31: 1 | P31: BURequest | Q31: sso-backoffice | R31: sso-user | U31: 600 | V31: [Dev][All Project] Sprint 26
A32: Story | B32: DEVRDECOM-254 | C32: 54514 | D32: [DEV][RD][Ecom][Gustron][SA] Impact analysis - guest checkout without Rabbit Connect login | E32: Aek:Atiphat Nanthachitvanich | F32: 5d48155f5b8ea70c7e4f1b0f | G32: Aek:Atiphat Nanthachitvanich | H32: 5d48155f5b8ea70c7e4f1b0f | I32: Medium | J32: In Progress | L32: 08/Jun/26 1:16 PM | M32: 12/Jun/26 9:24 AM | O32: 2 | P32: Gustron | Q32: impact-analysis | R32: SA | V32: [Dev][RD][Ecom] Sprint 26
A33: Sub-task | B33: DPE-674 | C33: 54507 | D33: Test execution | E33: Plai Thanaporn Rimnong-ang | F33: 62c2a5acefb17d6ce62e41bf | G33: Aom: Pornsawan Polnyiem | H33: 5d2ed694a666040c85096e17 | I33: Medium | J33: Done | L33: 08/Jun/26 10:49 AM | M33: 08/Jun/26 11:20 AM | V33: [Dev][RD][New PE] Sprint 26
A34: Sub-task | B34: DPE-673 | C34: 54506 | D34: Create test case | E34: Plai Thanaporn Rimnong-ang | F34: 62c2a5acefb17d6ce62e41bf | G34: Aom: Pornsawan Polnyiem | H34: 5d2ed694a666040c85096e17 | I34: Medium | J34: Done | L34: 08/Jun/26 10:49 AM | M34: 08/Jun/26 11:20 AM | V34: [Dev][RD][New PE] Sprint 26
A35: Story | B35: DPE-672 | C35: 54505 | D35: [Dev][RD][PE Proxy Scheduler] Implement Discord notification after each command processed | E35: Arm:Worawat Chotipongchoawalit | F35: 712020:2195d849-5cdb-4ec8-866f-e82a3528bff7 | G35: Aom: Pornsawan Polnyiem | H35: 5d2ed694a666040c85096e17 | I35: Medium | J35: Ready To Test | L35: 08/Jun/26 10:38 AM | M35: 12/Jun/26 10:00 AM | P35: point-engine-proxy-scheduler | V35: [Dev][RD][New PE] Sprint 26
A36: Sub-task | B36: DPE-671 | C36: 54503 | D36: [QA] Test execution | E36: Plai Thanaporn Rimnong-ang | F36: 62c2a5acefb17d6ce62e41bf | G36: Plai Thanaporn Rimnong-ang | H36: 62c2a5acefb17d6ce62e41bf | I36: Medium | J36: Done | L36: 08/Jun/26 9:48 AM | M36: 08/Jun/26 9:49 AM | V36: [Dev][RD][New PE] Sprint 22 | W36: [Dev][RD][New PE] Sprint 23 | X36: [Dev][RD][New PE] Sprint 24 | Y36: [Dev][RD][New PE] Sprint 25 | Z36: [Dev][RD][New PE] Sprint 26
A37: Sub-task | B37: DPE-670 | C37: 54496 | D37: Test execution | E37: Plai Thanaporn Rimnong-ang | F37: 62c2a5acefb17d6ce62e41bf | G37: Aom: Pornsawan Polnyiem | H37: 5d2ed694a666040c85096e17 | I37: Medium | J37: Done | L37: 06/Jun/26 1:31 AM | M37: 08/Jun/26 3:06 PM | V37: [Dev][RD][New PE] Sprint 22 | W37: [Dev][RD][New PE] Sprint 23 | X37: [Dev][RD][New PE] Sprint 24 | Y37: [Dev][RD][New PE] Sprint 25 | Z37: [Dev][RD][New PE] Sprint 26
A38: Sub-task | B38: DPE-669 | C38: 54495 | D38: Create test case | E38: Plai Thanaporn Rimnong-ang | F38: 62c2a5acefb17d6ce62e41bf | G38: Aom: Pornsawan Polnyiem | H38: 5d2ed694a666040c85096e17 | I38: Medium | J38: Done | L38: 06/Jun/26 1:31 AM | M38: 06/Jun/26 1:31 AM | V38: [Dev][RD][New PE] Sprint 22 | W38: [Dev][RD][New PE] Sprint 23 | X38: [Dev][RD][New PE] Sprint 24 | Y38: [Dev][RD][New PE] Sprint 25 | Z38: [Dev][RD][New PE] Sprint 26
A39: Story | B39: DEVRDSUP-627 | C39: 54488 | D39: [SUP-719][Turtle][PL] Request to resend failed point issue TXN to resolve user's complain. The point issue TXN from POS was failed. | E39: Aek:Atiphat Nanthachitvanich | F39: 5d48155f5b8ea70c7e4f1b0f | G39: Abhinaf Singh | H39: 712020:a81c99dd-d5cd-44bd-950a-32f4ff7d56ac | I39: Medium | J39: Done | L39: 05/Jun/26 3:47 PM | M39: 12/Jun/26 2:00 PM | N39: 09/Jun/26 12:00 AM | O39: 1 | P39: partner-loyalty | Q39: turtle | U39: 900 | V39: [Dev][All Project] Sprint 26
A40: Bug | B40: DEVRDSUP-626 | C40: 54483 | D40: [SUP-712]Review of Turtle Coupon Data, missing coupon data on 21&24 May 2026. | E40: Aom: Pornsawan Polnyiem | F40: 5d2ed694a666040c85096e17 | G40: Abhinaf Singh | H40: 712020:a81c99dd-d5cd-44bd-950a-32f4ff7d56ac | I40: Highest | J40: RETESTING | L40: 05/Jun/26 11:39 AM | M40: 12/Jun/26 1:04 PM | N40: 12/Jun/26 12:00 AM | P40: data | Q40: sub | R40: turtle | V40: [Dev][All Project] Sprint 26
A41: Sub-task | B41: DPE-667 | C41: 54482 | D41: Test execution | E41: Plai Thanaporn Rimnong-ang | F41: 62c2a5acefb17d6ce62e41bf | G41: Aom: Pornsawan Polnyiem | H41: 5d2ed694a666040c85096e17 | I41: Medium | J41: Done | L41: 05/Jun/26 11:33 AM | M41: 05/Jun/26 11:34 AM | V41: [Dev][RD][New PE] Sprint 25 | W41: [Dev][RD][New PE] Sprint 26
A42: Sub-task | B42: DPE-666 | C42: 54481 | D42: Test execution | E42: Plai Thanaporn Rimnong-ang | F42: 62c2a5acefb17d6ce62e41bf | G42: Aom: Pornsawan Polnyiem | H42: 5d2ed694a666040c85096e17 | I42: Medium | J42: Done | L42: 05/Jun/26 11:33 AM | M42: 05/Jun/26 11:34 AM | V42: [Dev][RD][New PE] Sprint 25 | W42: [Dev][RD][New PE] Sprint 26
A43: Sub-task | B43: DPE-665 | C43: 54480 | D43: Create test case | E43: Plai Thanaporn Rimnong-ang | F43: 62c2a5acefb17d6ce62e41bf | G43: Aom: Pornsawan Polnyiem | H43: 5d2ed694a666040c85096e17 | I43: Medium | J43: Done | L43: 05/Jun/26 11:33 AM | M43: 05/Jun/26 11:34 AM | V43: [Dev][RD][New PE] Sprint 25 | W43: [Dev][RD][New PE] Sprint 26
A44: Sub-task | B44: DPE-664 | C44: 54479 | D44: Create test case | E44: Plai Thanaporn Rimnong-ang | F44: 62c2a5acefb17d6ce62e41bf | G44: Aom: Pornsawan Polnyiem | H44: 5d2ed694a666040c85096e17 | I44: Medium | J44: Done | L44: 05/Jun/26 11:33 AM | M44: 05/Jun/26 11:34 AM | V44: [Dev][RD][New PE] Sprint 25 | W44: [Dev][RD][New PE] Sprint 26
A45: Bug | B45: DPE-663 | C45: 54477 | D45: [S3][NPE] Unable to credit/debit points when using an offer containing special characters | E45: Moss : Kittapath Sangvikukit | F45: 712020:b33baa03-2b29-4662-9923-dbdc2bbf980d | G45: Plai Thanaporn Rimnong-ang | H45: 62c2a5acefb17d6ce62e41bf | I45: Medium | J45: Solution Proposal Pending | L45: 05/Jun/26 10:36 AM | M45: 05/Jun/26 1:56 PM | V45: [Dev][RD][New PE] Sprint 26
A46: Story | B46: DPE-662 | C46: 54473 | D46: [Dev][RD][BOF] Improve product creation | E46: Arm:Worawat Chotipongchoawalit | F46: 712020:2195d849-5cdb-4ec8-866f-e82a3528bff7 | G46: Aom: Pornsawan Polnyiem | H46: 5d2ed694a666040c85096e17 | I46: Medium | J46: Done | L46: 05/Jun/26 9:48 AM | M46: 12/Jun/26 10:00 AM | P46: rr-backoffice | V46: [Dev][RD][New PE] Sprint 26
A47: Story | B47: DPE-661 | C47: 54466 | D47: [Dev][RD][PE Middleware] Prevent Debit/Credit Transaction Creation When Offer Name Is Missing | E47: Moss : Kittapath Sangvikukit | F47: 712020:b33baa03-2b29-4662-9923-dbdc2bbf980d | G47: Aom: Pornsawan Polnyiem | H47: 5d2ed694a666040c85096e17 | I47: Medium | J47: Done | L47: 04/Jun/26 2:41 PM | M47: 12/Jun/26 1:29 PM | N47: 12/Jun/26 12:00 AM | O47: 3 | P47: point-engine-proxy | U47: 28800 | V47: [Dev][RD][New PE] Sprint 26
A48: Story | B48: DEVRDSUP-623 | C48: 54444 | D48: [SUP-713][SUB] : Request to export receipt due to Incomplete Emails Received by BTSC (MAY26) | E48: A:Phongthorn | F48: 5b3c867ae263df2dc32f7e35 | G48: Abhinaf Singh | H48: 712020:a81c99dd-d5cd-44bd-950a-32f4ff7d56ac | I48: High | J48: Done | L48: 02/Jun/26 5:35 PM | M48: 12/Jun/26 2:00 PM | N48: 05/Jun/26 12:00 AM | O48: 1 | P48: sub | U48: 7200 | V48: [Dev][All Project] Sprint 26
A49: Sub-task | B49: RDAPS-492 | C49: 54443 | D49: [QA] Test Execution Verify Enhance clear member card cache after add card success | E49: Pueng Prachpreeya | F49: 642a5328f8bc2116accac530 | G49: Pueng Prachpreeya | H49: 642a5328f8bc2116accac530 | I49: Medium | J49: Done | L49: 02/Jun/26 2:53 PM | M49: 02/Jun/26 5:30 PM | V49: [Dev][All Project] Sprint 25 | W49: [Dev][All Project] Sprint 26
A50: Sub-task | B50: DPE-660 | C50: 54440 | D50: Test execution | E50: Plai Thanaporn Rimnong-ang | F50: 62c2a5acefb17d6ce62e41bf | G50: Aom: Pornsawan Polnyiem | H50: 5d2ed694a666040c85096e17 | I50: Medium | J50: Done | L50: 02/Jun/26 1:57 PM | M50: 05/Jun/26 4:17 PM | V50: [Dev][RD][New PE] Sprint 21 | W50: [Dev][RD][New PE] Sprint 22 | X50: [Dev][RD][New PE] Sprint 23 | Y50: [Dev][RD][New PE] Sprint 24 | Z50: [Dev][RD][New PE] Sprint 25 | AA50: [Dev][RD][New PE] Sprint 26
A51: Sub-task | B51: DPE-659 | C51: 54439 | D51: Create test case | E51: Plai Thanaporn Rimnong-ang | F51: 62c2a5acefb17d6ce62e41bf | G51: Aom: Pornsawan Polnyiem | H51: 5d2ed694a666040c85096e17 | I51: Medium | J51: Done | L51: 02/Jun/26 1:57 PM | M51: 04/Jun/26 4:56 PM | V51: [Dev][RD][New PE] Sprint 21 | W51: [Dev][RD][New PE] Sprint 22 | X51: [Dev][RD][New PE] Sprint 23 | Y51: [Dev][RD][New PE] Sprint 24 | Z51: [Dev][RD][New PE] Sprint 25 | AA51: [Dev][RD][New PE] Sprint 26
A52: Bug | B52: DEVRDSUP-622 | C52: 54438 | D52: [SUP-714][Incident] – Member Data Import Issue | Member imported but SSO is not mapped. | E52: Zan : Isarapong Bulan | F52: 5d4814e9da0c4d0c789a4bb7 | G52: Abhinaf Singh | H52: 712020:a81c99dd-d5cd-44bd-950a-32f4ff7d56ac | I52: Highest | J52: Closed | L52: 02/Jun/26 1:11 PM | M52: 12/Jun/26 1:04 PM | N52: 02/Jun/26 12:00 AM | P52: hop | Q52: hr-solution | V52: [Dev][All Project] Sprint 26
A53: Sub-task | B53: DEVRDSUP-621 | C53: 54437 | D53: [SODA] Update config file for RR DevOps | E53: Soda Team | F53: 712020:c2762549-600f-4b8e-80d0-86600ba589a5 | G53: Abhinaf Singh | H53: 712020:a81c99dd-d5cd-44bd-950a-32f4ff7d56ac | I53: Medium | J53: Done | L53: 02/Jun/26 11:57 AM | M53: 02/Jun/26 2:28 PM | V53: [Dev][All Project] Sprint 26
A54: Sub-task | B54: DEVRDSUP-620 | C54: 54436 | D54: [DevOps] Switch periodically at 9AM on Tuesday from 2June - 21July 2026. | E54: Pui Wigrom Naddakul | F54: 61d40990ce3652006ab55354 | G54: Abhinaf Singh | H54: 712020:a81c99dd-d5cd-44bd-950a-32f4ff7d56ac | I54: Medium | J54: In Progress | L54: 02/Jun/26 11:56 AM | M54: 05/Jun/26 1:35 PM | V54: [Dev][All Project] Sprint 26
A55: Story | B55: DEVRDSUP-619 | C55: 54435 | D55: [SUP-715][UAT] Request to switch API from CleverTap's loyalty to uLoyalty for ST team for training. Switch on every Tuesday 9AM-12PM until end of July26. | E55: Mai:Sateta Abvanawong | F55: 64000e4f15d668edd8edc7ea | G55: Abhinaf Singh | H55: 712020:a81c99dd-d5cd-44bd-950a-32f4ff7d56ac | I55: Medium | J55: In Progress | L55: 02/Jun/26 11:50 AM | M55: 12/Jun/26 2:00 PM | N55: 21/Jul/26 12:00 AM | P55: app | Q55: turtle | V55: [Dev][All Project] Sprint 26
A56: Story | B56: RDTHANA-510 | C56: 54418 | D56: [DEV][RD][TDM] Callback API x FITNESS_IN event | E56: Mac: Jarupong Pawichpongkul | F56: 62c2a16240923988ba097c14 | G56: Zan : Isarapong Bulan | H56: 5d4814e9da0c4d0c789a4bb7 | I56: Medium | J56: Ready To Test | L56: 02/Jun/26 9:42 AM | M56: 11/Jun/26 5:07 PM | N56: 05/Jun/26 12:00 AM | O56: 2 | V56: [Dev][RD][Thana] Sprint 26
A57: Story | B57: RDTHANA-509 | C57: 54417 | D57: [DEV][RD][TDM] Callback API x GATE_OUT event | E57: Mac: Jarupong Pawichpongkul | F57: 62c2a16240923988ba097c14 | G57: Zan : Isarapong Bulan | H57: 5d4814e9da0c4d0c789a4bb7 | I57: Medium | J57: Ready To Test | L57: 02/Jun/26 9:41 AM | M57: 11/Jun/26 5:07 PM | N57: 05/Jun/26 12:00 AM | O57: 2 | V57: [Dev][RD][Thana] Sprint 26
A58: Story | B58: RDTHANA-508 | C58: 54416 | D58: [DEV][RD][TDM] Callback API x GATE_IN event | E58: Mac: Jarupong Pawichpongkul | F58: 62c2a16240923988ba097c14 | G58: Zan : Isarapong Bulan | H58: 5d4814e9da0c4d0c789a4bb7 | I58: Medium | J58: Ready To Test | L58: 02/Jun/26 9:41 AM | M58: 11/Jun/26 5:07 PM | N58: 04/Jun/26 12:00 AM | O58: 3 | V58: [Dev][RD][Thana] Sprint 26
A59: Story | B59: RDTHANA-507 | C59: 54415 | D59: [DEV][RD][POC] Shopify Data | E59: Aek:Atiphat Nanthachitvanich | F59: 5d48155f5b8ea70c7e4f1b0f | G59: Zan : Isarapong Bulan | H59: 5d4814e9da0c4d0c789a4bb7 | I59: Medium | J59: To Do | L59: 02/Jun/26 9:20 AM | M59: 12/Jun/26 9:30 AM | V59: [Dev][RD][Thana] Sprint 26
A60: Story | B60: DRST-102 | C60: 54414 | D60: [DEV][RD][VIMI] Remove BTS daily + ScheduleService (MyCity only) | E60: Nim : muthita munmueang | F60: 712020:e80312b7-b5b0-43e8-b198-3d8fce4532bb | G60: Zan : Isarapong Bulan | H60: 5d4814e9da0c4d0c789a4bb7 | I60: Medium | J60: Ready To Test | L60: 02/Jun/26 9:04 AM | M60: 12/Jun/26 1:46 PM | O60: 3 | V60: [Dev RD][VIMI Termi] Sprint 26
A61: Story | B61: DRST-101 | C61: 54413 | D61: [DEV][RD][VIMI] Remove subscription transaction export PG (subscriptions_report) | E61: Nim : muthita munmueang | F61: 712020:e80312b7-b5b0-43e8-b198-3d8fce4532bb | G61: Zan : Isarapong Bulan | H61: 5d4814e9da0c4d0c789a4bb7 | I61: Medium | J61: Ready To Test | L61: 02/Jun/26 9:03 AM | M61: 12/Jun/26 1:46 PM | O61: 2 | P61: No-QA | V61: [Dev RD][VIMI Termi] Sprint 26
A62: Story | B62: DRST-100 | C62: 54412 | D62: [DEV][RD][VIMI] Remove subscription coupon import (subscriptions_product) | E62: Nim : muthita munmueang | F62: 712020:e80312b7-b5b0-43e8-b198-3d8fce4532bb | G62: Zan : Isarapong Bulan | H62: 5d4814e9da0c4d0c789a4bb7 | I62: Medium | J62: Ready To Test | L62: 02/Jun/26 9:03 AM | M62: 12/Jun/26 1:46 PM | O62: 1 | P62: No-QA | V62: [Dev RD][VIMI Termi] Sprint 26
A63: Sub-task | B63: DPE-658 | C63: 54411 | D63: Test execution | E63: Plai Thanaporn Rimnong-ang | F63: 62c2a5acefb17d6ce62e41bf | G63: Aom: Pornsawan Polnyiem | H63: 5d2ed694a666040c85096e17 | I63: Medium | J63: Done | L63: 01/Jun/26 5:38 PM | M63: 05/Jun/26 4:24 PM | V63: [Dev][RD][New PE] Sprint 21 | W63: [Dev][RD][New PE] Sprint 22 | X63: [Dev][RD][New PE] Sprint 23 | Y63: [Dev][RD][New PE] Sprint 24 | Z63: [Dev][RD][New PE] Sprint 25 | AA63: [Dev][RD][New PE] Sprint 26
A64: Sub-task | B64: DPE-657 | C64: 54410 | D64: Create test case | E64: Plai Thanaporn Rimnong-ang | F64: 62c2a5acefb17d6ce62e41bf | G64: Aom: Pornsawan Polnyiem | H64: 5d2ed694a666040c85096e17 | I64: Medium | J64: Done | L64: 01/Jun/26 5:38 PM | M64: 04/Jun/26 4:56 PM | V64: [Dev][RD][New PE] Sprint 21 | W64: [Dev][RD][New PE] Sprint 22 | X64: [Dev][RD][New PE] Sprint 23 | Y64: [Dev][RD][New PE] Sprint 24 | Z64: [Dev][RD][New PE] Sprint 25 | AA64: [Dev][RD][New PE] Sprint 26
A65: Sub-task | B65: DPE-656 | C65: 54409 | D65: Test execution | E65: Plai Thanaporn Rimnong-ang | F65: 62c2a5acefb17d6ce62e41bf | G65: Aom: Pornsawan Polnyiem | H65: 5d2ed694a666040c85096e17 | I65: Medium | J65: Done | L65: 01/Jun/26 5:38 PM | M65: 05/Jun/26 4:24 PM | V65: [Dev][RD][New PE] Sprint 24 | W65: [Dev][RD][New PE] Sprint 25 | X65: [Dev][RD][New PE] Sprint 26
A66: Sub-task | B66: DPE-655 | C66: 54408 | D66: Test execution | E66: Plai Thanaporn Rimnong-ang | F66: 62c2a5acefb17d6ce62e41bf | G66: Aom: Pornsawan Polnyiem | H66: 5d2ed694a666040c85096e17 | I66: Medium | J66: Done | L66: 01/Jun/26 5:38 PM | M66: 05/Jun/26 4:56 PM | V66: [Dev][RD][New PE] Sprint 24 | W66: [Dev][RD][New PE] Sprint 25 | X66: [Dev][RD][New PE] Sprint 26
A67: Sub-task | B67: DPE-654 | C67: 54407 | D67: Create test case | E67: Plai Thanaporn Rimnong-ang | F67: 62c2a5acefb17d6ce62e41bf | G67: Aom: Pornsawan Polnyiem | H67: 5d2ed694a666040c85096e17 | I67: Medium | J67: Done | L67: 01/Jun/26 5:38 PM | M67: 04/Jun/26 4:56 PM | V67: [Dev][RD][New PE] Sprint 24 | W67: [Dev][RD][New PE] Sprint 25 | X67: [Dev][RD][New PE] Sprint 26
A68: Sub-task | B68: DPE-653 | C68: 54406 | D68: Create test case | E68: Plai Thanaporn Rimnong-ang | F68: 62c2a5acefb17d6ce62e41bf | G68: Aom: Pornsawan Polnyiem | H68: 5d2ed694a666040c85096e17 | I68: Medium | J68: Done | L68: 01/Jun/26 5:38 PM | M68: 04/Jun/26 4:56 PM | V68: [Dev][RD][New PE] Sprint 24 | W68: [Dev][RD][New PE] Sprint 25 | X68: [Dev][RD][New PE] Sprint 26
A69: Sub-task | B69: DPE-652 | C69: 54405 | D69: Test execution | E69: Plai Thanaporn Rimnong-ang | F69: 62c2a5acefb17d6ce62e41bf | G69: Aom: Pornsawan Polnyiem | H69: 5d2ed694a666040c85096e17 | I69: Medium | J69: Done | L69: 01/Jun/26 5:38 PM | M69: 05/Jun/26 4:56 PM | V69: [Dev][RD][New PE] Sprint 24 | W69: [Dev][RD][New PE] Sprint 25 | X69: [Dev][RD][New PE] Sprint 26
A70: Sub-task | B70: DPE-651 | C70: 54404 | D70: Create test case | E70: Plai Thanaporn Rimnong-ang | F70: 62c2a5acefb17d6ce62e41bf | G70: Aom: Pornsawan Polnyiem | H70: 5d2ed694a666040c85096e17 | I70: Medium | J70: Done | L70: 01/Jun/26 5:38 PM | M70: 04/Jun/26 4:56 PM | V70: [Dev][RD][New PE] Sprint 24 | W70: [Dev][RD][New PE] Sprint 25 | X70: [Dev][RD][New PE] Sprint 26
A71: Story | B71: RDTHANA-506 | C71: 54402 | D71: [DEV][RD][POC] Shopify x Clevertrap | E71: Mac: Jarupong Pawichpongkul | F71: 62c2a16240923988ba097c14 | G71: Zan : Isarapong Bulan | H71: 5d4814e9da0c4d0c789a4bb7 | I71: Medium | J71: In Review | L71: 01/Jun/26 4:52 PM | M71: 12/Jun/26 1:53 PM | N71: 12/Jun/26 12:00 AM | O71: 5 | V71: [Dev][RD][Thana] Sprint 26
A72: Story | B72: DRST-99 | C72: 54398 | D72: [DEV][RD][VIMI] Remove e-receipt export (MyCity + S3 subscription) | E72: Nim : muthita munmueang | F72: 712020:e80312b7-b5b0-43e8-b198-3d8fce4532bb | G72: Zan : Isarapong Bulan | H72: 5d4814e9da0c4d0c789a4bb7 | I72: Medium | J72: Ready To Test | L72: 01/Jun/26 4:04 PM | M72: 12/Jun/26 1:46 PM | O72: 2 | P72: No-QA | V72: [Dev RD][VIMI Termi] Sprint 26
A73: Story | B73: RDAPS-490 | C73: 54389 | D73: [SA][RD] Meeting Sprint 26 | E73: Aom: Pornsawan Polnyiem | F73: 5d2ed694a666040c85096e17 | G73: Aom: Pornsawan Polnyiem | H73: 5d2ed694a666040c85096e17 | I73: Medium | J73: In Progress | L73: 01/Jun/26 10:37 AM | M73: 02/Jun/26 10:07 AM | N73: 12/Jun/26 12:00 AM | O73: 5 | V73: [Dev][All Project] Sprint 26
A74: Epic | B74: RDAPS-489 | C74: 54388 | D74: [SA][RD] Meeting Sprint 26 | G74: Aom: Pornsawan Polnyiem | H74: 5d2ed694a666040c85096e17 | I74: Medium | J74: To Do | L74: 01/Jun/26 10:36 AM | M74: 01/Jun/26 10:36 AM | V74: [Dev][All Project] Sprint 26
A75: Epic | B75: RDAPS-488 | C75: 54387 | D75: [SA][RD] Meeting Sprint 26 | G75: Aom: Pornsawan Polnyiem | H75: 5d2ed694a666040c85096e17 | I75: Medium | J75: To Do | L75: 01/Jun/26 10:35 AM | M75: 01/Jun/26 10:35 AM | V75: [Dev][All Project] Sprint 26
A76: Sub-task | B76: DPE-649 | C76: 54385 | D76: Test execution | E76: Plai Thanaporn Rimnong-ang | F76: 62c2a5acefb17d6ce62e41bf | G76: Aom: Pornsawan Polnyiem | H76: 5d2ed694a666040c85096e17 | I76: Medium | J76: Done | L76: 01/Jun/26 10:29 AM | M76: 01/Jun/26 2:48 PM | V76: [Dev][RD][New PE] Sprint 26
A77: Sub-task | B77: DPE-648 | C77: 54384 | D77: Create test case | E77: Plai Thanaporn Rimnong-ang | F77: 62c2a5acefb17d6ce62e41bf | G77: Aom: Pornsawan Polnyiem | H77: 5d2ed694a666040c85096e17 | I77: Medium | J77: Done | L77: 01/Jun/26 10:28 AM | M77: 01/Jun/26 10:45 AM | V77: [Dev][RD][New PE] Sprint 26
A78: Story | B78: DEVRDECOM-253 | C78: 54375 | D78: [DEV][RD][Ecom][Gustron][POC] Banner auto login from RR app (Browser Share Session Cookie) | E78: A:Phongthorn | F78: 5b3c867ae263df2dc32f7e35 | G78: Aek:Atiphat Nanthachitvanich | H78: 5d48155f5b8ea70c7e4f1b0f | I78: Low | J78: In Review | L78: 31/May/26 7:14 AM | M78: 12/Jun/26 9:24 AM | N78: 09/Jun/26 12:00 AM | O78: 5 | P78: No-QA | Q78: poc | R78: rr-ecommerce-shopify | U78: 57600 | V78: [Dev][RD][Ecom] Sprint 26
A79: Story | B79: RDAPS-487 | C79: 54344 | D79: [SA][RD] Prepare task for sprint 27 | E79: Aek:Atiphat Nanthachitvanich | F79: 5d48155f5b8ea70c7e4f1b0f | G79: Aek:Atiphat Nanthachitvanich | H79: 5d48155f5b8ea70c7e4f1b0f | I79: Medium | J79: Done | L79: 29/May/26 5:09 PM | M79: 12/Jun/26 2:55 PM | O79: 1 | U79: 7200 | V79: [Dev][All Project] Sprint 26
A80: Story | B80: RDAPS-486 | C80: 54343 | D80: [SA][RD] Team Support & Management Sprint 26 | E80: Aek:Atiphat Nanthachitvanich | F80: 5d48155f5b8ea70c7e4f1b0f | G80: Aek:Atiphat Nanthachitvanich | H80: 5d48155f5b8ea70c7e4f1b0f | I80: Medium | J80: Done | L80: 29/May/26 5:08 PM | M80: 12/Jun/26 10:13 AM | O80: 3 | U80: 28800 | V80: [Dev][All Project] Sprint 26
A81: Story | B81: RDAPS-485 | C81: 54342 | D81: [SA][RD] Meeting Sprint 26 | E81: Aek:Atiphat Nanthachitvanich | F81: 5d48155f5b8ea70c7e4f1b0f | G81: Aek:Atiphat Nanthachitvanich | H81: 5d48155f5b8ea70c7e4f1b0f | I81: Medium | J81: Done | L81: 29/May/26 5:08 PM | M81: 12/Jun/26 10:14 AM | O81: 2 | U81: 14400 | V81: [Dev][All Project] Sprint 26
A82: Story | B82: RDAPS-484 | C82: 54341 | D82: [Dev][RD][Adhoc] Open DevOps ticket for Lens access (Staging & UAT) | E82: A:Phongthorn | F82: 5b3c867ae263df2dc32f7e35 | G82: Aek:Atiphat Nanthachitvanich | H82: 5d48155f5b8ea70c7e4f1b0f | I82: Medium | J82: In Review | L82: 29/May/26 4:41 PM | M82: 12/Jun/26 1:51 PM | O82: 1 | P82: access | Q82: devops | R82: lens | S82: staging | T82: uat | V82: [Dev][All Project] Sprint 26
A83: Story | B83: RDTHANA-505 | C83: 54339 | D83: [DEV][RD][TDM] Integrate queue and retry to coin revoke api | E83: Moss : Kittapath Sangvikukit | F83: 712020:b33baa03-2b29-4662-9923-dbdc2bbf980d | G83: Zan : Isarapong Bulan | H83: 5d4814e9da0c4d0c789a4bb7 | I83: Medium | J83: Ready to Staging | L83: 29/May/26 3:23 PM | M83: 11/Jun/26 5:07 PM | N83: 12/Jun/26 12:00 AM | O83: 3 | P83: No-QA | U83: 28800 | V83: [Dev][RD][Thana] Sprint 26
A84: Story | B84: RDTHANA-504 | C84: 54338 | D84: [DEV][RD][TDM] Log invalid generic transaction requests to S3 | E84: Mac: Jarupong Pawichpongkul | F84: 62c2a16240923988ba097c14 | G84: Zan : Isarapong Bulan | H84: 5d4814e9da0c4d0c789a4bb7 | I84: Medium | J84: Ready to Staging | L84: 29/May/26 2:46 PM | M84: 11/Jun/26 5:07 PM | N84: 09/Jun/26 12:00 AM | O84: 5 | V84: [Dev][RD][Thana] Sprint 26
A85: Story | B85: DEVRDSS-12 | C85: 54334 | D85: [SA][RD][Samsung] Sync up with BSS teams | E85: Aek:Atiphat Nanthachitvanich | F85: 5d48155f5b8ea70c7e4f1b0f | G85: Aek:Atiphat Nanthachitvanich | H85: 5d48155f5b8ea70c7e4f1b0f | I85: Medium | J85: Done | L85: 29/May/26 10:40 AM | M85: 12/Jun/26 12:53 PM | O85: 2 | V85: [Dev][RD][Samsung] Sprint 26
A86: Story | B86: RDAPS-483 | C86: 54330 | D86: [Dev][RD][Adhoc] Update GCloud Cost for Rcash, RR, and BSS Tabs in Cost Tracking Google Sheet for May | E86: A:Phongthorn | F86: 5b3c867ae263df2dc32f7e35 | G86: Aek:Atiphat Nanthachitvanich | H86: 5d48155f5b8ea70c7e4f1b0f | I86: Medium | J86: Done | L86: 29/May/26 8:40 AM | M86: 12/Jun/26 1:51 PM | N86: 03/Jun/26 12:00 AM | O86: 1 | P86: cost-management | Q86: finance | R86: gcloud | S86: report | U86: 7200 | V86: [Dev][All Project] Sprint 26
A87: Story | B87: DEVRDUA-1 | C87: 54323 | D87: [SA][RD][Unified App] Assess project feasibility and implementation options | E87: Jack: Warin Kesorn | F87: 61a98e8e744c4d00693281d1 | G87: Aek:Atiphat Nanthachitvanich | H87: 5d48155f5b8ea70c7e4f1b0f | I87: Medium | J87: In Progress | L87: 28/May/26 5:38 PM | M87: 12/Jun/26 10:27 AM | P87: architecture | Q87: feasibility | R87: sa | S87: unified-app | V87: [Dev][RD][Unified] Sprint 26
A88: Story | B88: RDTHANA-503 | C88: 54322 | D88: [DEV][RD][TDM] Add is_legacy to callback API | E88: Mac: Jarupong Pawichpongkul | F88: 62c2a16240923988ba097c14 | G88: Zan : Isarapong Bulan | H88: 5d4814e9da0c4d0c789a4bb7 | I88: Medium | J88: Ready To Test | L88: 28/May/26 5:16 PM | M88: 11/Jun/26 5:07 PM | N88: 29/May/26 12:00 AM | O88: 1 | V88: [Dev][RD][Thana] Sprint 25 | W88: [Dev][RD][Thana] Sprint 26
A89: Story | B89: DEV-12 | C89: 54321 | D89: [DEV][RD][TechDebt] Provide RR Operation & Incident API matrix in central sheet | E89: A:Phongthorn | F89: 5b3c867ae263df2dc32f7e35 | G89: Aek:Atiphat Nanthachitvanich | H89: 5d48155f5b8ea70c7e4f1b0f | I89: Medium | J89: In Review | L89: 28/May/26 5:12 PM | M89: 12/Jun/26 1:04 PM | N89: 04/Jun/26 12:00 AM | O89: 5 | P89: api-mapping | Q89: devops | R89: incident | S89: operations | U89: 57600 | V89: [Dev][RD][TechDebt] Sprint 26
A90: Story | B90: DEVRDECOM-252 | C90: 54320 | D90: [Dev][RD][Ecom][Turtle] Auto prefill location/phone and branch | E90: Aek:Atiphat Nanthachitvanich | F90: 5d48155f5b8ea70c7e4f1b0f | G90: Aek:Atiphat Nanthachitvanich | H90: 5d48155f5b8ea70c7e4f1b0f | I90: Medium | J90: To Do | L90: 28/May/26 4:16 PM | M90: 12/Jun/26 4:31 PM | O90: 8 | V90: [Dev][RD][Ecom] Sprint 26
A91: Story | B91: DEVRDECOM-251 | C91: 54312 | D91: [DEV][RD][Ecom] Filter unnecessary logs to reduce observability cost | E91: A:Phongthorn | F91: 5b3c867ae263df2dc32f7e35 | G91: Aek:Atiphat Nanthachitvanich | H91: 5d48155f5b8ea70c7e4f1b0f | I91: High | J91: Done | L91: 28/May/26 3:02 PM | M91: 12/Jun/26 9:24 AM | N91: 05/Jun/26 12:00 AM | O91: 2 | P91: cost-optimization | Q91: log-filtering | U91: 14400 | V91: [Dev][RD][Ecom] Sprint 26
A92: Story | B92: RDAPS-482 | C92: 54310 | D92: [Dev][RD][Adhoc][HR Solution] Turtle Upgrade/Downgrade tier batch | E92: Mai:Sateta Abvanawong | F92: 64000e4f15d668edd8edc7ea | G92: Zan : Isarapong Bulan | H92: 5d4814e9da0c4d0c789a4bb7 | I92: Medium | J92: Ready to Staging | L92: 28/May/26 2:19 PM | M92: 11/Jun/26 5:07 PM | N92: 08/Jun/26 12:00 AM | O92: 8 | U92: 86400 | V92: [Dev][All Project] Sprint 26
A93: Story | B93: DEVRRBOF-211 | C93: 54308 | D93: [Dev][RD][Order API][SUB] Support crm_case_ref and crm_note on POST /v1/orders/update for Payment Inquiry | E93: Mac: Jarupong Pawichpongkul | F93: 62c2a16240923988ba097c14 | G93: Aom: Pornsawan Polnyiem | H93: 5d2ed694a666040c85096e17 | I93: Medium | J93: Ready to Staging | L93: 28/May/26 1:51 PM | M93: 12/Jun/26 12:57 PM | N93: 11/Jun/26 12:00 AM | O93: 3 | V93: [Dev][RD][BOF] Sprint 26
A94: Story | B94: DPE-646 | C94: 54304 | D94: [Dev][RD][CT] Adjust config MAU filtering | E94: Jack: Warin Kesorn | F94: 61a98e8e744c4d00693281d1 | G94: Jack: Warin Kesorn | H94: 61a98e8e744c4d00693281d1 | I94: Medium | J94: Done | L94: 28/May/26 1:45 PM | M94: 12/Jun/26 10:01 AM | N94: 12/Jun/26 12:00 AM | O94: 1 | P94: CleverTap | Q94: No-QA | V94: [Dev][RD][New PE] Sprint 26
A95: Bug | B95: DEVRDSUP-613 | C95: 54302 | D95: [SUP-703]"Point_Issued" events duplicate data in Clevertap | E95: Pan:Paliwan Boonhian | F95: 62e8dfd1432ef494c8c98577 | G95: Abhinaf Singh | H95: 712020:a81c99dd-d5cd-44bd-950a-32f4ff7d56ac | I95: Medium | J95: Closed | L95: 28/May/26 1:08 PM | M95: 12/Jun/26 10:20 AM | N95: 16/Jun/26 12:00 AM | P95: CleverTap | Q95: prod-issue | V95: [Dev][All Project] Sprint 26
A96: Bug | B96: DEVRDSUP-612 | C96: 54301 | D96: [SUP-702]"checkin" events are also being recorded as "charged" events in Clevertap | E96: Jack: Warin Kesorn | F96: 61a98e8e744c4d00693281d1 | G96: Abhinaf Singh | H96: 712020:a81c99dd-d5cd-44bd-950a-32f4ff7d56ac | I96: Medium | J96: Enhancement | L96: 28/May/26 1:06 PM | M96: 12/Jun/26 1:04 PM | N96: 16/Jun/26 12:00 AM | V96: [Dev][All Project] Sprint 26
A97: Story | B97: DEVRDSUP-611 | C97: 54299 | D97: [SUP-701][Need Support] BTSG – Import User (Employee ID เปลี่ยน) | E97: Zan : Isarapong Bulan | F97: 5d4814e9da0c4d0c789a4bb7 | G97: Abhinaf Singh | H97: 712020:a81c99dd-d5cd-44bd-950a-32f4ff7d56ac | I97: Highest | J97: Done | L97: 28/May/26 11:48 AM | M97: 12/Jun/26 2:00 PM | N97: 29/May/26 12:00 AM | P97: hop | Q97: hr-solution | V97: [Dev][All Project] Sprint 25 | W97: [Dev][All Project] Sprint 26
A98: Story | B98: DEVRDSUP-610 | C98: 54298 | D98: [SUP-706][SSO][Access] Request SSO back office access for HOP AE 28/05/2026 | E98: Aek:Atiphat Nanthachitvanich | F98: 5d48155f5b8ea70c7e4f1b0f | G98: Abhinaf Singh | H98: 712020:a81c99dd-d5cd-44bd-950a-32f4ff7d56ac | I98: Medium | J98: Done | L98: 28/May/26 11:36 AM | M98: 12/Jun/26 2:00 PM | N98: 11/Jun/26 12:00 AM | O98: 1 | U98: 300 | V98: [Dev][All Project] Sprint 26
A99: Story | B99: RDAPS-481 | C99: 54294 | D99: [Dev][RD][Adhoc] Estimate Point expire 2026 - Donation | E99: Aom: Pornsawan Polnyiem | F99: 5d2ed694a666040c85096e17 | G99: Aom: Pornsawan Polnyiem | H99: 5d2ed694a666040c85096e17 | I99: Medium | J99: Done | L99: 28/May/26 9:52 AM | M99: 12/Jun/26 1:51 PM | O99: 2 | V99: [Dev][All Project] Sprint 26
A100: Story | B100: DPE-645 | C100: 54292 | D100: [Dev][RD][BFF] Revise transaction type filter logic for earn / burn history | E100: Nim : muthita munmueang | F100: 712020:e80312b7-b5b0-43e8-b198-3d8fce4532bb | G100: Aom: Pornsawan Polnyiem | H100: 5d2ed694a666040c85096e17 | I100: Medium | J100: Done | L100: 28/May/26 7:37 AM | M100: 12/Jun/26 1:29 PM | O100: 1 | P100: BFF | V100: [Dev][RD][New PE] Sprint 26
...

Sheet Summarize Sprint 25
A1: Column 1 | B1: Total Stories Point | C1: Total Manhour | D1: Point Done | E1: Manhour Done | F1: Note
A2: 18 May - 29 May
A3: Dev Resource Available | B3: 21 | C3: 462
A4: Meeting Planned | F4: Ref
A5: Additional Meeting | F5: Ref
A6: Deployment | C6: 2 | F6: 2 ครั้ง 1. 1 คน 2. 2 คน
A7: Development Sprint Total | B7: =SUM('Sprint 25'!O:O) -> 548 | C7: =ROUND(SUM('Sprint 25'!U:U)/3600,2) -> 804.17 | D7: =SUMIF('Sprint 25'!J:J, "Done", 'Sprint 25'!O:O) -> 300 | E7: =ROUND(SUMIF('Sprint 25'!J:J, "Done", 'Sprint 25'!U:U)/3600,2) -> 448.17
A9: Ad-hoc Mid Sprint | B9: 0 | C9: =IFERROR(__xludf.DUMMYFUNCTION("ROUND(IFERROR(SUM(FILTER('Sprint 25'!U:U, ('Sprint 25'!Q:Q = ""mid-sprint"")))/3600,0),2)"),0.0) -> 0 | D9: =IFERROR(__xludf.DUMMYFUNCTION("IFERROR(SUM(FILTER('Sprint 25'!O:O, (('Sprint 25'!J:J = ""Done"")) * ('Sprint 25'!Q:Q = ""mid-sprint""))),0)"),0.0) -> 0 | E9: =IFERROR(__xludf.DUMMYFUNCTION("ROUND(IFERROR(SUM(FILTER('Sprint 25'!U:U, (('Sprint 25'!J:J = ""Done"")) * ('Sprint 25'!P:P = ""mid-sprint"")))/3600,0),2)"),0.0) -> 0 | F9: 2 tasks
A10: Requirement changes after refinement? | B10: =IFERROR(__xludf.DUMMYFUNCTION("ROUND(IFERROR(SUM(FILTER('Sprint 25'!U:U, ('Sprint 25'!Q:Q = ""change-request"")))/3600,0),2)"),0.0) -> 0 | D10: =IFERROR(__xludf.DUMMYFUNCTION("IFERROR(SUM(FILTER('Sprint 25'!O:O, (('Sprint 25'!J:J = ""Done"")) * ('Sprint 25'!Q:Q = ""change-request""))),0)"),0.0) -> 0 | E10: =IFERROR(__xludf.DUMMYFUNCTION("ROUND(IFERROR(SUM(FILTER('Sprint 25'!U:U, (('Sprint 25'!J:J = ""Done"")) * ('Sprint 25'!Q:Q = ""change-request"")))/3600,0),2)"),0.0) -> 0 | F10: 0 tasks
A12: Aek | B12: =IFERROR(__xludf.DUMMYFUNCTION("IFERROR(SUM(FILTER('Sprint 25'!O:O, ('Sprint 25'!E:E = ""Aek:Atiphat Nanthachitvanich""))),0)"),35.0) -> 35 | C12: =IFERROR(__xludf.DUMMYFUNCTION("ROUND(IFERROR(SUM(FILTER('Sprint 25'!U:U, ('Sprint 25'!E:E = ""Aek:Atiphat Nanthachitvanich"")))/3600,0),2)"),91.0) -> 91 | D12: =IFERROR(__xludf.DUMMYFUNCTION("IFERROR(SUM(FILTER('Sprint 25'!O:O, (('Sprint 25'!J:J = ""Done"")) * ('Sprint 25'!E:E = ""Aek:Atiphat Nanthachitvanich""))),0)"),27.0) -> 27 | E12: =IFERROR(__xludf.DUMMYFUNCTION("ROUND(IFERROR(SUM(FILTER('Sprint 25'!U:U, (('Sprint 25'!J:J = ""Done"")) * ('Sprint 25'!E:E = ""Aek:Atiphat Nanthachitvanich"")))/3600,0),2)"),59.0) -> 59
A13: A | B13: =IFERROR(__xludf.DUMMYFUNCTION("IFERROR(SUM(FILTER('Sprint 25'!O:O, ('Sprint 25'!E:E = ""A:Phongthorn""))),0)"),89.0) -> 89 | C13: =IFERROR(__xludf.DUMMYFUNCTION("ROUND(IFERROR(SUM(FILTER('Sprint 25'!U:U, ('Sprint 25'!E:E = ""A:Phongthorn"")))/3600,0),2)"),230.0) -> 230 | D13: =IFERROR(__xludf.DUMMYFUNCTION("IFERROR(SUM(FILTER('Sprint 25'!O:O, (('Sprint 25'!J:J = ""Done"")) * ('Sprint 25'!E:E = ""A:Phongthorn""))),0)"),27.0) -> 27 | E13: =IFERROR(__xludf.DUMMYFUNCTION("ROUND(IFERROR(SUM(FILTER('Sprint 25'!U:U, (('Sprint 25'!J:J = ""Done"")) * ('Sprint 25'!E:E = ""A:Phongthorn"")))/3600,0),2)"),68.0) -> 68
A14: Aom | B14: =IFERROR(__xludf.DUMMYFUNCTION("IFERROR(SUM(FILTER('Sprint 25'!O:O, ('Sprint 25'!E:E = ""Aom: Pornsawan Polnyiem""))),0)"),47.0) -> 47 | C14: =IFERROR(__xludf.DUMMYFUNCTION("ROUND(IFERROR(SUM(FILTER('Sprint 25'!U:U, ('Sprint 25'!E:E = ""Aom: Pornsawan Polnyiem"")))/3600,0),2)"),0.17) -> 0.17 | D14: =IFERROR(__xludf.DUMMYFUNCTION("IFERROR(SUM(FILTER('Sprint 25'!O:O, (('Sprint 25'!J:J = ""Done"")) * ('Sprint 25'!E:E = ""Aom: Pornsawan Polnyiem""))),0)"),43.0) -> 43 | E14: =IFERROR(__xludf.DUMMYFUNCTION("ROUND(IFERROR(SUM(FILTER('Sprint 25'!U:U, (('Sprint 25'!J:J = ""Done"")) * ('Sprint 25'!E:E = ""Aom: Pornsawan Polnyiem"")))/3600,0),2)"),0.17) -> 0.17
A15: Zan | B15: =IFERROR(__xludf.DUMMYFUNCTION("IFERROR(SUM(FILTER('Sprint 25'!O:O, ('Sprint 25'!E:E = ""Zan : Isarapong Bulan""))),0)"),9.0) -> 9 | C15: =IFERROR(__xludf.DUMMYFUNCTION("ROUND(IFERROR(SUM(FILTER('Sprint 25'!U:U, ('Sprint 25'!E:E = ""Zan : Isarapong Bulan"")))/3600,0),2)"),0.0) -> 0 | D15: =IFERROR(__xludf.DUMMYFUNCTION("IFERROR(SUM(FILTER('Sprint 25'!O:O, (('Sprint 25'!J:J = ""Done"")) * ('Sprint 25'!E:E = ""Zan : Isarapong Bulan""))),0)"),1.0) -> 1 | E15: =IFERROR(__xludf.DUMMYFUNCTION("ROUND(IFERROR(SUM(FILTER('Sprint 25'!U:U, (('Sprint 25'!J:J = ""Done"")) * ('Sprint 25'!E:E = ""Zan : Isarapong Bulan"")))/3600,0),2)"),0.0) -> 0
A16: Mai | B16: =IFERROR(__xludf.DUMMYFUNCTION("IFERROR(SUM(FILTER('Sprint 25'!O:O, ('Sprint 25'!E:E = ""Mai:Sateta Abvanawong""))),0)"),73.0) -> 73 | C16: =IFERROR(__xludf.DUMMYFUNCTION("ROUND(IFERROR(SUM(FILTER('Sprint 25'!U:U, ('Sprint 25'!E:E = ""Mai:Sateta Abvanawong"")))/3600,0),2)"),146.0) -> 146 | D16: =IFERROR(__xludf.DUMMYFUNCTION("IFERROR(SUM(FILTER('Sprint 25'!O:O, (('Sprint 25'!J:J = ""Done"")) * ('Sprint 25'!E:E = ""Mai:Sateta Abvanawong""))),0)"),55.0) -> 55 | E16: =IFERROR(__xludf.DUMMYFUNCTION("ROUND(IFERROR(SUM(FILTER('Sprint 25'!U:U, (('Sprint 25'!J:J = ""Done"")) * ('Sprint 25'!E:E = ""Mai:Sateta Abvanawong""))),0)/3600,2)"),118.0) -> 118
A17: Mac | B17: =IFERROR(__xludf.DUMMYFUNCTION("IFERROR(SUM(FILTER('Sprint 25'!O:O, ('Sprint 25'!E:E = ""Mac: Jarupong Pawichpongkul""))),0)"),84.0) -> 84 | C17: =IFERROR(__xludf.DUMMYFUNCTION("ROUND(IFERROR(SUM(FILTER('Sprint 25'!U:U, ('Sprint 25'!E:E = ""Mac: Jarupong Pawichpongkul"")))/3600,0),2)"),176.0) -> 176 | D17: =IFERROR(__xludf.DUMMYFUNCTION("IFERROR(SUM(FILTER('Sprint 25'!O:O, (('Sprint 25'!J:J = ""Done"")) * ('Sprint 25'!E:E = ""Mac: Jarupong Pawichpongkul""))),0)"),57.0) -> 57 | E17: =IFERROR(__xludf.DUMMYFUNCTION("ROUND(IFERROR(SUM(FILTER('Sprint 25'!U:U, (('Sprint 25'!J:J = ""Done"")) * ('Sprint 25'!E:E = ""Mac: Jarupong Pawichpongkul"")))/3600,0),2)"),120.0) -> 120
A18: Mos | B18: =IFERROR(__xludf.DUMMYFUNCTION("IFERROR(SUM(FILTER('Sprint 25'!O:O, ('Sprint 25'!E:E = ""Moss : Kittapath Sangvikukit""))),0)"),71.0) -> 71 | C18: =IFERROR(__xludf.DUMMYFUNCTION("ROUND(IFERROR(SUM(FILTER('Sprint 25'!U:U, ('Sprint 25'!E:E = ""Moss : Kittapath Sangvikukit"")))/3600,0),2)"),121.0) -> 121 | D18: =IFERROR(__xludf.DUMMYFUNCTION("IFERROR(SUM(FILTER('Sprint 25'!O:O, (('Sprint 25'!J:J = ""Done"")) * ('Sprint 25'!E:E = ""Moss : Kittapath Sangvikukit""))),0)"),32.0) -> 32 | E18: =IFERROR(__xludf.DUMMYFUNCTION("ROUND(IFERROR(SUM(FILTER('Sprint 25'!U:U, (('Sprint 25'!J:J = ""Done"")) * ('Sprint 25'!E:E = ""Moss : Kittapath Sangvikukit"")))/3600,0),2)"),51.0) -> 51
A19: Jack | B19: =IFERROR(__xludf.DUMMYFUNCTION("IFERROR(SUM(FILTER('Sprint 25'!O:O, ('Sprint 25'!E:E = ""Jack: Warin Kesorn""))),0)"),5.0) -> 5 | C19: =IFERROR(__xludf.DUMMYFUNCTION("ROUND(IFERROR(SUM(FILTER('Sprint 25'!U:U, ('Sprint 25'!E:E = ""Jack: Warin Kesorn"")))/3600,0),2)"),0.0) -> 0 | D19: =IFERROR(__xludf.DUMMYFUNCTION("IFERROR(SUM(FILTER('Sprint 25'!O:O, (('Sprint 25'!J:J = ""Done"")) * ('Sprint 25'!E:E = ""Jack: Warin Kesorn""))),0)"),5.0) -> 5 | E19: =IFERROR(__xludf.DUMMYFUNCTION("ROUND(IFERROR(SUM(FILTER('Sprint 25'!U:U, (('Sprint 25'!J:J = ""Done"")) * ('Sprint 25'!E:E = ""Jack: Warin Kesorn"")))/3600,0),2)"),0.0) -> 0
A20: Nim | B20: =IFERROR(__xludf.DUMMYFUNCTION("IFERROR(SUM(FILTER('Sprint 25'!O:O, ('Sprint 25'!E:E = ""Nim : muthita munmueang""))),0)"),64.0) -> 64 | C20: =IFERROR(__xludf.DUMMYFUNCTION("ROUND(IFERROR(SUM(FILTER('Sprint 25'!U:U, ('Sprint 25'!E:E = ""Nim : muthita munmueang"")))/3600,0),2)"),40.0) -> 40 | D20: =IFERROR(__xludf.DUMMYFUNCTION("IFERROR(SUM(FILTER('Sprint 25'!O:O, (('Sprint 25'!J:J = ""Done"")) * ('Sprint 25'!E:E = ""Nim : muthita munmueang""))),0)"),39.0) -> 39 | E20: =IFERROR(__xludf.DUMMYFUNCTION("ROUND(IFERROR(SUM(FILTER('Sprint 25'!U:U, (('Sprint 25'!J:J = ""Done"")) * ('Sprint 25'!E:E = ""Nim : muthita munmueang"")))/3600,0),2)"),32.0) -> 32
A21: Arm | B21: =IFERROR(__xludf.DUMMYFUNCTION("IFERROR(SUM(FILTER('Sprint 25'!O:O, ('Sprint 25'!E:E = ""Arm:Worawat Chotipongchoawalit""))),0)"),71.0) -> 71 | C21: =IFERROR(__xludf.DUMMYFUNCTION("ROUND(IFERROR(SUM(FILTER('Sprint 25'!U:U, ('Sprint 25'!E:E = ""Arm:Worawat Chotipongchoawalit"")))/3600,0),2)"),0.0) -> 0 | D21: =IFERROR(__xludf.DUMMYFUNCTION("IFERROR(SUM(FILTER('Sprint 25'!O:O, (('Sprint 25'!J:J = ""Done"")) * ('Sprint 25'!E:E = ""Arm:Worawat Chotipongchoawalit""))),0)"),14.0) -> 14 | E21: =IFERROR(__xludf.DUMMYFUNCTION("ROUND(IFERROR(SUM(FILTER('Sprint 25'!U:U, (('Sprint 25'!J:J = ""Done"")) * ('Sprint 25'!E:E = ""Arm:Worawat Chotipongchoawalit"")))/3600,0),2)"),0.0) -> 0

Sheet Sprint 25
A1: Issue Type | B1: Issue key | C1: Issue id | D1: Summary | E1: Assignee | F1: Assignee Id | G1: Reporter | H1: Reporter Id | I1: Priority | J1: Status | K1: Resolution | L1: Created | M1: Updated | N1: Due date | O1: Custom field (Story Points) | P1: Labels | Q1: Labels | R1: Labels | S1: Labels | T1: Labels | U1: Original estimate | V1: Sprint | W1: Sprint | X1: Sprint | Y1: Sprint | Z1: Sprint | AA1: Sprint | AB1: Sprint | AC1: Sprint | AD1: Sprint | AE1: Sprint | AF1: Sprint | AG1: Sprint | AH1: Sprint
A2: Sub-task | B2: RDAPS-492 | C2: 54443 | D2: [QA] Test Execution Verify Enhance clear member card cache after add card success | E2: Pueng Prachpreeya | F2: 642a5328f8bc2116accac530 | G2: Pueng Prachpreeya | H2: 642a5328f8bc2116accac530 | I2: Medium | J2: Done | L2: 02/Jun/26 2:53 PM | M2: 02/Jun/26 5:30 PM | V2: [Dev][All Project] Sprint 25 | W2: [Dev][All Project] Sprint 26
A3: Sub-task | B3: DPE-660 | C3: 54440 | D3: Test execution | E3: Plai Thanaporn Rimnong-ang | F3: 62c2a5acefb17d6ce62e41bf | G3: Aom: Pornsawan Polnyiem | H3: 5d2ed694a666040c85096e17 | I3: Medium | J3: To Do | L3: 02/Jun/26 1:57 PM | M3: 02/Jun/26 1:57 PM | V3: [Dev][RD][New PE] Sprint 21 | W3: [Dev][RD][New PE] Sprint 22 | X3: [Dev][RD][New PE] Sprint 23 | Y3: [Dev][RD][New PE] Sprint 24 | Z3: [Dev][RD][New PE] Sprint 25 | AA3: [Dev][RD][New PE] Sprint 26
A4: Sub-task | B4: DPE-659 | C4: 54439 | D4: Create test case | E4: Plai Thanaporn Rimnong-ang | F4: 62c2a5acefb17d6ce62e41bf | G4: Aom: Pornsawan Polnyiem | H4: 5d2ed694a666040c85096e17 | I4: Medium | J4: In Progress | L4: 02/Jun/26 1:57 PM | M4: 02/Jun/26 2:11 PM | V4: [Dev][RD][New PE] Sprint 21 | W4: [Dev][RD][New PE] Sprint 22 | X4: [Dev][RD][New PE] Sprint 23 | Y4: [Dev][RD][New PE] Sprint 24 | Z4: [Dev][RD][New PE] Sprint 25 | AA4: [Dev][RD][New PE] Sprint 26
A5: Sub-task | B5: DPE-658 | C5: 54411 | D5: Test execution | E5: Plai Thanaporn Rimnong-ang | F5: 62c2a5acefb17d6ce62e41bf | G5: Aom: Pornsawan Polnyiem | H5: 5d2ed694a666040c85096e17 | I5: Medium | J5: To Do | L5: 01/Jun/26 5:38 PM | M5: 01/Jun/26 5:39 PM | V5: [Dev][RD][New PE] Sprint 21 | W5: [Dev][RD][New PE] Sprint 22 | X5: [Dev][RD][New PE] Sprint 23 | Y5: [Dev][RD][New PE] Sprint 24 | Z5: [Dev][RD][New PE] Sprint 25 | AA5: [Dev][RD][New PE] Sprint 26
A6: Sub-task | B6: DPE-657 | C6: 54410 | D6: Create test case | E6: Plai Thanaporn Rimnong-ang | F6: 62c2a5acefb17d6ce62e41bf | G6: Aom: Pornsawan Polnyiem | H6: 5d2ed694a666040c85096e17 | I6: Medium | J6: In Progress | L6: 01/Jun/26 5:38 PM | M6: 02/Jun/26 2:11 PM | V6: [Dev][RD][New PE] Sprint 21 | W6: [Dev][RD][New PE] Sprint 22 | X6: [Dev][RD][New PE] Sprint 23 | Y6: [Dev][RD][New PE] Sprint 24 | Z6: [Dev][RD][New PE] Sprint 25 | AA6: [Dev][RD][New PE] Sprint 26
A7: Sub-task | B7: DPE-656 | C7: 54409 | D7: Test execution | E7: Plai Thanaporn Rimnong-ang | F7: 62c2a5acefb17d6ce62e41bf | G7: Aom: Pornsawan Polnyiem | H7: 5d2ed694a666040c85096e17 | I7: Medium | J7: To Do | L7: 01/Jun/26 5:38 PM | M7: 01/Jun/26 5:38 PM | V7: [Dev][RD][New PE] Sprint 24 | W7: [Dev][RD][New PE] Sprint 25 | X7: [Dev][RD][New PE] Sprint 26
A8: Sub-task | B8: DPE-655 | C8: 54408 | D8: Test execution | E8: Plai Thanaporn Rimnong-ang | F8: 62c2a5acefb17d6ce62e41bf | G8: Aom: Pornsawan Polnyiem | H8: 5d2ed694a666040c85096e17 | I8: Medium | J8: To Do | L8: 01/Jun/26 5:38 PM | M8: 01/Jun/26 5:38 PM | V8: [Dev][RD][New PE] Sprint 24 | W8: [Dev][RD][New PE] Sprint 25 | X8: [Dev][RD][New PE] Sprint 26
A9: Sub-task | B9: DPE-654 | C9: 54407 | D9: Create test case | E9: Plai Thanaporn Rimnong-ang | F9: 62c2a5acefb17d6ce62e41bf | G9: Aom: Pornsawan Polnyiem | H9: 5d2ed694a666040c85096e17 | I9: Medium | J9: In Progress | L9: 01/Jun/26 5:38 PM | M9: 02/Jun/26 2:11 PM | V9: [Dev][RD][New PE] Sprint 24 | W9: [Dev][RD][New PE] Sprint 25 | X9: [Dev][RD][New PE] Sprint 26
A10: Sub-task | B10: DPE-653 | C10: 54406 | D10: Create test case | E10: Plai Thanaporn Rimnong-ang | F10: 62c2a5acefb17d6ce62e41bf | G10: Aom: Pornsawan Polnyiem | H10: 5d2ed694a666040c85096e17 | I10: Medium | J10: In Progress | L10: 01/Jun/26 5:38 PM | M10: 02/Jun/26 2:11 PM | V10: [Dev][RD][New PE] Sprint 24 | W10: [Dev][RD][New PE] Sprint 25 | X10: [Dev][RD][New PE] Sprint 26
A11: Sub-task | B11: DPE-652 | C11: 54405 | D11: Test execution | E11: Plai Thanaporn Rimnong-ang | F11: 62c2a5acefb17d6ce62e41bf | G11: Aom: Pornsawan Polnyiem | H11: 5d2ed694a666040c85096e17 | I11: Medium | J11: To Do | L11: 01/Jun/26 5:38 PM | M11: 01/Jun/26 5:38 PM | V11: [Dev][RD][New PE] Sprint 24 | W11: [Dev][RD][New PE] Sprint 25 | X11: [Dev][RD][New PE] Sprint 26
A12: Sub-task | B12: DPE-651 | C12: 54404 | D12: Create test case | E12: Plai Thanaporn Rimnong-ang | F12: 62c2a5acefb17d6ce62e41bf | G12: Aom: Pornsawan Polnyiem | H12: 5d2ed694a666040c85096e17 | I12: Medium | J12: In Progress | L12: 01/Jun/26 5:38 PM | M12: 02/Jun/26 2:11 PM | V12: [Dev][RD][New PE] Sprint 24 | W12: [Dev][RD][New PE] Sprint 25 | X12: [Dev][RD][New PE] Sprint 26
A13: Bug | B13: DPE-647 | C13: 54331 | D13: [S3][Coupon] Push coupon is not working properly | E13: Mac: Jarupong Pawichpongkul | F13: 62c2a16240923988ba097c14 | G13: Plai Thanaporn Rimnong-ang | H13: 62c2a5acefb17d6ce62e41bf | I13: Medium | J13: Closed | L13: 29/May/26 9:55 AM | M13: 01/Jun/26 9:58 AM | V13: [Dev][RD][New PE] Sprint 25
A14: Story | B14: RDTHANA-503 | C14: 54322 | D14: [DEV][RD][TDM] Add is_legacy to callback API | E14: Mac: Jarupong Pawichpongkul | F14: 62c2a16240923988ba097c14 | G14: Zan : Isarapong Bulan | H14: 5d4814e9da0c4d0c789a4bb7 | I14: Medium | J14: Ready To Test | L14: 28/May/26 5:16 PM | M14: 02/Jun/26 9:19 AM | N14: 29/May/26 12:00 AM | O14: 1 | V14: [Dev][RD][Thana] Sprint 25 | W14: [Dev][RD][Thana] Sprint 26
A15: Sub-task | B15: DEV-11 | C15: 54313 | D15: [QA] Test execution verify Enhance getMemberTier | E15: Pueng Prachpreeya | F15: 642a5328f8bc2116accac530 | G15: Pueng Prachpreeya | H15: 642a5328f8bc2116accac530 | I15: Medium | J15: Done | L15: 28/May/26 3:08 PM | M15: 02/Jun/26 10:11 AM | V15: [Dev][RD][TechDebt] Sprint 24 | W15: [Dev][RD][TechDebt] Sprint 25
A16: Story | B16: DEVRDSUP-611 | C16: 54299 | D16: [SUP-701][Need Support] BTSG – Import User (Employee ID เปลี่ยน) | E16: Zan : Isarapong Bulan | F16: 5d4814e9da0c4d0c789a4bb7 | G16: Abhinaf Singh | H16: 712020:a81c99dd-d5cd-44bd-950a-32f4ff7d56ac | I16: Highest | J16: In Progress | L16: 28/May/26 11:48 AM | M16: 04/Jun/26 10:28 AM | N16: 29/May/26 12:00 AM | P16: hop | Q16: hr-solution | V16: [Dev][All Project] Sprint 25 | W16: [Dev][All Project] Sprint 26
A17: Story | B17: DEVRDSUP-609 | C17: 54296 | D17: [SUP-705][PROD] Request to create BU in HR Solution | E17: Aek:Atiphat Nanthachitvanich | F17: 5d48155f5b8ea70c7e4f1b0f | G17: Abhinaf Singh | H17: 712020:a81c99dd-d5cd-44bd-950a-32f4ff7d56ac | I17: High | J17: Done | L17: 28/May/26 10:54 AM | M17: 28/May/26 5:18 PM | N17: 29/May/26 12:00 AM | O17: 1 | P17: hop | U17: 600 | V17: [Dev][All Project] Sprint 25
A18: Story | B18: DEVRDSUP-608 | C18: 54287 | D18: [SUP-699]User properties birthday has changed in Clevertap again | E18: Jack: Warin Kesorn | F18: 61a98e8e744c4d00693281d1 | G18: Thanakrit Chanthaworn | H18: 712020:3fc982cb-c268-4f1d-9265-d3dd8fb08304 | I18: Medium | J18: Done | L18: 27/May/26 5:43 PM | M18: 02/Jun/26 7:04 PM | N18: 01/Jun/26 12:00 AM | P18: CleverTap | Q18: prod-issue | R18: rr-app | V18: [Dev][All Project] Sprint 25
A19: Bug | B19: DPE-644 | C19: 54280 | D19: [S3][RR-BOF][ATN] Campaign Issue Point flow is not working properly | E19: Mai:Sateta Abvanawong | F19: 64000e4f15d668edd8edc7ea | G19: Plai Thanaporn Rimnong-ang | H19: 62c2a5acefb17d6ce62e41bf | I19: Medium | J19: Closed | L19: 27/May/26 12:51 PM | M19: 01/Jun/26 3:06 PM | V19: [Dev][RD][New PE] Sprint 25
A20: Bug | B20: DPE-643 | C20: 54275 | D20: [S3][PL] Get Internal Server Error when reverse transaction | E20: Mai:Sateta Abvanawong | F20: 64000e4f15d668edd8edc7ea | G20: Plai Thanaporn Rimnong-ang | H20: 62c2a5acefb17d6ce62e41bf | I20: Medium | J20: Closed | L20: 27/May/26 11:19 AM | M20: 28/May/26 4:58 PM | V20: [Dev][RD][New PE] Sprint 25
A21: Bug | B21: DPE-642 | C21: 54272 | D21: [S4][REM] Data source is incorrect for refund coupon flow | E21: Moss : Kittapath Sangvikukit | F21: 712020:b33baa03-2b29-4662-9923-dbdc2bbf980d | G21: Plai Thanaporn Rimnong-ang | H21: 62c2a5acefb17d6ce62e41bf | I21: Medium | J21: Closed ( Change Request) | L21: 27/May/26 10:34 AM | M21: 28/May/26 4:58 PM | V21: [Dev][RD][New PE] Sprint 25
A22: Story | B22: RDAPS-480 | C22: 54264 | D22: [Dev][RD][SA] Meeting Sprint25 | E22: Aom: Pornsawan Polnyiem | F22: 5d2ed694a666040c85096e17 | G22: Aom: Pornsawan Polnyiem | H22: 5d2ed694a666040c85096e17 | I22: Medium | J22: Done | L22: 27/May/26 9:15 AM | M22: 01/Jun/26 10:12 AM | O22: 8 | V22: [Dev][All Project] Sprint 25
A23: Sub-task | B23: DPE-641 | C23: 54261 | D23: Test execution | E23: Plai Thanaporn Rimnong-ang | F23: 62c2a5acefb17d6ce62e41bf | G23: Aom: Pornsawan Polnyiem | H23: 5d2ed694a666040c85096e17 | I23: Medium | J23: Done | L23: 26/May/26 11:59 PM | M23: 01/Jun/26 2:50 PM | V23: [Dev][RD][New PE] Sprint 21 | W23: [Dev][RD][New PE] Sprint 22 | X23: [Dev][RD][New PE] Sprint 23 | Y23: [Dev][RD][New PE] Sprint 24 | Z23: [Dev][RD][New PE] Sprint 25
A24: Sub-task | B24: DPE-640 | C24: 54260 | D24: Create test case | E24: Plai Thanaporn Rimnong-ang | F24: 62c2a5acefb17d6ce62e41bf | G24: Aom: Pornsawan Polnyiem | H24: 5d2ed694a666040c85096e17 | I24: Medium | J24: Done | L24: 26/May/26 11:59 PM | M24: 01/Jun/26 2:50 PM | V24: [Dev][RD][New PE] Sprint 21 | W24: [Dev][RD][New PE] Sprint 22 | X24: [Dev][RD][New PE] Sprint 23 | Y24: [Dev][RD][New PE] Sprint 24 | Z24: [Dev][RD][New PE] Sprint 25
A25: Sub-task | B25: DPE-639 | C25: 54259 | D25: Test execution | E25: Plai Thanaporn Rimnong-ang | F25: 62c2a5acefb17d6ce62e41bf | G25: Aom: Pornsawan Polnyiem | H25: 5d2ed694a666040c85096e17 | I25: Medium | J25: Done | L25: 26/May/26 11:51 PM | M25: 01/Jun/26 2:51 PM | V25: [Dev][RD][New PE] Sprint 21 | W25: [Dev][RD][New PE] Sprint 22 | X25: [Dev][RD][New PE] Sprint 23 | Y25: [Dev][RD][New PE] Sprint 24 | Z25: [Dev][RD][New PE] Sprint 25
A26: Sub-task | B26: DPE-638 | C26: 54258 | D26: Create test case | E26: Plai Thanaporn Rimnong-ang | F26: 62c2a5acefb17d6ce62e41bf | G26: Aom: Pornsawan Polnyiem | H26: 5d2ed694a666040c85096e17 | I26: Medium | J26: Done | L26: 26/May/26 11:51 PM | M26: 26/May/26 11:51 PM | V26: [Dev][RD][New PE] Sprint 21 | W26: [Dev][RD][New PE] Sprint 22 | X26: [Dev][RD][New PE] Sprint 23 | Y26: [Dev][RD][New PE] Sprint 24 | Z26: [Dev][RD][New PE] Sprint 25
A27: Sub-task | B27: DPE-637 | C27: 54255 | D27: Test execution | E27: Plai Thanaporn Rimnong-ang | F27: 62c2a5acefb17d6ce62e41bf | G27: Aom: Pornsawan Polnyiem | H27: 5d2ed694a666040c85096e17 | I27: Medium | J27: Done | L27: 26/May/26 11:27 PM | M27: 01/Jun/26 2:50 PM | V27: [Dev][RD][New PE] Sprint 21 | W27: [Dev][RD][New PE] Sprint 22 | X27: [Dev][RD][New PE] Sprint 23 | Y27: [Dev][RD][New PE] Sprint 24 | Z27: [Dev][RD][New PE] Sprint 25
A28: Sub-task | B28: DPE-636 | C28: 54254 | D28: Create test case | E28: Plai Thanaporn Rimnong-ang | F28: 62c2a5acefb17d6ce62e41bf | G28: Aom: Pornsawan Polnyiem | H28: 5d2ed694a666040c85096e17 | I28: Medium | J28: Done | L28: 26/May/26 11:27 PM | M28: 26/May/26 11:40 PM | V28: [Dev][RD][New PE] Sprint 21 | W28: [Dev][RD][New PE] Sprint 22 | X28: [Dev][RD][New PE] Sprint 23 | Y28: [Dev][RD][New PE] Sprint 24 | Z28: [Dev][RD][New PE] Sprint 25
A29: Sub-task | B29: DPE-635 | C29: 54253 | D29: Test execution | E29: Plai Thanaporn Rimnong-ang | F29: 62c2a5acefb17d6ce62e41bf | G29: Aek:Atiphat Nanthachitvanich | H29: 5d48155f5b8ea70c7e4f1b0f | I29: Medium | J29: Done | L29: 26/May/26 10:40 PM | M29: 26/May/26 10:40 PM | V29: [Dev][RD][New PE] Sprint 24 | W29: [Dev][RD][New PE] Sprint 25
A30: Sub-task | B30: DPE-634 | C30: 54252 | D30: Create test case | E30: Plai Thanaporn Rimnong-ang | F30: 62c2a5acefb17d6ce62e41bf | G30: Aek:Atiphat Nanthachitvanich | H30: 5d48155f5b8ea70c7e4f1b0f | I30: Medium | J30: Done | L30: 26/May/26 10:40 PM | M30: 26/May/26 10:40 PM | V30: [Dev][RD][New PE] Sprint 24 | W30: [Dev][RD][New PE] Sprint 25
A31: Sub-task | B31: DPE-633 | C31: 54250 | D31: Test execution | E31: Plai Thanaporn Rimnong-ang | F31: 62c2a5acefb17d6ce62e41bf | G31: Aom: Pornsawan Polnyiem | H31: 5d2ed694a666040c85096e17 | I31: Medium | J31: Done | L31: 26/May/26 9:57 PM | M31: 29/May/26 11:20 AM | V31: [Dev][RD][New PE] Sprint 24 | W31: [Dev][RD][New PE] Sprint 25
A32: Sub-task | B32: DPE-632 | C32: 54249 | D32: Create test case | E32: Plai Thanaporn Rimnong-ang | F32: 62c2a5acefb17d6ce62e41bf | G32: Aom: Pornsawan Polnyiem | H32: 5d2ed694a666040c85096e17 | I32: Medium | J32: Done | L32: 26/May/26 9:57 PM | M32: 28/May/26 3:46 PM | V32: [Dev][RD][New PE] Sprint 24 | W32: [Dev][RD][New PE] Sprint 25
A33: Sub-task | B33: DPE-631 | C33: 54248 | D33: Test execution | E33: Plai Thanaporn Rimnong-ang | F33: 62c2a5acefb17d6ce62e41bf | G33: Aom: Pornsawan Polnyiem | H33: 5d2ed694a666040c85096e17 | I33: Medium | J33: Done | L33: 26/May/26 9:37 PM | M33: 28/May/26 3:35 PM | V33: [Dev][RD][New PE] Sprint 24 | W33: [Dev][RD][New PE] Sprint 25
A34: Sub-task | B34: DPE-630 | C34: 54247 | D34: Create test case | E34: Plai Thanaporn Rimnong-ang | F34: 62c2a5acefb17d6ce62e41bf | G34: Aom: Pornsawan Polnyiem | H34: 5d2ed694a666040c85096e17 | I34: Medium | J34: Done | L34: 26/May/26 9:37 PM | M34: 28/May/26 3:35 PM | V34: [Dev][RD][New PE] Sprint 24 | W34: [Dev][RD][New PE] Sprint 25
A35: Bug | B35: DPE-629 | C35: 54245 | D35: [S4][SSO-User] RABBIT_CARD_FACE_TYPE value on CleverTab is not correctly | E35: Mai:Sateta Abvanawong | F35: 64000e4f15d668edd8edc7ea | G35: Plai Thanaporn Rimnong-ang | H35: 62c2a5acefb17d6ce62e41bf | I35: Medium | J35: Closed | L35: 26/May/26 4:23 PM | M35: 28/May/26 4:58 PM | V35: [Dev][RD][New PE] Sprint 25
A36: Bug | B36: DPE-628 | C36: 54244 | D36: [S3][REM] Unable to refund coupon for zero point redeemed txn | E36: Moss : Kittapath Sangvikukit | F36: 712020:b33baa03-2b29-4662-9923-dbdc2bbf980d | G36: Plai Thanaporn Rimnong-ang | H36: 62c2a5acefb17d6ce62e41bf | I36: Medium | J36: Closed | L36: 26/May/26 4:18 PM | M36: 28/May/26 4:58 PM | V36: [Dev][RD][New PE] Sprint 25
A37: Test Execution | B37: QA-3080 | C37: 54241 | D37: [TX][Sprint #25][Member] Rabbit Sky API and Rabbit web member | E37: Pueng Prachpreeya | F37: 642a5328f8bc2116accac530 | G37: Pueng Prachpreeya | H37: 642a5328f8bc2116accac530 | I37: Medium | J37: In Progress | L37: 26/May/26 3:34 PM | M37: 27/May/26 10:45 AM | V37: [Dev][RD][New PE] Sprint 25
A38: Test Plan | B38: QA-3079 | C38: 54240 | D38: [TP][Sprint #25][Member] Rabbit Sky API and Rabbit Sky web member | G38: Pueng Prachpreeya | H38: 642a5328f8bc2116accac530 | I38: Medium | J38: To Do | L38: 26/May/26 3:29 PM | M38: 26/May/26 3:31 PM | V38: [Dev][RD][New PE] Sprint 25
A39: Story | B39: DEVRDSUP-605 | C39: 54238 | D39: [SUP-697]Group Rewards - Lucky Draw Apple_Jun26 | E39: Aom: Pornsawan Polnyiem | F39: 5d2ed694a666040c85096e17 | G39: Abhinaf Singh | H39: 712020:a81c99dd-d5cd-44bd-950a-32f4ff7d56ac | I39: Medium | J39: To Do | L39: 26/May/26 2:43 PM | M39: 04/Jun/26 10:28 AM | N39: 29/May/26 12:00 AM | P39: BURequest | Q39: groupReward | R39: rem | V39: [Dev][All Project] Sprint 25 | W39: [Dev][All Project] Sprint 26
A40: Story | B40: DEVRDSUP-604 | C40: 54188 | D40: [SUP-696]SUB : Disable Credit/Debit Card Payment for BBL Package (JUNE2026 Package) | E40: Aom: Pornsawan Polnyiem | F40: 5d2ed694a666040c85096e17 | G40: Thanakrit Chanthaworn | H40: 712020:3fc982cb-c268-4f1d-9265-d3dd8fb08304 | I40: Medium | J40: Done | L40: 26/May/26 10:31 AM | M40: 29/May/26 9:40 AM | N40: 29/May/26 12:00 AM | O40: 1 | P40: BURequest | Q40: sub | U40: 600 | V40: [Dev][All Project] Sprint 25
A41: Story | B41: DEV-10 | C41: 54186 | D41: [DEV][RD][HRS] Enhance package issue on Local | E41: A:Phongthorn | F41: 5b3c867ae263df2dc32f7e35 | G41: Zan : Isarapong Bulan | H41: 5d4814e9da0c4d0c789a4bb7 | I41: Medium | J41: Ready to Staging | L41: 26/May/26 10:26 AM | M41: 02/Jun/26 10:04 AM | N41: 01/Jun/26 12:00 AM | O41: 3 | U41: 28800 | V41: [Dev][RD][TechDebt] Sprint 25 | W41: [Dev][RD][TechDebt] Sprint 26
A42: Bug | B42: DPE-599 | C42: 54176 | D42: [S3][Redemption API] Able to redeem rewards with inactive merchant | E42: Moss : Kittapath Sangvikukit | F42: 712020:b33baa03-2b29-4662-9923-dbdc2bbf980d | G42: Plai Thanaporn Rimnong-ang | H42: 62c2a5acefb17d6ce62e41bf | I42: Medium | J42: Closed | L42: 25/May/26 2:08 PM | M42: 28/May/26 4:58 PM | V42: [Dev][RD][New PE] Sprint 25
A43: Story | B43: DEVRDECOM-250 | C43: 54168 | D43: [DEV][RD][Ecom] Regression Test | E43: Moss : Kittapath Sangvikukit | F43: 712020:b33baa03-2b29-4662-9923-dbdc2bbf980d | G43: Aek:Atiphat Nanthachitvanich | H43: 5d48155f5b8ea70c7e4f1b0f | I43: High | J43: Done | L43: 22/May/26 5:12 PM | M43: 29/May/26 10:22 AM | O43: 3 | P43: No-QA | Q43: rr-ecommerce-shopify | V43: [Dev][RD][Ecom] Sprint 25
A44: Story | B44: DEVRDSUP-602 | C44: 54167 | D44: [SUP-694][SUB] Urgent! CS-20260500028131>> รบกวนออกแพ็กเกจและ Mark used Order ID 20260509-0001238 // หักเงินแต่ไม่ได้แพ็กเกจ OPN ปรับสถานะจาก Failed --->> Paid เรียบร้อย | E44: Mac: Jarupong Pawichpongkul | F44: 62c2a16240923988ba097c14 | G44: Abhinaf Singh | H44: 712020:a81c99dd-d5cd-44bd-950a-32f4ff7d56ac | I44: Medium | J44: Done | L44: 22/May/26 5:00 PM | M44: 22/May/26 5:15 PM | O44: 1 | V44: [Dev][All Project] Sprint 25
A45: Story | B45: DPE-597 | C45: 54154 | D45: [Dev][RD][PE Proxy Scheduler] Implement Discord Error Notifications | E45: Aom: Pornsawan Polnyiem | F45: 5d2ed694a666040c85096e17 | G45: Aom: Pornsawan Polnyiem | H45: 5d2ed694a666040c85096e17 | I45: Medium | J45: To Do | L45: 22/May/26 9:17 AM | M45: 02/Jun/26 11:19 AM | P45: No-QA | Q45: point-engine-proxy-scheduler | V45: [Dev][RD][New PE] Sprint 25 | W45: [Dev][RD][New PE] Sprint 26
A46: Story | B46: RDAPS-479 | C46: 54146 | D46: [SA][RD][Adhoc] Consent Tracking Report for Legal Compliance | E46: Aek:Atiphat Nanthachitvanich | F46: 5d48155f5b8ea70c7e4f1b0f | G46: Aek:Atiphat Nanthachitvanich | H46: 5d48155f5b8ea70c7e4f1b0f | I46: Medium | J46: Done | L46: 21/May/26 3:53 PM | M46: 25/May/26 9:58 AM | O46: 1 | U46: 1800 | V46: [Dev][All Project] Sprint 25
A47: Bug | B47: DEVRDSUP-599 | C47: 54132 | D47: [SUP-643]Event Charged in Clevertap and data format mismatch | E47: Jack: Warin Kesorn | F47: 61a98e8e744c4d00693281d1 | G47: Thanakrit Chanthaworn | H47: 712020:3fc982cb-c268-4f1d-9265-d3dd8fb08304 | I47: Medium | J47: Resolved | L47: 21/May/26 9:57 AM | M47: 04/Jun/26 10:27 AM | P47: partner-loyalty | V47: [Dev][All Project] Sprint 25 | W47: [Dev][All Project] Sprint 26
A48: Story | B48: DPE-596 | C48: 54131 | D48: [Dev][RD][PE Middleware][UnitTest] Implement Unit Test Coverage for `GET /v1/wallets/{id}/point-history` | E48: Nim : muthita munmueang | F48: 712020:e80312b7-b5b0-43e8-b198-3d8fce4532bb | G48: Aom: Pornsawan Polnyiem | H48: 5d2ed694a666040c85096e17 | I48: Medium | J48: Done | L48: 21/May/26 9:48 AM | M48: 28/May/26 4:49 PM | N48: 22/May/26 12:00 AM | O48: 2 | P48: No-QA | Q48: point-engine-proxy | V48: [Dev][RD][New PE] Sprint 25
A49: Story | B49: DPE-595 | C49: 54130 | D49: [Dev][RD][PE Middleware][UnitTest] Implement Unit Test Coverage for `GET /v1/wallets/{id}/point-expiring` | E49: Moss : Kittapath Sangvikukit | F49: 712020:b33baa03-2b29-4662-9923-dbdc2bbf980d | G49: Aom: Pornsawan Polnyiem | H49: 5d2ed694a666040c85096e17 | I49: Medium | J49: Done | L49: 21/May/26 9:43 AM | M49: 28/May/26 4:48 PM | N49: 29/May/26 12:00 AM | P49: No-QA | Q49: point-engine-proxy | U49: 14400 | V49: [Dev][RD][New PE] Sprint 25
A50: Story | B50: DPE-594 | C50: 54129 | D50: [Dev][RD][PE Middleware][UnitTest] Implement Unit Test Coverage for `POST /v1/wallets/{id}/debit` | E50: Moss : Kittapath Sangvikukit | F50: 712020:b33baa03-2b29-4662-9923-dbdc2bbf980d | G50: Aom: Pornsawan Polnyiem | H50: 5d2ed694a666040c85096e17 | I50: Medium | J50: Done | L50: 21/May/26 9:42 AM | M50: 28/May/26 4:48 PM | N50: 29/May/26 12:00 AM | P50: No-QA | Q50: point-engine-proxy | U50: 14400 | V50: [Dev][RD][New PE] Sprint 25
A51: Story | B51: DPE-593 | C51: 54128 | D51: [Dev][RD][PE Middleware][UnitTest] Implement Unit Test Coverage for `POST /v1/wallets/{id}/credit` | E51: Moss : Kittapath Sangvikukit | F51: 712020:b33baa03-2b29-4662-9923-dbdc2bbf980d | G51: Aom: Pornsawan Polnyiem | H51: 5d2ed694a666040c85096e17 | I51: Medium | J51: Done | L51: 21/May/26 9:42 AM | M51: 28/May/26 4:48 PM | N51: 29/May/26 12:00 AM | P51: No-QA | Q51: point-engine-proxy | U51: 14400 | V51: [Dev][RD][New PE] Sprint 25
A52: Story | B52: DPE-592 | C52: 54127 | D52: [Dev][RD][PE Middleware][UnitTest] Implement Unit Test Coverage for `POST /v1/wallets/reversal` | E52: Nim : muthita munmueang | F52: 712020:e80312b7-b5b0-43e8-b198-3d8fce4532bb | G52: Aom: Pornsawan Polnyiem | H52: 5d2ed694a666040c85096e17 | I52: Medium | J52: Done | L52: 21/May/26 9:41 AM | M52: 28/May/26 4:49 PM | N52: 21/May/26 12:00 AM | O52: 2 | P52: No-QA | Q52: point-engine-proxy | V52: [Dev][RD][New PE] Sprint 25
A53: Story | B53: RDTHANA-500 | C53: 54124 | D53: [DEV][RD] Enhance generic transaction support request revert for void/fail transaction | E53: Mac: Jarupong Pawichpongkul | F53: 62c2a16240923988ba097c14 | G53: Zan : Isarapong Bulan | H53: 5d4814e9da0c4d0c789a4bb7 | I53: Highest | J53: Done | L53: 21/May/26 1:13 AM | M53: 29/May/26 9:35 AM | N53: 21/May/26 12:00 AM | O53: 3 | P53: No-QA | V53: [Dev][RD][Thana] Sprint 25
A54: Bug | B54: DPE-591 | C54: 54123 | D54: [S3][PE Proxy] Able to reverse point with invalid offer | E54: Moss : Kittapath Sangvikukit | F54: 712020:b33baa03-2b29-4662-9923-dbdc2bbf980d | G54: Plai Thanaporn Rimnong-ang | H54: 62c2a5acefb17d6ce62e41bf | I54: Medium | J54: Closed ( Change Request) | L54: 20/May/26 11:19 PM | M54: 22/May/26 10:54 AM | V54: [Dev][RD][New PE] Sprint 25
A55: Bug | B55: DPE-590 | C55: 54122 | D55: [S4][PE Proxy] The response contains an incorrect field name | E55: Moss : Kittapath Sangvikukit | F55: 712020:b33baa03-2b29-4662-9923-dbdc2bbf980d | G55: Plai Thanaporn Rimnong-ang | H55: 62c2a5acefb17d6ce62e41bf | I55: Medium | J55: Closed | L55: 20/May/26 10:48 PM | M55: 22/May/26 10:54 AM | V55: [Dev][RD][New PE] Sprint 25
A56: Story | B56: DEVRDSUP-597 | C56: 54093 | D56: [SUP-690][SUB] Urgent! CS-20260500028044>> รบกวนออกแพ็กเกจ Order ID 20260519-0002216 // หักเงินแต่ไม่ได้แพ็กเกจ OPN ปรับสถานะจาก Failed --->> Paid เรียบร้อย | E56: Mac: Jarupong Pawichpongkul | F56: 62c2a16240923988ba097c14 | G56: Abhinaf Singh | H56: 712020:a81c99dd-d5cd-44bd-950a-32f4ff7d56ac | I56: Medium | J56: Done | L56: 20/May/26 5:36 PM | M56: 21/May/26 1:54 PM | N56: 25/May/26 12:00 AM | O56: 1 | P56: bts | Q56: rr-app | R56: sub | V56: [Dev][All Project] Sprint 25
A57: Bug | B57: DEVRDSUP-596 | C57: 54091 | D57: [SUP-689]NBO][Rewards][Subscription] - Upload code double | E57: Aom: Pornsawan Polnyiem | F57: 5d2ed694a666040c85096e17 | G57: Abhinaf Singh | H57: 712020:a81c99dd-d5cd-44bd-950a-32f4ff7d56ac | I57: Low | J57: ACCEPTED | L57: 20/May/26 5:12 PM | M57: 04/Jun/26 10:30 AM | N57: 25/Jun/26 12:00 AM | P57: rem | Q57: sub | V57: [Dev][All Project] Sprint 25 | W57: [Dev][All Project] Sprint 26
A58: Bug | B58: DEVRDSUP-595 | C58: 54089 | D58: [SUP-688]Event properties are not appearing in the user profile | E58: Moss : Kittapath Sangvikukit | F58: 712020:b33baa03-2b29-4662-9923-dbdc2bbf980d | G58: Thanakrit Chanthaworn | H58: 712020:3fc982cb-c268-4f1d-9265-d3dd8fb08304 | I58: Medium | J58: Resolved | L58: 20/May/26 4:47 PM | M58: 04/Jun/26 10:27 AM | N58: 09/Jun/26 12:00 AM | P58: CleverTap | Q58: prod-issue | R58: rr-app | V58: [Dev][All Project] Sprint 25 | W58: [Dev][All Project] Sprint 26
A59: Story | B59: DEVRDSUP-594 | C59: 54087 | D59: [SUP-625][RR Member Account] CS-20260300026232 // Cannot add RC into RR Member account [RD SSO show- "Rabbit card already in use." / Member ID 30245337 | E59: A:Phongthorn | F59: 5b3c867ae263df2dc32f7e35 | G59: Abhinaf Singh | H59: 712020:a81c99dd-d5cd-44bd-950a-32f4ff7d56ac | I59: Medium | J59: In Review | L59: 20/May/26 4:35 PM | M59: 04/Jun/26 10:29 AM | O59: 1 | U59: 7200 | V59: [Dev][All Project] Sprint 25 | W59: [Dev][All Project] Sprint 26
A60: Story | B60: DEVRDECOM-249 | C60: 54086 | D60: [DEV][RD][Ecom] Add Shopify customers/create webhook handler to sync shopify_members and update Shopify customer profile | E60: A:Phongthorn | F60: 5b3c867ae263df2dc32f7e35 | G60: Aek:Atiphat Nanthachitvanich | H60: 5d48155f5b8ea70c7e4f1b0f | I60: High | J60: Done | L60: 20/May/26 4:33 PM | M60: 29/May/26 10:22 AM | N60: 22/May/26 12:00 AM | O60: 5 | P60: No-QA | Q60: rr-ecommerce-shopify | U60: 57600 | V60: [Dev][RD][Ecom] Sprint 25
A61: Bug | B61: DPE-589 | C61: 54079 | D61: [S2][PE Proxy] Unable to reverse/refund point | E61: Nim : muthita munmueang | F61: 712020:e80312b7-b5b0-43e8-b198-3d8fce4532bb | G61: Plai Thanaporn Rimnong-ang | H61: 62c2a5acefb17d6ce62e41bf | I61: Medium | J61: Closed | L61: 20/May/26 9:45 AM | M61: 22/May/26 10:54 AM | V61: [Dev][RD][New PE] Sprint 25
A62: Bug | B62: DPE-588 | C62: 54073 | D62: [S4][SSO-User] Marking data on CT detail is incorrect | E62: Mai:Sateta Abvanawong | F62: 64000e4f15d668edd8edc7ea | G62: Plai Thanaporn Rimnong-ang | H62: 62c2a5acefb17d6ce62e41bf | I62: Medium | J62: Closed | L62: 19/May/26 5:01 PM | M62: 28/May/26 5:07 PM | N62: 25/May/26 12:00 AM | V62: [Dev][RD][New PE] Sprint 25
A63: Bug | B63: DPE-587 | C63: 54070 | D63: [S2][PE Proxy] Unable to debit point | E63: Arm:Worawat Chotipongchoawalit | F63: 712020:2195d849-5cdb-4ec8-866f-e82a3528bff7 | G63: Plai Thanaporn Rimnong-ang | H63: 62c2a5acefb17d6ce62e41bf | I63: Medium | J63: Closed | L63: 19/May/26 3:26 PM | M63: 22/May/26 10:54 AM | V63: [Dev][RD][New PE] Sprint 25
A64: Bug | B64: DPE-586 | C64: 54069 | D64: [S2][PE Proxy] Unable to credit point | E64: Arm:Worawat Chotipongchoawalit | F64: 712020:2195d849-5cdb-4ec8-866f-e82a3528bff7 | G64: Plai Thanaporn Rimnong-ang | H64: 62c2a5acefb17d6ce62e41bf | I64: Medium | J64: Closed | L64: 19/May/26 3:20 PM | M64: 22/May/26 10:53 AM | V64: [Dev][RD][New PE] Sprint 25
A65: Sub-task | B65: RDTHANA-499 | C65: 54064 | D65: [QA] Test Execution | E65: Max (QA) : Surawut Sae-nim | F65: 62d4e007098e73c4e5ee0d8d | G65: Max (QA) : Surawut Sae-nim | H65: 62d4e007098e73c4e5ee0d8d | I65: Medium | J65: Done | L65: 19/May/26 1:45 PM | M65: 19/May/26 5:53 PM | V65: [Dev][RD][Thana] Sprint 24 | W65: [Dev][RD][Thana] Sprint 25
A66: Sub-task | B66: RDTHANA-497 | C66: 54062 | D66: [QA] Test Execution | E66: Max (QA) : Surawut Sae-nim | F66: 62d4e007098e73c4e5ee0d8d | G66: Max (QA) : Surawut Sae-nim | H66: 62d4e007098e73c4e5ee0d8d | I66: Medium | J66: Done | L66: 19/May/26 1:44 PM | M66: 20/May/26 9:29 AM | V66: [Dev][RD][Thana] Sprint 23 | W66: [Dev][RD][Thana] Sprint 23 | X66: [Dev][RD][Thana] Sprint 24 | Y66: [Dev][RD][Thana] Sprint 24 | Z66: [Dev][RD][Thana] Sprint 25
A67: Sub-task | B67: RDTHANA-496 | C67: 54061 | D67: [QA] Test Execution | E67: Max (QA) : Surawut Sae-nim | F67: 62d4e007098e73c4e5ee0d8d | G67: Max (QA) : Surawut Sae-nim | H67: 62d4e007098e73c4e5ee0d8d | I67: Medium | J67: Done | L67: 19/May/26 1:44 PM | M67: 19/May/26 5:09 PM | V67: [Dev][RD][Thana] Sprint 23 | W67: [Dev][RD][Thana] Sprint 24 | X67: [Dev][RD][Thana] Sprint 24 | Y67: [Dev][RD][Thana] Sprint 25
A68: Sub-task | B68: RDTHANA-495 | C68: 54060 | D68: [QA] Test Execution | E68: Max (QA) : Surawut Sae-nim | F68: 62d4e007098e73c4e5ee0d8d | G68: Max (QA) : Surawut Sae-nim | H68: 62d4e007098e73c4e5ee0d8d | I68: Medium | J68: Done | L68: 19/May/26 1:44 PM | M68: 19/May/26 5:07 PM | V68: [Dev][RD][Thana] Sprint 23 | W68: [Dev][RD][Thana] Sprint 23 | X68: [Dev][RD][Thana] Sprint 24 | Y68: [Dev][RD][Thana] Sprint 24 | Z68: [Dev][RD][Thana] Sprint 25
A69: Sub-task | B69: RDTHANA-494 | C69: 54059 | D69: [QA] Test Execution | E69: Max (QA) : Surawut Sae-nim | F69: 62d4e007098e73c4e5ee0d8d | G69: Max (QA) : Surawut Sae-nim | H69: 62d4e007098e73c4e5ee0d8d | I69: Medium | J69: Done | L69: 19/May/26 1:43 PM | M69: 19/May/26 6:08 PM | V69: [Dev][RD][Thana] Sprint 22 | W69: [Dev][RD][Thana] Sprint 23 | X69: [Dev][RD][Thana] Sprint 23 | Y69: [Dev][RD][Thana] Sprint 24 | Z69: [Dev][RD][Thana] Sprint 24 | AA69: [Dev][RD][Thana] Sprint 25
A70: Sub-task | B70: DPE-585 | C70: 54058 | D70: Test execution | E70: Plai Thanaporn Rimnong-ang | F70: 62c2a5acefb17d6ce62e41bf | G70: Jack: Warin Kesorn | H70: 61a98e8e744c4d00693281d1 | I70: Medium | J70: Done | L70: 19/May/26 1:32 PM | M70: 21/May/26 2:23 PM | V70: [Dev][RD][New PE] Sprint 25
A71: Sub-task | B71: DPE-584 | C71: 54057 | D71: Create test case | E71: Plai Thanaporn Rimnong-ang | F71: 62c2a5acefb17d6ce62e41bf | G71: Jack: Warin Kesorn | H71: 61a98e8e744c4d00693281d1 | I71: Medium | J71: Done | L71: 19/May/26 1:32 PM | M71: 20/May/26 10:13 PM | V71: [Dev][RD][New PE] Sprint 25
A72: Sub-task | B72: DPE-583 | C72: 54056 | D72: Test execution | E72: Plai Thanaporn Rimnong-ang | F72: 62c2a5acefb17d6ce62e41bf | G72: Jack: Warin Kesorn | H72: 61a98e8e744c4d00693281d1 | I72: Medium | J72: Done | L72: 19/May/26 1:32 PM | M72: 20/May/26 8:32 PM | V72: [Dev][RD][New PE] Sprint 25
A73: Sub-task | B73: DPE-582 | C73: 54055 | D73: Create test case | E73: Plai Thanaporn Rimnong-ang | F73: 62c2a5acefb17d6ce62e41bf | G73: Jack: Warin Kesorn | H73: 61a98e8e744c4d00693281d1 | I73: Medium | J73: Done | L73: 19/May/26 1:32 PM | M73: 19/May/26 4:46 PM | V73: [Dev][RD][New PE] Sprint 25
A74: Sub-task | B74: DPE-581 | C74: 54054 | D74: Test execution | E74: Plai Thanaporn Rimnong-ang | F74: 62c2a5acefb17d6ce62e41bf | G74: Jack: Warin Kesorn | H74: 61a98e8e744c4d00693281d1 | I74: Medium | J74: Done | L74: 19/May/26 1:32 PM | M74: 20/May/26 8:58 PM | V74: [Dev][RD][New PE] Sprint 25
A75: Sub-task | B75: DPE-580 | C75: 54053 | D75: Create test case | E75: Plai Thanaporn Rimnong-ang | F75: 62c2a5acefb17d6ce62e41bf | G75: Jack: Warin Kesorn | H75: 61a98e8e744c4d00693281d1 | I75: Medium | J75: Done | L75: 19/May/26 1:32 PM | M75: 19/May/26 4:46 PM | V75: [Dev][RD][New PE] Sprint 25
A76: Story | B76: DEVRDSUP-592 | C76: 54052 | D76: [SUP-686][SUB] Receipt is not generated after SUB transaction is made (TXN Date 18 May 2026) | E76: Aom: Pornsawan Polnyiem | F76: 5d2ed694a666040c85096e17 | G76: Thanakrit Chanthaworn | H76: 712020:3fc982cb-c268-4f1d-9265-d3dd8fb08304 | I76: Medium | J76: Done | L76: 19/May/26 12:05 PM | M76: 20/May/26 11:17 AM | O76: 1 | V76: [Dev][All Project] Sprint 25
A77: Story | B77: RDAPS-478 | C77: 54045 | D77: [Dev][VGI][VGIONE] Update Meta API version | E77: Jack: Warin Kesorn | F77: 61a98e8e744c4d00693281d1 | G77: Jack: Warin Kesorn | H77: 61a98e8e744c4d00693281d1 | I77: Highest | J77: Done | L77: 18/May/26 4:22 PM | M77: 27/May/26 9:52 AM | O77: 5 | P77: vgi-one | V77: [Dev][All Project] Sprint 25
A78: Story | B78: RDAPS-477 | C78: 54039 | D78: [DEV][RD] Support DevOps | E78: A:Phongthorn | F78: 5b3c867ae263df2dc32f7e35 | G78: Aek:Atiphat Nanthachitvanich | H78: 5d48155f5b8ea70c7e4f1b0f | I78: Medium | J78: Done | L78: 18/May/26 2:51 PM | M78: 28/May/26 11:57 AM | O78: 1 | U78: 7200 | V78: [Dev][All Project] Sprint 25
A79: Story | B79: DEVRDSS-4 | C79: 54038 | D79: [SA][RD][Samsung] Analysis and Design | E79: A:Phongthorn | F79: 5b3c867ae263df2dc32f7e35 | G79: Aek:Atiphat Nanthachitvanich | H79: 5d48155f5b8ea70c7e4f1b0f | I79: Medium | J79: Done | L79: 18/May/26 2:37 PM | M79: 29/May/26 10:20 AM | O79: 1 | V79: [Dev][RD][Samsung] Sprint 25
A80: Story | B80: DEV-5 | C80: 54037 | D80: [DEV][RD][TechDebt] Enhance command re register support by options | E80: Arm:Worawat Chotipongchoawalit | F80: 712020:2195d849-5cdb-4ec8-866f-e82a3528bff7 | G80: Zan : Isarapong Bulan | H80: 5d4814e9da0c4d0c789a4bb7 | I80: Medium | J80: Ready To Test | L80: 18/May/26 1:45 PM | M80: 02/Jun/26 10:04 AM | N80: 20/May/26 12:00 AM | P80: hr-solution | Q80: No-QA | V80: [Dev][RD][TechDebt] Sprint 25 | W80: [Dev][RD][TechDebt] Sprint 26
A81: Story | B81: RDTHANA-493 | C81: 54033 | D81: [DEV][RD][TDM][POC] Get Shopify data for BU Dashboard | E81: Mac: Jarupong Pawichpongkul | F81: 62c2a16240923988ba097c14 | G81: Zan : Isarapong Bulan | H81: 5d4814e9da0c4d0c789a4bb7 | I81: Medium | J81: Ready to Staging | L81: 18/May/26 10:43 AM | M81: 02/Jun/26 9:19 AM | N81: 26/May/26 12:00 AM | O81: 8 | P81: No-QA | U81: 86400 | V81: [Dev][RD][Thana] Sprint 25 | W81: [Dev][RD][Thana] Sprint 26
A82: Story | B82: RDTHANA-492 | C82: 54027 | D82: [DEV][RD][TDM] Enhance Generic transaction | E82: Mac: Jarupong Pawichpongkul | F82: 62c2a16240923988ba097c14 | G82: Zan : Isarapong Bulan | H82: 5d4814e9da0c4d0c789a4bb7 | I82: Medium | J82: Ready To Test | L82: 18/May/26 9:56 AM | M82: 02/Jun/26 9:19 AM | N82: 19/May/26 12:00 AM | O82: 1 | P82: No-QA | U82: 7200 | V82: [Dev][RD][Thana] Sprint 25 | W82: [Dev][RD][Thana] Sprint 26
A83: Story | B83: DPE-579 | C83: 54025 | D83: [DEV][RD][NPE] Investigate member count discrepancy between DA and RD due to email matching issues | E83: Zan : Isarapong Bulan | F83: 5d4814e9da0c4d0c789a4bb7 | G83: Zan : Isarapong Bulan | H83: 5d4814e9da0c4d0c789a4bb7 | I83: Medium | J83: In Review | L83: 18/May/26 9:43 AM | M83: 02/Jun/26 11:11 AM | O83: 8 | V83: [Dev][RD][New PE] Sprint 25 | W83: [Dev][RD][New PE] Sprint 26
A84: Sub-task | B84: DPE-576 | C84: 54019 | D84: Test execution | E84: Plai Thanaporn Rimnong-ang | F84: 62c2a5acefb17d6ce62e41bf | G84: Jack: Warin Kesorn | H84: 61a98e8e744c4d00693281d1 | I84: Medium | J84: Done | L84: 17/May/26 4:26 PM | M84: 25/May/26 7:09 PM | V84: [Dev][RD][New PE] Sprint 24 | W84: [Dev][RD][New PE] Sprint 25
A85: Sub-task | B85: DPE-575 | C85: 54018 | D85: Create test case | E85: Plai Thanaporn Rimnong-ang | F85: 62c2a5acefb17d6ce62e41bf | G85: Jack: Warin Kesorn | H85: 61a98e8e744c4d00693281d1 | I85: Medium | J85: Done | L85: 17/May/26 4:26 PM | M85: 25/May/26 7:09 PM | V85: [Dev][RD][New PE] Sprint 24 | W85: [Dev][RD][New PE] Sprint 25
A86: Sub-task | B86: DPE-574 | C86: 54017 | D86: Test execution | E86: Plai Thanaporn Rimnong-ang | F86: 62c2a5acefb17d6ce62e41bf | G86: Aom: Pornsawan Polnyiem | H86: 5d2ed694a666040c85096e17 | I86: Medium | J86: Done | L86: 17/May/26 4:26 PM | M86: 21/May/26 2:25 PM | V86: [Dev][RD][New PE] Sprint 23 | W86: [Dev][RD][New PE] Sprint 24 | X86: [Dev][RD][New PE] Sprint 25
A87: Sub-task | B87: DPE-573 | C87: 54016 | D87: Create test case | E87: Plai Thanaporn Rimnong-ang | F87: 62c2a5acefb17d6ce62e41bf | G87: Aom: Pornsawan Polnyiem | H87: 5d2ed694a666040c85096e17 | I87: Medium | J87: Done | L87: 17/May/26 4:26 PM | M87: 20/May/26 10:13 PM | V87: [Dev][RD][New PE] Sprint 23 | W87: [Dev][RD][New PE] Sprint 24 | X87: [Dev][RD][New PE] Sprint 25
A88: Sub-task | B88: DPE-572 | C88: 54015 | D88: Test execution | E88: Plai Thanaporn Rimnong-ang | F88: 62c2a5acefb17d6ce62e41bf | G88: Jack: Warin Kesorn | H88: 61a98e8e744c4d00693281d1 | I88: Medium | J88: Done | L88: 17/May/26 4:26 PM | M88: 21/May/26 2:23 PM | V88: [Dev][RD][New PE] Sprint 23 | W88: [Dev][RD][New PE] Sprint 24 | X88: [Dev][RD][New PE] Sprint 25
A89: Sub-task | B89: DPE-571 | C89: 54014 | D89: Create test case | E89: Plai Thanaporn Rimnong-ang | F89: 62c2a5acefb17d6ce62e41bf | G89: Jack: Warin Kesorn | H89: 61a98e8e744c4d00693281d1 | I89: Medium | J89: Done | L89: 17/May/26 4:26 PM | M89: 20/May/26 2:40 PM | V89: [Dev][RD][New PE] Sprint 23 | W89: [Dev][RD][New PE] Sprint 24 | X89: [Dev][RD][New PE] Sprint 25
A90: Sub-task | B90: DPE-570 | C90: 53996 | D90: Test execution | E90: Plai Thanaporn Rimnong-ang | F90: 62c2a5acefb17d6ce62e41bf | G90: Aom: Pornsawan Polnyiem | H90: 5d2ed694a666040c85096e17 | I90: Medium | J90: Done | L90: 17/May/26 11:15 AM | M90: 01/Jun/26 4:07 PM | V90: [Dev][RD][New PE] Sprint 22 | W90: [Dev][RD][New PE] Sprint 23 | X90: [Dev][RD][New PE] Sprint 24 | Y90: [Dev][RD][New PE] Sprint 25
A91: Sub-task | B91: DPE-569 | C91: 53995 | D91: Create test case | E91: Plai Thanaporn Rimnong-ang | F91: 62c2a5acefb17d6ce62e41bf | G91: Aom: Pornsawan Polnyiem | H91: 5d2ed694a666040c85096e17 | I91: Medium | J91: Done | L91: 17/May/26 11:15 AM | M91: 17/May/26 4:13 PM | V91: [Dev][RD][New PE] Sprint 22 | W91: [Dev][RD][New PE] Sprint 23 | X91: [Dev][RD][New PE] Sprint 24 | Y91: [Dev][RD][New PE] Sprint 25
A92: Sub-task | B92: DPE-568 | C92: 53994 | D92: Test execution | E92: Plai Thanaporn Rimnong-ang | F92: 62c2a5acefb17d6ce62e41bf | G92: Aom: Pornsawan Polnyiem | H92: 5d2ed694a666040c85096e17 | I92: Medium | J92: Done | L92: 17/May/26 11:11 AM | M92: 25/May/26 7:09 PM | V92: [Dev][RD][New PE] Sprint 24 | W92: [Dev][RD][New PE] Sprint 25
A93: Sub-task | B93: DPE-567 | C93: 53993 | D93: Create test case | E93: Plai Thanaporn Rimnong-ang | F93: 62c2a5acefb17d6ce62e41bf | G93: Aom: Pornsawan Polnyiem | H93: 5d2ed694a666040c85096e17 | I93: Medium | J93: Done | L93: 17/May/26 11:11 AM | M93: 25/May/26 7:09 PM | V93: [Dev][RD][New PE] Sprint 24 | W93: [Dev][RD][New PE] Sprint 25
A94: Sub-task | B94: DPE-566 | C94: 53992 | D94: Test execution | E94: Plai Thanaporn Rimnong-ang | F94: 62c2a5acefb17d6ce62e41bf | G94: Aom: Pornsawan Polnyiem | H94: 5d2ed694a666040c85096e17 | I94: Medium | J94: Done | L94: 17/May/26 11:11 AM | M94: 25/May/26 2:45 PM | V94: [Dev][RD][New PE] Sprint 23 | W94: [Dev][RD][New PE] Sprint 24 | X94: [Dev][RD][New PE] Sprint 25
A95: Sub-task | B95: DPE-565 | C95: 53991 | D95: Test execution | E95: Plai Thanaporn Rimnong-ang | F95: 62c2a5acefb17d6ce62e41bf | G95: Aom: Pornsawan Polnyiem | H95: 5d2ed694a666040c85096e17 | I95: Medium | J95: Done | L95: 17/May/26 11:11 AM | M95: 26/May/26 2:35 PM | V95: [Dev][RD][New PE] Sprint 22 | W95: [Dev][RD][New PE] Sprint 23 | X95: [Dev][RD][New PE] Sprint 24 | Y95: [Dev][RD][New PE] Sprint 25
A96: Sub-task | B96: DPE-564 | C96: 53990 | D96: Test execution | E96: Plai Thanaporn Rimnong-ang | F96: 62c2a5acefb17d6ce62e41bf | G96: Aom: Pornsawan Polnyiem | H96: 5d2ed694a666040c85096e17 | I96: Medium | J96: Done | L96: 17/May/26 11:11 AM | M96: 28/May/26 11:21 AM | V96: [Dev][RD][New PE] Sprint 24 | W96: [Dev][RD][New PE] Sprint 25
A97: Sub-task | B97: DPE-563 | C97: 53989 | D97: Test execution | E97: Plai Thanaporn Rimnong-ang | F97: 62c2a5acefb17d6ce62e41bf | G97: Aom: Pornsawan Polnyiem | H97: 5d2ed694a666040c85096e17 | I97: Medium | J97: Done | L97: 17/May/26 11:11 AM | M97: 25/May/26 7:09 PM | V97: [Dev][RD][New PE] Sprint 24 | W97: [Dev][RD][New PE] Sprint 25
A98: Sub-task | B98: DPE-562 | C98: 53988 | D98: Create test case | E98: Plai Thanaporn Rimnong-ang | F98: 62c2a5acefb17d6ce62e41bf | G98: Aom: Pornsawan Polnyiem | H98: 5d2ed694a666040c85096e17 | I98: Medium | J98: Done | L98: 17/May/26 11:11 AM | M98: 22/May/26 4:47 PM | V98: [Dev][RD][New PE] Sprint 23 | W98: [Dev][RD][New PE] Sprint 24 | X98: [Dev][RD][New PE] Sprint 25
A99: Sub-task | B99: DPE-561 | C99: 53987 | D99: Create test case | E99: Plai Thanaporn Rimnong-ang | F99: 62c2a5acefb17d6ce62e41bf | G99: Aom: Pornsawan Polnyiem | H99: 5d2ed694a666040c85096e17 | I99: Medium | J99: Done | L99: 17/May/26 11:11 AM | M99: 26/May/26 7:37 PM | V99: [Dev][RD][New PE] Sprint 24 | W99: [Dev][RD][New PE] Sprint 25
A100: Sub-task | B100: DPE-560 | C100: 53986 | D100: Create test case | E100: Plai Thanaporn Rimnong-ang | F100: 62c2a5acefb17d6ce62e41bf | G100: Aom: Pornsawan Polnyiem | H100: 5d2ed694a666040c85096e17 | I100: Medium | J100: Done | L100: 17/May/26 11:11 AM | M100: 21/May/26 5:35 PM | V100: [Dev][RD][New PE] Sprint 22 | W100: [Dev][RD][New PE] Sprint 23 | X100: [Dev][RD][New PE] Sprint 24 | Y100: [Dev][RD][New PE] Sprint 25
...

Sheet Summarize Sprint 24
A1: Column 1 | B1: Total Stories Point | C1: Total Manhour | D1: Point Done | E1: Manhour Done | F1: Note
A2: 4 May - 15 May
A3: Dev Resource Available | B3: 21 | C3: 462
A4: Meeting Planned | F4: Ref
A5: Additional Meeting | F5: Ref
A6: Deployment | C6: 2 | F6: 2 ครั้ง 1. 1 คน 2. 2 คน
A7: Development Sprint Total | B7: =SUM('Sprint 24'!O:O) -> 516 | C7: =ROUND(SUM('Sprint 24'!U:U)/3600,2) -> 709.5 | D7: =SUMIF('Sprint 24'!J:J, "Done", 'Sprint 24'!O:O) -> 85 | E7: =ROUND(SUMIF('Sprint 24'!J:J, "Done", 'Sprint 24'!U:U)/3600,2) -> 102.5
A9: Ad-hoc Mid Sprint | B9: 0 | C9: =IFERROR(__xludf.DUMMYFUNCTION("ROUND(IFERROR(SUM(FILTER('Sprint 24'!U:U, ('Sprint 24'!Q:Q = ""mid-sprint"")))/3600,0),2)"),0.0) -> 0 | D9: =IFERROR(__xludf.DUMMYFUNCTION("IFERROR(SUM(FILTER('Sprint 24'!O:O, (('Sprint 24'!J:J = ""Done"")) * ('Sprint 24'!Q:Q = ""mid-sprint""))),0)"),0.0) -> 0 | E9: =IFERROR(__xludf.DUMMYFUNCTION("ROUND(IFERROR(SUM(FILTER('Sprint 24'!U:U, (('Sprint 24'!J:J = ""Done"")) * ('Sprint 24'!P:P = ""mid-sprint"")))/3600,0),2)"),0.0) -> 0 | F9: 2 tasks
A10: Requirement changes after refinement? | B10: =IFERROR(__xludf.DUMMYFUNCTION("ROUND(IFERROR(SUM(FILTER('Sprint 24'!U:U, ('Sprint 24'!Q:Q = ""change-request"")))/3600,0),2)"),0.0) -> 0 | D10: =IFERROR(__xludf.DUMMYFUNCTION("IFERROR(SUM(FILTER('Sprint 24'!O:O, (('Sprint 24'!J:J = ""Done"")) * ('Sprint 24'!Q:Q = ""change-request""))),0)"),0.0) -> 0 | E10: =IFERROR(__xludf.DUMMYFUNCTION("ROUND(IFERROR(SUM(FILTER('Sprint 24'!U:U, (('Sprint 24'!J:J = ""Done"")) * ('Sprint 24'!Q:Q = ""change-request"")))/3600,0),2)"),0.0) -> 0 | F10: 0 tasks
A12: Aek | B12: =IFERROR(__xludf.DUMMYFUNCTION("IFERROR(SUM(FILTER('Sprint 24'!O:O, ('Sprint 24'!E:E = ""Aek:Atiphat Nanthachitvanich""))),0)"),35.0) -> 35 | C12: =IFERROR(__xludf.DUMMYFUNCTION("ROUND(IFERROR(SUM(FILTER('Sprint 24'!U:U, ('Sprint 24'!E:E = ""Aek:Atiphat Nanthachitvanich"")))/3600,0),2)"),55.33) -> 55.33 | D12: =IFERROR(__xludf.DUMMYFUNCTION("IFERROR(SUM(FILTER('Sprint 24'!O:O, (('Sprint 24'!J:J = ""Done"")) * ('Sprint 24'!E:E = ""Aek:Atiphat Nanthachitvanich""))),0)"),13.0) -> 13 | E12: =IFERROR(__xludf.DUMMYFUNCTION("ROUND(IFERROR(SUM(FILTER('Sprint 24'!U:U, (('Sprint 24'!J:J = ""Done"")) * ('Sprint 24'!E:E = ""Aek:Atiphat Nanthachitvanich"")))/3600,0),2)"),23.33) -> 23.33
A13: A | B13: =IFERROR(__xludf.DUMMYFUNCTION("IFERROR(SUM(FILTER('Sprint 24'!O:O, ('Sprint 24'!E:E = ""A:Phongthorn""))),0)"),66.0) -> 66 | C13: =IFERROR(__xludf.DUMMYFUNCTION("ROUND(IFERROR(SUM(FILTER('Sprint 24'!U:U, ('Sprint 24'!E:E = ""A:Phongthorn"")))/3600,0),2)"),170.0) -> 170 | D13: =IFERROR(__xludf.DUMMYFUNCTION("IFERROR(SUM(FILTER('Sprint 24'!O:O, (('Sprint 24'!J:J = ""Done"")) * ('Sprint 24'!E:E = ""A:Phongthorn""))),0)"),0.0) -> 0 | E13: =IFERROR(__xludf.DUMMYFUNCTION("ROUND(IFERROR(SUM(FILTER('Sprint 24'!U:U, (('Sprint 24'!J:J = ""Done"")) * ('Sprint 24'!E:E = ""A:Phongthorn"")))/3600,0),2)"),0.0) -> 0
A14: Aom | B14: =IFERROR(__xludf.DUMMYFUNCTION("IFERROR(SUM(FILTER('Sprint 24'!O:O, ('Sprint 24'!E:E = ""Aom: Pornsawan Polnyiem""))),0)"),29.0) -> 29 | C14: =IFERROR(__xludf.DUMMYFUNCTION("ROUND(IFERROR(SUM(FILTER('Sprint 24'!U:U, ('Sprint 24'!E:E = ""Aom: Pornsawan Polnyiem"")))/3600,0),2)"),0.17) -> 0.17 | D14: =IFERROR(__xludf.DUMMYFUNCTION("IFERROR(SUM(FILTER('Sprint 24'!O:O, (('Sprint 24'!J:J = ""Done"")) * ('Sprint 24'!E:E = ""Aom: Pornsawan Polnyiem""))),0)"),1.0) -> 1 | E14: =IFERROR(__xludf.DUMMYFUNCTION("ROUND(IFERROR(SUM(FILTER('Sprint 24'!U:U, (('Sprint 24'!J:J = ""Done"")) * ('Sprint 24'!E:E = ""Aom: Pornsawan Polnyiem"")))/3600,0),2)"),0.17) -> 0.17
A15: Zan | B15: =IFERROR(__xludf.DUMMYFUNCTION("IFERROR(SUM(FILTER('Sprint 24'!O:O, ('Sprint 24'!E:E = ""Zan : Isarapong Bulan""))),0)"),22.0) -> 22 | C15: =IFERROR(__xludf.DUMMYFUNCTION("ROUND(IFERROR(SUM(FILTER('Sprint 24'!U:U, ('Sprint 24'!E:E = ""Zan : Isarapong Bulan"")))/3600,0),2)"),0.0) -> 0 | D15: =IFERROR(__xludf.DUMMYFUNCTION("IFERROR(SUM(FILTER('Sprint 24'!O:O, (('Sprint 24'!J:J = ""Done"")) * ('Sprint 24'!E:E = ""Zan : Isarapong Bulan""))),0)"),21.0) -> 21 | E15: =IFERROR(__xludf.DUMMYFUNCTION("ROUND(IFERROR(SUM(FILTER('Sprint 24'!U:U, (('Sprint 24'!J:J = ""Done"")) * ('Sprint 24'!E:E = ""Zan : Isarapong Bulan"")))/3600,0),2)"),0.0) -> 0
A16: Mai | B16: =IFERROR(__xludf.DUMMYFUNCTION("IFERROR(SUM(FILTER('Sprint 24'!O:O, ('Sprint 24'!E:E = ""Mai:Sateta Abvanawong""))),0)"),78.0) -> 78 | C16: =IFERROR(__xludf.DUMMYFUNCTION("ROUND(IFERROR(SUM(FILTER('Sprint 24'!U:U, ('Sprint 24'!E:E = ""Mai:Sateta Abvanawong"")))/3600,0),2)"),156.0) -> 156 | D16: =IFERROR(__xludf.DUMMYFUNCTION("IFERROR(SUM(FILTER('Sprint 24'!O:O, (('Sprint 24'!J:J = ""Done"")) * ('Sprint 24'!E:E = ""Mai:Sateta Abvanawong""))),0)"),5.0) -> 5 | E16: =IFERROR(__xludf.DUMMYFUNCTION("ROUND(IFERROR(SUM(FILTER('Sprint 24'!U:U, (('Sprint 24'!J:J = ""Done"")) * ('Sprint 24'!E:E = ""Mai:Sateta Abvanawong""))),0)/3600,2)"),10.0) -> 10
A17: Mac | B17: =IFERROR(__xludf.DUMMYFUNCTION("IFERROR(SUM(FILTER('Sprint 24'!O:O, ('Sprint 24'!E:E = ""Mac: Jarupong Pawichpongkul""))),0)"),85.0) -> 85 | C17: =IFERROR(__xludf.DUMMYFUNCTION("ROUND(IFERROR(SUM(FILTER('Sprint 24'!U:U, ('Sprint 24'!E:E = ""Mac: Jarupong Pawichpongkul"")))/3600,0),2)"),179.0) -> 179 | D17: =IFERROR(__xludf.DUMMYFUNCTION("IFERROR(SUM(FILTER('Sprint 24'!O:O, (('Sprint 24'!J:J = ""Done"")) * ('Sprint 24'!E:E = ""Mac: Jarupong Pawichpongkul""))),0)"),17.0) -> 17 | E17: =IFERROR(__xludf.DUMMYFUNCTION("ROUND(IFERROR(SUM(FILTER('Sprint 24'!U:U, (('Sprint 24'!J:J = ""Done"")) * ('Sprint 24'!E:E = ""Mac: Jarupong Pawichpongkul"")))/3600,0),2)"),39.0) -> 39
A18: Mos | B18: =IFERROR(__xludf.DUMMYFUNCTION("IFERROR(SUM(FILTER('Sprint 24'!O:O, ('Sprint 24'!E:E = ""Moss : Kittapath Sangvikukit""))),0)"),60.0) -> 60 | C18: =IFERROR(__xludf.DUMMYFUNCTION("ROUND(IFERROR(SUM(FILTER('Sprint 24'!U:U, ('Sprint 24'!E:E = ""Moss : Kittapath Sangvikukit"")))/3600,0),2)"),81.0) -> 81 | D18: =IFERROR(__xludf.DUMMYFUNCTION("IFERROR(SUM(FILTER('Sprint 24'!O:O, (('Sprint 24'!J:J = ""Done"")) * ('Sprint 24'!E:E = ""Moss : Kittapath Sangvikukit""))),0)"),1.0) -> 1 | E18: =IFERROR(__xludf.DUMMYFUNCTION("ROUND(IFERROR(SUM(FILTER('Sprint 24'!U:U, (('Sprint 24'!J:J = ""Done"")) * ('Sprint 24'!E:E = ""Moss : Kittapath Sangvikukit"")))/3600,0),2)"),2.0) -> 2
A19: Jack | B19: =IFERROR(__xludf.DUMMYFUNCTION("IFERROR(SUM(FILTER('Sprint 24'!O:O, ('Sprint 24'!E:E = ""Jack: Warin Kesorn""))),0)"),0.0) -> 0 | C19: =IFERROR(__xludf.DUMMYFUNCTION("ROUND(IFERROR(SUM(FILTER('Sprint 24'!U:U, ('Sprint 24'!E:E = ""Jack: Warin Kesorn"")))/3600,0),2)"),0.0) -> 0 | D19: =IFERROR(__xludf.DUMMYFUNCTION("IFERROR(SUM(FILTER('Sprint 24'!O:O, (('Sprint 24'!J:J = ""Done"")) * ('Sprint 24'!E:E = ""Jack: Warin Kesorn""))),0)"),0.0) -> 0 | E19: =IFERROR(__xludf.DUMMYFUNCTION("ROUND(IFERROR(SUM(FILTER('Sprint 24'!U:U, (('Sprint 24'!J:J = ""Done"")) * ('Sprint 24'!E:E = ""Jack: Warin Kesorn"")))/3600,0),2)"),0.0) -> 0
A20: Nim | B20: =IFERROR(__xludf.DUMMYFUNCTION("IFERROR(SUM(FILTER('Sprint 24'!O:O, ('Sprint 24'!E:E = ""Nim : muthita munmueang""))),0)"),65.0) -> 65 | C20: =IFERROR(__xludf.DUMMYFUNCTION("ROUND(IFERROR(SUM(FILTER('Sprint 24'!U:U, ('Sprint 24'!E:E = ""Nim : muthita munmueang"")))/3600,0),2)"),68.0) -> 68 | D20: =IFERROR(__xludf.DUMMYFUNCTION("IFERROR(SUM(FILTER('Sprint 24'!O:O, (('Sprint 24'!J:J = ""Done"")) * ('Sprint 24'!E:E = ""Nim : muthita munmueang""))),0)"),10.0) -> 10 | E20: =IFERROR(__xludf.DUMMYFUNCTION("ROUND(IFERROR(SUM(FILTER('Sprint 24'!U:U, (('Sprint 24'!J:J = ""Done"")) * ('Sprint 24'!E:E = ""Nim : muthita munmueang"")))/3600,0),2)"),28.0) -> 28
A21: Arm | B21: =IFERROR(__xludf.DUMMYFUNCTION("IFERROR(SUM(FILTER('Sprint 24'!O:O, ('Sprint 24'!E:E = ""Arm:Worawat Chotipongchoawalit""))),0)"),76.0) -> 76 | C21: =IFERROR(__xludf.DUMMYFUNCTION("ROUND(IFERROR(SUM(FILTER('Sprint 24'!U:U, ('Sprint 24'!E:E = ""Arm:Worawat Chotipongchoawalit"")))/3600,0),2)"),0.0) -> 0 | D21: =IFERROR(__xludf.DUMMYFUNCTION("IFERROR(SUM(FILTER('Sprint 24'!O:O, (('Sprint 24'!J:J = ""Done"")) * ('Sprint 24'!E:E = ""Arm:Worawat Chotipongchoawalit""))),0)"),17.0) -> 17 | E21: =IFERROR(__xludf.DUMMYFUNCTION("ROUND(IFERROR(SUM(FILTER('Sprint 24'!U:U, (('Sprint 24'!J:J = ""Done"")) * ('Sprint 24'!E:E = ""Arm:Worawat Chotipongchoawalit"")))/3600,0),2)"),0.0) -> 0
B25: System Architech | F25: Permanent Dev. | I25: Contract | J25: Outsource
A26: Projects (Stories Points) | B26: Aek | C26: Zan | D26: Aom | E26: Jack | F26: A | G26: Mac | H26: Mai | I26: Arm | J26: Mos | K26: Nim

Sheet Sprint 24
A1: Issue Type | B1: Issue key | C1: Issue id | D1: Summary | E1: Assignee | F1: Assignee Id | G1: Reporter | H1: Reporter Id | I1: Priority | J1: Status | K1: Resolution | L1: Created | M1: Updated | N1: Due date | O1: Custom field (Story Points) | P1: Labels | Q1: Labels | R1: Labels | S1: Labels | T1: Labels | U1: Original estimate | V1: Sprint | W1: Sprint | X1: Sprint | Y1: Sprint | Z1: Sprint | AA1: Sprint | AB1: Sprint | AC1: Sprint | AD1: Sprint | AE1: Sprint | AF1: Sprint
A2: Story | B2: DEVRDSUP-587 | C2: 53955 | D2: [SUP-683][RRApp][Binding RW] RW Card not show in RR_Prod | E2: Aek:Atiphat Nanthachitvanich | F2: 5d48155f5b8ea70c7e4f1b0f | G2: Thanakrit Chanthaworn | H2: 712020:3fc982cb-c268-4f1d-9265-d3dd8fb08304 | I2: Medium | J2: Done | L2: 15/May/26 2:12 PM | M2: 15/May/26 3:57 PM | O2: 1 | U2: 600 | V2: [Dev][All Project] Sprint 24
A3: Bug | B3: DPE-545 | C3: 53943 | D3: [S3][BFF] The point history response is incorrect when no data matched | E3: Nim : muthita munmueang | F3: 712020:e80312b7-b5b0-43e8-b198-3d8fce4532bb | G3: Plai Thanaporn Rimnong-ang | H3: 62c2a5acefb17d6ce62e41bf | I3: Medium | J3: Closed | L3: 15/May/26 10:28 AM | M3: 15/May/26 11:14 AM | V3: [Dev][RD][New PE] Sprint 24
A4: Story | B4: DEVRDSUP-584 | C4: 53895 | D4: [SUP-678]#20260300026281 [RW Binding] Binding but no TXN / No Binding got TXN ? | E4: Aek:Atiphat Nanthachitvanich | F4: 5d48155f5b8ea70c7e4f1b0f | G4: Abhinaf Singh | H4: 712020:a81c99dd-d5cd-44bd-950a-32f4ff7d56ac | I4: Medium | J4: Done | L4: 14/May/26 3:00 PM | M4: 15/May/26 12:58 PM | O4: 1 | U4: 600 | V4: [Dev][All Project] Sprint 24
A5: Bug | B5: DEVRDSUP-588 | C5: 53890 | D5: [S3][RR-Backoffice][Rewards] Some deeplink is not displayed | E5: Mai:Sateta Abvanawong | F5: 64000e4f15d668edd8edc7ea | G5: Plai Thanaporn Rimnong-ang | H5: 62c2a5acefb17d6ce62e41bf | I5: Medium | J5: RETESTING | L5: 14/May/26 2:19 PM | M5: 15/May/26 3:52 PM | N5: 15/May/26 12:00 AM | V5: [Dev][All Project] Sprint 24
A6: Bug | B6: DPE-538 | C6: 53888 | D6: [S3][BFF] The point history response filtered by date and time is incorrect | E6: Nim : muthita munmueang | F6: 712020:e80312b7-b5b0-43e8-b198-3d8fce4532bb | G6: Plai Thanaporn Rimnong-ang | H6: 62c2a5acefb17d6ce62e41bf | I6: Medium | J6: UNDER VALIDATION | L6: 14/May/26 1:41 PM | M6: 15/May/26 10:33 AM | V6: [Dev][RD][New PE] Sprint 24
A7: Story | B7: DEVRDSUP-581 | C7: 53880 | D7: [SUP-676][SUB] Receipt is not generated after SUB transaction is made (TXN Date 13 May 2026) | E7: Aom: Pornsawan Polnyiem | F7: 5d2ed694a666040c85096e17 | G7: Abhinaf Singh | H7: 712020:a81c99dd-d5cd-44bd-950a-32f4ff7d56ac | I7: Medium | J7: Done | L7: 14/May/26 11:52 AM | M7: 15/May/26 12:58 PM | N7: 14/May/26 12:00 AM | O7: 1 | U7: 600 | V7: [Dev][All Project] Sprint 24
A8: Story | B8: DEV-3 | C8: 53866 | D8: [DEV][RD][Tech Debt][HRS] : Enhance getMemberTier — Cache, Bug Fix & Cache Invalidation | E8: Arm:Worawat Chotipongchoawalit | F8: 712020:2195d849-5cdb-4ec8-866f-e82a3528bff7 | G8: Aek:Atiphat Nanthachitvanich | H8: 5d48155f5b8ea70c7e4f1b0f | I8: Medium | J8: Ready to Staging | L8: 14/May/26 9:47 AM | M8: 15/May/26 2:58 PM | O8: 3 | V8: [Dev][RD][TechDebt] Sprint 24
A9: Story | B9: DEV-2 | C9: 53859 | D9: [DEV][RD][Tech Debt][SSO] Improve performance (Relational) | E9: A:Phongthorn | F9: 5b3c867ae263df2dc32f7e35 | G9: Aek:Atiphat Nanthachitvanich | H9: 5d48155f5b8ea70c7e4f1b0f | I9: Medium | J9: In Review | L9: 14/May/26 9:24 AM | M9: 14/May/26 3:01 PM | N9: 15/May/26 12:00 AM | O9: 1 | U9: 7200 | V9: [Dev][RD][TechDebt] Sprint 24
A10: Story | B10: DEV-1 | C10: 53858 | D10: [DEV][RD][Tech Debt][PL] Fix Log File Permission Issue to Prevent Root-Owned File Blocking Application Logs | E10: A:Phongthorn | F10: 5b3c867ae263df2dc32f7e35 | G10: Aek:Atiphat Nanthachitvanich | H10: 5d48155f5b8ea70c7e4f1b0f | I10: Medium | J10: In Review | L10: 14/May/26 9:19 AM | M10: 15/May/26 3:01 PM | N10: 15/May/26 12:00 AM | O10: 3 | U10: 28800 | V10: [Dev][RD][TechDebt] Sprint 24
A11: Story | B11: RDAPS-466 | C11: 53857 | D11: [SA][RD][Unified App] Info Preparation | E11: Zan : Isarapong Bulan | F11: 5d4814e9da0c4d0c789a4bb7 | G11: Aek:Atiphat Nanthachitvanich | H11: 5d48155f5b8ea70c7e4f1b0f | I11: Medium | J11: In Progress | L11: 14/May/26 8:22 AM | M11: 14/May/26 8:22 AM | O11: 1 | V11: [Dev][All Project] Sprint 24
A12: Story | B12: RDAPS-465 | C12: 53856 | D12: [SA][RD][Unified App] Info Preparation | E12: Aek:Atiphat Nanthachitvanich | F12: 5d48155f5b8ea70c7e4f1b0f | G12: Aek:Atiphat Nanthachitvanich | H12: 5d48155f5b8ea70c7e4f1b0f | I12: Medium | J12: Done | L12: 14/May/26 8:21 AM | M12: 15/May/26 10:11 AM | O12: 1 | U12: 7200 | V12: [Dev][All Project] Sprint 24
A13: Bug | B13: DPE-537 | C13: 53855 | D13: [S3][RR-Backoffice][Rewards] The offer details is npt updated when the reward detail updates | E13: Arm:Worawat Chotipongchoawalit | F13: 712020:2195d849-5cdb-4ec8-866f-e82a3528bff7 | G13: Plai Thanaporn Rimnong-ang | H13: 62c2a5acefb17d6ce62e41bf | I13: Medium | J13: Closed | L13: 13/May/26 5:24 PM | M13: 14/May/26 4:43 PM | V13: [Dev][RD][New PE] Sprint 24
A14: Bug | B14: DPE-536 | C14: 53854 | D14: [S3][RR-Backoffice][Rewards] Unable to update reward information | E14: Arm:Worawat Chotipongchoawalit | F14: 712020:2195d849-5cdb-4ec8-866f-e82a3528bff7 | G14: Plai Thanaporn Rimnong-ang | H14: 62c2a5acefb17d6ce62e41bf | I14: Medium | J14: Closed | L14: 13/May/26 5:20 PM | M14: 14/May/26 4:43 PM | V14: [Dev][RD][New PE] Sprint 24
A15: Story | B15: RDTHANA-490 | C15: 53844 | D15: [DEV][RD][TDM] Enhance merchant detail to transaction without coin Event | E15: Mac: Jarupong Pawichpongkul | F15: 62c2a16240923988ba097c14 | G15: Zan : Isarapong Bulan | H15: 5d4814e9da0c4d0c789a4bb7 | I15: Medium | J15: Ready To Test | L15: 13/May/26 2:46 PM | M15: 15/May/26 11:38 AM | N15: 14/May/26 12:00 AM | O15: 3 | V15: [Dev][RD][Thana] Sprint 24
A16: Sub-task | B16: DPE-535 | C16: 53843 | D16: Test execution | E16: Plai Thanaporn Rimnong-ang | F16: 62c2a5acefb17d6ce62e41bf | G16: Aom: Pornsawan Polnyiem | H16: 5d2ed694a666040c85096e17 | I16: Medium | J16: Done | L16: 13/May/26 2:35 PM | M16: 13/May/26 4:10 PM | V16: [Dev][RD][New PE] Sprint 23 | W16: [Dev][RD][New PE] Sprint 24
A17: Sub-task | B17: DPE-534 | C17: 53841 | D17: Create test case | E17: Plai Thanaporn Rimnong-ang | F17: 62c2a5acefb17d6ce62e41bf | G17: Aom: Pornsawan Polnyiem | H17: 5d2ed694a666040c85096e17 | I17: Medium | J17: Done | L17: 13/May/26 2:35 PM | M17: 13/May/26 2:39 PM | V17: [Dev][RD][New PE] Sprint 23 | W17: [Dev][RD][New PE] Sprint 24
A18: Sub-task | B18: DRST-98 | C18: 53827 | D18: [QA] Test Execution | E18: Max (QA) : Surawut Sae-nim | F18: 62d4e007098e73c4e5ee0d8d | G18: Max (QA) : Surawut Sae-nim | H18: 62d4e007098e73c4e5ee0d8d | I18: Medium | J18: Done | L18: 13/May/26 10:42 AM | M18: 13/May/26 10:44 AM | V18: [Dev][All Project] Sprint 15 | W18: [Dev][All Project] Sprint 16 | X18: [Dev RD][VIMI Termi] Sprint 17 | Y18: [Dev RD][VIMI Termi] Sprint 18 | Z18: [Dev RD][VIMI Termi] Sprint 19 | AA18: [Dev RD][VIMI Termi] Sprint 20 | AB18: [Dev RD][VIMI Termi] Sprint 21 | AC18: [Dev RD][VIMI Termi] Sprint 22 | AD18: [Dev RD][VIMI Termi] Sprint 23 | AE18: [Dev RD][VIMI Termi] Sprint 24
A19: Sub-task | B19: DRST-97 | C19: 53814 | D19: [QA] Test Execution | E19: Max (QA) : Surawut Sae-nim | F19: 62d4e007098e73c4e5ee0d8d | G19: Max (QA) : Surawut Sae-nim | H19: 62d4e007098e73c4e5ee0d8d | I19: Medium | J19: Done | L19: 13/May/26 1:04 AM | M19: 13/May/26 1:09 AM | V19: [Dev RD][VIMI Termi] Sprint 18 | W19: [Dev RD][VIMI Termi] Sprint 19 | X19: [Dev RD][VIMI Termi] Sprint 20 | Y19: [Dev RD][VIMI Termi] Sprint 21 | Z19: [Dev RD][VIMI Termi] Sprint 22 | AA19: [Dev RD][VIMI Termi] Sprint 23 | AB19: [Dev RD][VIMI Termi] Sprint 24
A20: Story | B20: DEVRDSUP-577 | C20: 53791 | D20: [SUP-671][Line Pay] #20260500027631 Cannot tou-up BTS Trips in Line Pay Account [User is not found in Cloud ID system] | E20: Aek:Atiphat Nanthachitvanich | F20: 5d48155f5b8ea70c7e4f1b0f | G20: Abhinaf Singh | H20: 712020:a81c99dd-d5cd-44bd-950a-32f4ff7d56ac | I20: Medium | J20: Done | L20: 11/May/26 4:23 PM | M20: 15/May/26 12:58 PM | O20: 1 | U20: 1800 | V20: [Dev][All Project] Sprint 24
A21: Story | B21: DEVRDSUP-576 | C21: 53742 | D21: [SUP-670]Urgent [SUB] CS-#20260500027429 // หักเงิน แต่ไม่ได้รับแพ็กเกจ รบกวนออกแพ็กเกจให้ลูกค้าค่ะ | E21: Mac: Jarupong Pawichpongkul | F21: 62c2a16240923988ba097c14 | G21: Abhinaf Singh | H21: 712020:a81c99dd-d5cd-44bd-950a-32f4ff7d56ac | I21: Highest | J21: Done | L21: 08/May/26 2:43 PM | M21: 15/May/26 12:58 PM | N21: 08/May/26 12:00 AM | O21: 1 | U21: 0 | V21: [Dev][All Project] Sprint 24
A22: Bug | B22: RDTHANA-489 | C22: 53730 | D22: [DEV][RD] Refund webhook event not sync to datamart view table | E22: Mac: Jarupong Pawichpongkul | F22: 62c2a16240923988ba097c14 | G22: Zan : Isarapong Bulan | H22: 5d4814e9da0c4d0c789a4bb7 | I22: Highest | J22: Resolved | L22: 08/May/26 12:36 AM | M22: 08/May/26 1:25 PM | V22: [Dev][RD][Thana] Sprint 24
A23: Story | B23: DPE-531 | C23: 53720 | D23: [Dev][RD][SSO-User DB] Create database view for active RC cards info | E23: Nim : muthita munmueang | F23: 712020:e80312b7-b5b0-43e8-b198-3d8fce4532bb | G23: Aom: Pornsawan Polnyiem | H23: 5d2ed694a666040c85096e17 | I23: Medium | J23: In Review | L23: 07/May/26 3:05 PM | M23: 15/May/26 1:25 PM | N23: 15/May/26 12:00 AM | O23: 1 | P23: DE | V23: [Dev][RD][New PE] Sprint 24
A24: Story | B24: DPE-530 | C24: 53712 | D24: [Dev][RD][IPF] Change the webhook issue point to use Point Engine Proxy | E24: Moss : Kittapath Sangvikukit | F24: 712020:b33baa03-2b29-4662-9923-dbdc2bbf980d | G24: Jack: Warin Kesorn | H24: 61a98e8e744c4d00693281d1 | I24: Medium | J24: Ready To Test | L24: 07/May/26 2:51 PM | M24: 14/May/26 4:15 PM | N24: 15/May/26 12:00 AM | O24: 3 | P24: rr-issue-point-function | U24: 28800 | V24: [Dev][RD][New PE] Sprint 24
A25: Sub-task | B25: DPE-529 | C25: 53708 | D25: [QA] Test Execution - STG | E25: Max (QA) : Surawut Sae-nim | F25: 62d4e007098e73c4e5ee0d8d | G25: Max (QA) : Surawut Sae-nim | H25: 62d4e007098e73c4e5ee0d8d | I25: Medium | J25: To Do | L25: 07/May/26 2:41 PM | M25: 07/May/26 2:41 PM | V25: [Dev][RD][New PE] Sprint 23 | W25: [Dev][RD][New PE] Sprint 24
A26: Sub-task | B26: DPE-528 | C26: 53707 | D26: [QA] Test Execution - STG | E26: Max (QA) : Surawut Sae-nim | F26: 62d4e007098e73c4e5ee0d8d | G26: Max (QA) : Surawut Sae-nim | H26: 62d4e007098e73c4e5ee0d8d | I26: Medium | J26: To Do | L26: 07/May/26 2:41 PM | M26: 07/May/26 2:41 PM | V26: [Dev][RD][New PE] Sprint 23 | W26: [Dev][RD][New PE] Sprint 24
A27: Sub-task | B27: DPE-527 | C27: 53706 | D27: [QA] Test Execution - STG | E27: Max (QA) : Surawut Sae-nim | F27: 62d4e007098e73c4e5ee0d8d | G27: Max (QA) : Surawut Sae-nim | H27: 62d4e007098e73c4e5ee0d8d | I27: Medium | J27: To Do | L27: 07/May/26 2:41 PM | M27: 07/May/26 2:41 PM | V27: [Dev][RD][New PE] Sprint 23 | W27: [Dev][RD][New PE] Sprint 24
A28: Sub-task | B28: DPE-526 | C28: 53705 | D28: [QA] Test Execution - STG | E28: Max (QA) : Surawut Sae-nim | F28: 62d4e007098e73c4e5ee0d8d | G28: Max (QA) : Surawut Sae-nim | H28: 62d4e007098e73c4e5ee0d8d | I28: Medium | J28: To Do | L28: 07/May/26 2:41 PM | M28: 07/May/26 2:41 PM | V28: [Dev][RD][New PE] Sprint 23 | W28: [Dev][RD][New PE] Sprint 24
A29: Sub-task | B29: DPE-525 | C29: 53704 | D29: [QA] Test Execution - STG | E29: Max (QA) : Surawut Sae-nim | F29: 62d4e007098e73c4e5ee0d8d | G29: Max (QA) : Surawut Sae-nim | H29: 62d4e007098e73c4e5ee0d8d | I29: Medium | J29: To Do | L29: 07/May/26 2:41 PM | M29: 07/May/26 2:41 PM | V29: [Dev][RD][New PE] Sprint 23 | W29: [Dev][RD][New PE] Sprint 24
A30: Sub-task | B30: DPE-524 | C30: 53703 | D30: [QA] Test Execution - STG | E30: Max (QA) : Surawut Sae-nim | F30: 62d4e007098e73c4e5ee0d8d | G30: Max (QA) : Surawut Sae-nim | H30: 62d4e007098e73c4e5ee0d8d | I30: Medium | J30: To Do | L30: 07/May/26 2:40 PM | M30: 07/May/26 2:40 PM | V30: [Dev][RD][New PE] Sprint 23 | W30: [Dev][RD][New PE] Sprint 24
A31: Sub-task | B31: DPE-523 | C31: 53702 | D31: [QA] Test Execution - STG | E31: Max (QA) : Surawut Sae-nim | F31: 62d4e007098e73c4e5ee0d8d | G31: Max (QA) : Surawut Sae-nim | H31: 62d4e007098e73c4e5ee0d8d | I31: Medium | J31: To Do | L31: 07/May/26 2:39 PM | M31: 07/May/26 2:39 PM | V31: [Dev][RD][New PE] Sprint 23 | W31: [Dev][RD][New PE] Sprint 24
A32: Sub-task | B32: DPE-522 | C32: 53701 | D32: [QA] Test Execution - STG | E32: Max (QA) : Surawut Sae-nim | F32: 62d4e007098e73c4e5ee0d8d | G32: Max (QA) : Surawut Sae-nim | H32: 62d4e007098e73c4e5ee0d8d | I32: Medium | J32: To Do | L32: 07/May/26 2:39 PM | M32: 07/May/26 2:39 PM | V32: [Dev][RD][New PE] Sprint 23 | W32: [Dev][RD][New PE] Sprint 24
A33: Sub-task | B33: DPE-521 | C33: 53700 | D33: [QA] Test Execution - STG | E33: Max (QA) : Surawut Sae-nim | F33: 62d4e007098e73c4e5ee0d8d | G33: Max (QA) : Surawut Sae-nim | H33: 62d4e007098e73c4e5ee0d8d | I33: Medium | J33: To Do | L33: 07/May/26 2:38 PM | M33: 07/May/26 2:39 PM | V33: [Dev][RD][New PE] Sprint 23 | W33: [Dev][RD][New PE] Sprint 24
A34: Sub-task | B34: DPE-520 | C34: 53699 | D34: [QA] Test Execution - STG | E34: Max (QA) : Surawut Sae-nim | F34: 62d4e007098e73c4e5ee0d8d | G34: Max (QA) : Surawut Sae-nim | H34: 62d4e007098e73c4e5ee0d8d | I34: Medium | J34: To Do | L34: 07/May/26 2:38 PM | M34: 07/May/26 2:38 PM | V34: [Dev][RD][New PE] Sprint 23 | W34: [Dev][RD][New PE] Sprint 24
A35: Story | B35: DPE-519 | C35: 53698 | D35: [Dev][RD][SSO-User DB] Create database view for registration_sources | E35: Nim : muthita munmueang | F35: 712020:e80312b7-b5b0-43e8-b198-3d8fce4532bb | G35: Aom: Pornsawan Polnyiem | H35: 5d2ed694a666040c85096e17 | I35: Medium | J35: Ready To Test | L35: 07/May/26 2:16 PM | M35: 15/May/26 1:25 PM | N35: 15/May/26 12:00 AM | O35: 1 | P35: DE | V35: [Dev][RD][New PE] Sprint 24
A36: Sub-task | B36: DPE-518 | C36: 53689 | D36: Test execution | E36: Plai Thanaporn Rimnong-ang | F36: 62c2a5acefb17d6ce62e41bf | G36: Aom: Pornsawan Polnyiem | H36: 5d2ed694a666040c85096e17 | I36: Medium | J36: Done | L36: 07/May/26 10:23 AM | M36: 08/May/26 11:56 AM | V36: [Dev][RD][New PE] Sprint 24
A37: Sub-task | B37: DPE-517 | C37: 53688 | D37: Create test case | E37: Plai Thanaporn Rimnong-ang | F37: 62c2a5acefb17d6ce62e41bf | G37: Aom: Pornsawan Polnyiem | H37: 5d2ed694a666040c85096e17 | I37: Medium | J37: Done | L37: 07/May/26 10:23 AM | M37: 08/May/26 11:38 AM | V37: [Dev][RD][New PE] Sprint 24
A38: Story | B38: DPE-516 | C38: 53687 | D38: [Dev][RD][PL][Point] Improve point redeem transaction | E38: Mai:Sateta Abvanawong | F38: 64000e4f15d668edd8edc7ea | G38: Aom: Pornsawan Polnyiem | H38: 5d2ed694a666040c85096e17 | I38: Medium | J38: Done | L38: 07/May/26 9:37 AM | M38: 08/May/26 12:01 PM | N38: 07/May/26 12:00 AM | O38: 1 | U38: 7200 | V38: [Dev][RD][New PE] Sprint 24
A39: Story | B39: RDAPS-463 | C39: 53685 | D39: [Dev][RD][SA] Meeting | E39: Aom: Pornsawan Polnyiem | F39: 5d2ed694a666040c85096e17 | G39: Aom: Pornsawan Polnyiem | H39: 5d2ed694a666040c85096e17 | I39: Medium | J39: In Progress | L39: 07/May/26 9:16 AM | M39: 14/May/26 11:08 AM | O39: 5 | V39: [Dev][All Project] Sprint 24
A40: Sub-task | B40: DRST-96 | C40: 53676 | D40: [QA] Test Execution - UAT | E40: Max (QA) : Surawut Sae-nim | F40: 62d4e007098e73c4e5ee0d8d | G40: Max (QA) : Surawut Sae-nim | H40: 62d4e007098e73c4e5ee0d8d | I40: Medium | J40: Done | L40: 06/May/26 3:59 PM | M40: 06/May/26 4:25 PM | V40: [Dev RD][VIMI Termi] Sprint 20 | W40: [Dev RD][VIMI Termi] Sprint 21 | X40: [Dev RD][VIMI Termi] Sprint 22 | Y40: [Dev RD][VIMI Termi] Sprint 23 | Z40: [Dev RD][VIMI Termi] Sprint 24
A41: Sub-task | B41: DRST-95 | C41: 53675 | D41: [QA] Test Execution - STG | E41: Max (QA) : Surawut Sae-nim | F41: 62d4e007098e73c4e5ee0d8d | G41: Max (QA) : Surawut Sae-nim | H41: 62d4e007098e73c4e5ee0d8d | I41: Medium | J41: Done | L41: 06/May/26 3:59 PM | M41: 06/May/26 3:59 PM | V41: [Dev RD][VIMI Termi] Sprint 20 | W41: [Dev RD][VIMI Termi] Sprint 21 | X41: [Dev RD][VIMI Termi] Sprint 22 | Y41: [Dev RD][VIMI Termi] Sprint 23 | Z41: [Dev RD][VIMI Termi] Sprint 24
A42: Story | B42: DPE-514 | C42: 53674 | D42: [Dev][RD][PE Middleware] Enhance Reversal API | E42: Moss : Kittapath Sangvikukit | F42: 712020:b33baa03-2b29-4662-9923-dbdc2bbf980d | G42: Jack: Warin Kesorn | H42: 61a98e8e744c4d00693281d1 | I42: Medium | J42: Ready To Test | L42: 06/May/26 3:49 PM | M42: 15/May/26 2:35 PM | N42: 15/May/26 12:00 AM | O42: 3 | P42: point-engine-proxy | U42: 28800 | V42: [Dev][RD][New PE] Sprint 24
A43: Story | B43: DEVRDSUP-572 | C43: 53659 | D43: [SUP-637][Earning BTS Point] #20260100023991 - บัตร RW 08800450771444 -Please check Eligible Trips and Point | E43: Abhinaf Singh | F43: 712020:a81c99dd-d5cd-44bd-950a-32f4ff7d56ac | G43: Abhinaf Singh | H43: 712020:a81c99dd-d5cd-44bd-950a-32f4ff7d56ac | I43: Medium | J43: To Do | L43: 06/May/26 11:19 AM | M43: 14/May/26 2:39 PM | V43: [Dev][All Project] Sprint 24
A44: Bug | B44: DEVRDSUP-571 | C44: 53655 | D44: [SUP-664]#20260300026281 [RW Binding] Binding but no TXN / No Binding got TXN ? | E44: Aek:Atiphat Nanthachitvanich | F44: 5d48155f5b8ea70c7e4f1b0f | G44: Abhinaf Singh | H44: 712020:a81c99dd-d5cd-44bd-950a-32f4ff7d56ac | I44: Medium | J44: Rejected | L44: 06/May/26 10:42 AM | M44: 15/May/26 9:32 AM | O44: 1 | V44: [Dev][All Project] Sprint 24
A45: Story | B45: DEVRDSUP-569 | C45: 53648 | D45: [SUP-663][SUB]CS-#20260500027382 // Request mark used[ Using] coupon - 13855211 >> RW 0880064263331 | E45: Mai:Sateta Abvanawong | F45: 64000e4f15d668edd8edc7ea | G45: Abhinaf Singh | H45: 712020:a81c99dd-d5cd-44bd-950a-32f4ff7d56ac | I45: Highest | J45: Done | L45: 05/May/26 4:37 PM | M45: 15/May/26 12:58 PM | N45: 08/May/26 12:00 AM | O45: 1 | V45: [Dev][All Project] Sprint 24
A46: Story | B46: DPE-512 | C46: 53647 | D46: [Dev][RD][REM] Implement Point Reversal if Coupon Allocation Fails After Deduction | E46: Moss : Kittapath Sangvikukit | F46: 712020:b33baa03-2b29-4662-9923-dbdc2bbf980d | G46: Aom: Pornsawan Polnyiem | H46: 5d2ed694a666040c85096e17 | I46: Medium | J46: Ready To Test | L46: 05/May/26 3:36 PM | M46: 08/May/26 10:26 AM | N46: 15/May/26 12:00 AM | O46: 2 | U46: 14400 | V46: [Dev][RD][New PE] Sprint 24
A47: Story | B47: DPE-510 | C47: 53618 | D47: [Dev][RD][REM] Add point_provider to redeem API | E47: Moss : Kittapath Sangvikukit | F47: 712020:b33baa03-2b29-4662-9923-dbdc2bbf980d | G47: Aom: Pornsawan Polnyiem | H47: 5d2ed694a666040c85096e17 | I47: Medium | J47: Ready To Test | L47: 05/May/26 11:42 AM | M47: 13/May/26 11:05 AM | N47: 15/May/26 12:00 AM | U47: 3600 | V47: [Dev][RD][New PE] Sprint 24
A48: Story | B48: DPE-509 | C48: 53616 | D48: [Dev][RD][PL] Add point_provider to transactions and redeems table | E48: Moss : Kittapath Sangvikukit | F48: 712020:b33baa03-2b29-4662-9923-dbdc2bbf980d | G48: Aom: Pornsawan Polnyiem | H48: 5d2ed694a666040c85096e17 | I48: Medium | J48: Ready To Test | L48: 05/May/26 11:29 AM | M48: 14/May/26 4:23 PM | N48: 15/May/26 12:00 AM | O48: 1 | U48: 7200 | V48: [Dev][RD][New PE] Sprint 24
A49: Story | B49: DEVRDSUP-568 | C49: 53612 | D49: [SUP-661][SUB] Receipt is not generate after txn is made (5/5/69) | E49: Mai:Sateta Abvanawong | F49: 64000e4f15d668edd8edc7ea | G49: Abhinaf Singh | H49: 712020:a81c99dd-d5cd-44bd-950a-32f4ff7d56ac | I49: Highest | J49: Done | L49: 05/May/26 10:55 AM | M49: 15/May/26 12:58 PM | N49: 05/May/26 12:00 AM | V49: [Dev][All Project] Sprint 24
A50: Story | B50: DEVRDSUP-567 | C50: 53609 | D50: [SUP-660]ตรวจสอบไม่พบข้อมูล TXN ที่คืน Point ของ BTSG จำนวน 47 TXN | E50: Aek:Atiphat Nanthachitvanich | F50: 5d48155f5b8ea70c7e4f1b0f | G50: Abhinaf Singh | H50: 712020:a81c99dd-d5cd-44bd-950a-32f4ff7d56ac | I50: Medium | J50: Done | L50: 05/May/26 10:22 AM | M50: 14/May/26 11:32 AM | O50: 1 | U50: 1800 | V50: [Dev][All Project] Sprint 24
A51: Story | B51: DPE-508 | C51: 53606 | D51: [Dev][RD][PWP] Refactor QR Scan API to Use Config-Based Point Provider | E51: Arm:Worawat Chotipongchoawalit | F51: 712020:2195d849-5cdb-4ec8-866f-e82a3528bff7 | G51: Aom: Pornsawan Polnyiem | H51: 5d2ed694a666040c85096e17 | I51: Medium | J51: Ready To Test | L51: 05/May/26 9:53 AM | M51: 14/May/26 2:05 PM | O51: 2 | V51: [Dev][RD][New PE] Sprint 24
A52: Story | B52: DEVRDECOM-246 | C52: 53605 | D52: [DEV][RD][Ecom][Turtle] Custom delivery option in email order confirmation | E52: Aek:Atiphat Nanthachitvanich | F52: 5d48155f5b8ea70c7e4f1b0f | G52: Aek:Atiphat Nanthachitvanich | H52: 5d48155f5b8ea70c7e4f1b0f | I52: Medium | J52: Ready To Test | L52: 05/May/26 9:44 AM | M52: 14/May/26 10:46 AM | O52: 3 | U52: 57600 | V52: [Dev][RD][Ecom] Sprint 24
A53: Story | B53: DEVRDECOM-243 | C53: 53602 | D53: [DEV][RD][Ecom][POC][Gustron] Banner auto login from RR app | E53: Aek:Atiphat Nanthachitvanich | F53: 5d48155f5b8ea70c7e4f1b0f | G53: Aek:Atiphat Nanthachitvanich | H53: 5d48155f5b8ea70c7e4f1b0f | I53: Medium | J53: To Do | L53: 05/May/26 9:36 AM | M53: 14/May/26 10:46 AM | O53: 3 | V53: [Dev][RD][Ecom] Sprint 24
A54: Story | B54: DEVRDECOM-242 | C54: 53601 | D54: [DEV][RD][Ecom][POC] New customer account type in shopify (Multipass deprecated) | E54: Aek:Atiphat Nanthachitvanich | F54: 5d48155f5b8ea70c7e4f1b0f | G54: Aek:Atiphat Nanthachitvanich | H54: 5d48155f5b8ea70c7e4f1b0f | I54: Medium | J54: In Progress | L54: 05/May/26 9:33 AM | M54: 15/May/26 10:34 AM | O54: 5 | V54: [Dev][RD][Ecom] Sprint 24
A55: Story | B55: RDAPS-462 | C55: 53600 | D55: [SA][RD] Prepare task for Sprint 24, 25 | E55: Aek:Atiphat Nanthachitvanich | F55: 5d48155f5b8ea70c7e4f1b0f | G55: Aek:Atiphat Nanthachitvanich | H55: 5d48155f5b8ea70c7e4f1b0f | I55: Medium | J55: Done | L55: 05/May/26 9:27 AM | M55: 15/May/26 4:07 PM | O55: 2 | U55: 14400 | V55: [Dev][All Project] Sprint 24
A56: Story | B56: RDAPS-461 | C56: 53599 | D56: [SA][RD] Team Support & Management Sprint 24 | E56: Aek:Atiphat Nanthachitvanich | F56: 5d48155f5b8ea70c7e4f1b0f | G56: Aek:Atiphat Nanthachitvanich | H56: 5d48155f5b8ea70c7e4f1b0f | I56: Medium | J56: Done | L56: 05/May/26 9:26 AM | M56: 14/May/26 11:34 AM | O56: 3 | U56: 28800 | V56: [Dev][All Project] Sprint 24
A57: Story | B57: RDAPS-460 | C57: 53598 | D57: [SA][RD] Meeting Sprint 24 | E57: Aek:Atiphat Nanthachitvanich | F57: 5d48155f5b8ea70c7e4f1b0f | G57: Aek:Atiphat Nanthachitvanich | H57: 5d48155f5b8ea70c7e4f1b0f | I57: Medium | J57: Done | L57: 05/May/26 9:26 AM | M57: 14/May/26 11:33 AM | O57: 3 | U57: 28800 | V57: [Dev][All Project] Sprint 24
A58: Story | B58: RDAPS-459 | C58: 53597 | D58: [SA][RD][Samsung][POC] Review BSS API to update card status v2 | E58: Aek:Atiphat Nanthachitvanich | F58: 5d48155f5b8ea70c7e4f1b0f | G58: Aek:Atiphat Nanthachitvanich | H58: 5d48155f5b8ea70c7e4f1b0f | I58: Medium | J58: In Review | L58: 05/May/26 9:22 AM | M58: 15/May/26 8:50 AM | O58: 2 | V58: [Dev][All Project] Sprint 24
A59: Story | B59: DPE-507 | C59: 53595 | D59: [Dev][RD][PL] Enhance Check Member by Phone API to Support Terminated Users | E59: A:Phongthorn | F59: 5b3c867ae263df2dc32f7e35 | G59: Aek:Atiphat Nanthachitvanich | H59: 5d48155f5b8ea70c7e4f1b0f | I59: Medium | J59: In Review | L59: 05/May/26 9:02 AM | M59: 14/May/26 1:43 PM | N59: 08/May/26 12:00 AM | O59: 2 | U59: 14400 | V59: [Dev][RD][New PE] Sprint 24
A60: Sub-task | B60: DRST-94 | C60: 53577 | D60: [QA] Test Execution - UAT | E60: Max (QA) : Surawut Sae-nim | F60: 62d4e007098e73c4e5ee0d8d | G60: Max (QA) : Surawut Sae-nim | H60: 62d4e007098e73c4e5ee0d8d | I60: Medium | J60: Done | L60: 30/Apr/26 5:35 PM | M60: 06/May/26 4:24 PM | V60: [Dev RD][VIMI Termi] Sprint 20 | W60: [Dev RD][VIMI Termi] Sprint 21 | X60: [Dev RD][VIMI Termi] Sprint 22 | Y60: [Dev RD][VIMI Termi] Sprint 23 | Z60: [Dev RD][VIMI Termi] Sprint 24
A61: Sub-task | B61: DRST-93 | C61: 53575 | D61: [QA] Test Execution - STG | E61: Max (QA) : Surawut Sae-nim | F61: 62d4e007098e73c4e5ee0d8d | G61: Max (QA) : Surawut Sae-nim | H61: 62d4e007098e73c4e5ee0d8d | I61: Medium | J61: Done | L61: 30/Apr/26 5:31 PM | M61: 30/Apr/26 5:34 PM | V61: [Dev RD][VIMI Termi] Sprint 20 | W61: [Dev RD][VIMI Termi] Sprint 21 | X61: [Dev RD][VIMI Termi] Sprint 22 | Y61: [Dev RD][VIMI Termi] Sprint 23 | Z61: [Dev RD][VIMI Termi] Sprint 24
A62: Story | B62: RDTHANA-485 | C62: 53569 | D62: [DEV][RD][TDM] Turtle Shopify Order event for datamart | E62: Mac: Jarupong Pawichpongkul | F62: 62c2a16240923988ba097c14 | G62: Zan : Isarapong Bulan | H62: 5d4814e9da0c4d0c789a4bb7 | I62: Medium | J62: In Review | L62: 30/Apr/26 2:47 PM | M62: 15/May/26 3:11 PM | N62: 15/May/26 12:00 AM | O62: 3 | P62: No-QA | Q62: Thana-datamart | V62: [Dev][RD][Thana] Sprint 24 | W62: [Dev][RD][Thana] Sprint 24
A63: Story | B63: RDTHANA-484 | C63: 53566 | D63: [DEV][RD][TDM] Access control API on landing zone | E63: Mac: Jarupong Pawichpongkul | F63: 62c2a16240923988ba097c14 | G63: Zan : Isarapong Bulan | H63: 5d4814e9da0c4d0c789a4bb7 | I63: Medium | J63: Ready to Staging | L63: 30/Apr/26 2:24 PM | M63: 11/May/26 5:22 PM | N63: 11/May/26 12:00 AM | O63: 3 | V63: [Dev][RD][Thana] Sprint 24 | W63: [Dev][RD][Thana] Sprint 24
A64: Story | B64: DEV-4 | C64: 53559 | D64: [Dev][RD][RRS] Optimize MongoDB Bulk Update Coupons Status to Reduce IO Wait (Batch Size Tuning) | E64: Arm:Worawat Chotipongchoawalit | F64: 712020:2195d849-5cdb-4ec8-866f-e82a3528bff7 | G64: Aom: Pornsawan Polnyiem | H64: 5d2ed694a666040c85096e17 | I64: Medium | J64: Ready to Staging | L64: 30/Apr/26 1:43 PM | M64: 15/May/26 2:35 PM | O64: 5 | V64: [Dev][All Project] Sprint 24
A65: Story | B65: RDTHANA-483 | C65: 53558 | D65: [DEV][RD][TDM] Setup Turtle Shopify on Production | E65: Zan : Isarapong Bulan | F65: 5d4814e9da0c4d0c789a4bb7 | G65: Zan : Isarapong Bulan | H65: 5d4814e9da0c4d0c789a4bb7 | I65: Medium | J65: Done | L65: 30/Apr/26 10:59 AM | M65: 13/May/26 11:45 AM | O65: 3 | P65: No-QA | V65: [Dev][RD][Thana] Sprint 24 | W65: [Dev][RD][Thana] Sprint 24
A66: Story | B66: RDTHANA-482 | C66: 53557 | D66: [DEV][RD][TDM] Setup Dashaus shopify in Production | E66: Zan : Isarapong Bulan | F66: 5d4814e9da0c4d0c789a4bb7 | G66: Zan : Isarapong Bulan | H66: 5d4814e9da0c4d0c789a4bb7 | I66: Medium | J66: Done | L66: 30/Apr/26 10:58 AM | M66: 13/May/26 11:44 AM | O66: 5 | P66: No-QA | V66: [Dev][RD][Thana] Sprint 24 | W66: [Dev][RD][Thana] Sprint 24
A67: Story | B67: RDAPS-456 | C67: 53553 | D67: [Dev][RD][RRS] Improve upload coupon code logic and refactor | E67: Mai:Sateta Abvanawong | F67: 64000e4f15d668edd8edc7ea | G67: Aom: Pornsawan Polnyiem | H67: 5d2ed694a666040c85096e17 | I67: Medium | J67: In Review | L67: 30/Apr/26 9:33 AM | M67: 14/May/26 2:09 PM | N67: 15/May/26 12:00 AM | O67: 5 | V67: [Dev][All Project] Sprint 24
A68: Story | B68: DPE-506 | C68: 53505 | D68: [Dev][RD][ORD] Enhance Pay with Point Flow to Handle CleverTap Payment Provider | E68: Moss : Kittapath Sangvikukit | F68: 712020:b33baa03-2b29-4662-9923-dbdc2bbf980d | G68: Aom: Pornsawan Polnyiem | H68: 5d2ed694a666040c85096e17 | I68: Medium | J68: Ready To Test | L68: 29/Apr/26 11:30 AM | M68: 14/May/26 4:23 PM | N68: 15/May/26 12:00 AM | O68: 2 | U68: 14400 | V68: [Dev][RD][New PE] Sprint 24
A69: Story | B69: DPE-505 | C69: 53504 | D69: [Dev][RD][PEP] Update golang version | E69: A:Phongthorn | F69: 5b3c867ae263df2dc32f7e35 | G69: Aom: Pornsawan Polnyiem | H69: 5d2ed694a666040c85096e17 | I69: Medium | J69: In Review | L69: 29/Apr/26 11:02 AM | M69: 15/May/26 3:13 PM | N69: 05/May/26 12:00 AM | O69: 5 | P69: No-QA | U69: 57600 | V69: [Dev][RD][New PE] Sprint 23 | W69: [Dev][RD][New PE] Sprint 24
A70: Sub-task | B70: DPE-503 | C70: 53479 | D70: Test execution | E70: Plai Thanaporn Rimnong-ang | F70: 62c2a5acefb17d6ce62e41bf | G70: Aom: Pornsawan Polnyiem | H70: 5d2ed694a666040c85096e17 | I70: Medium | J70: Done | L70: 28/Apr/26 3:44 PM | M70: 06/May/26 2:55 PM | V70: [Dev][RD][New PE] Sprint 21 | W70: [Dev][RD][New PE] Sprint 22 | X70: [Dev][RD][New PE] Sprint 23 | Y70: [Dev][RD][New PE] Sprint 24
A71: Sub-task | B71: DPE-502 | C71: 53477 | D71: Create test case | E71: Plai Thanaporn Rimnong-ang | F71: 62c2a5acefb17d6ce62e41bf | G71: Aom: Pornsawan Polnyiem | H71: 5d2ed694a666040c85096e17 | I71: Medium | J71: Done | L71: 28/Apr/26 3:44 PM | M71: 06/May/26 2:55 PM | V71: [Dev][RD][New PE] Sprint 21 | W71: [Dev][RD][New PE] Sprint 22 | X71: [Dev][RD][New PE] Sprint 23 | Y71: [Dev][RD][New PE] Sprint 24
A72: Sub-task | B72: DPE-499 | C72: 53471 | D72: Test execution | E72: Plai Thanaporn Rimnong-ang | F72: 62c2a5acefb17d6ce62e41bf | G72: Aom: Pornsawan Polnyiem | H72: 5d2ed694a666040c85096e17 | I72: Medium | J72: Done | L72: 28/Apr/26 3:44 PM | M72: 13/May/26 4:12 PM | V72: [Dev][RD][New PE] Sprint 21 | W72: [Dev][RD][New PE] Sprint 22 | X72: [Dev][RD][New PE] Sprint 23 | Y72: [Dev][RD][New PE] Sprint 24
A73: Sub-task | B73: DPE-498 | C73: 53469 | D73: Create test case | E73: Plai Thanaporn Rimnong-ang | F73: 62c2a5acefb17d6ce62e41bf | G73: Aom: Pornsawan Polnyiem | H73: 5d2ed694a666040c85096e17 | I73: Medium | J73: Done | L73: 28/Apr/26 3:44 PM | M73: 12/May/26 5:17 PM | V73: [Dev][RD][New PE] Sprint 21 | W73: [Dev][RD][New PE] Sprint 22 | X73: [Dev][RD][New PE] Sprint 23 | Y73: [Dev][RD][New PE] Sprint 24
A74: Sub-task | B74: DPE-497 | C74: 53467 | D74: Test execution | E74: Plai Thanaporn Rimnong-ang | F74: 62c2a5acefb17d6ce62e41bf | G74: Aom: Pornsawan Polnyiem | H74: 5d2ed694a666040c85096e17 | I74: Medium | J74: Done | L74: 28/Apr/26 3:44 PM | M74: 06/May/26 10:27 AM | V74: [Dev][RD][New PE] Sprint 21 | W74: [Dev][RD][New PE] Sprint 22 | X74: [Dev][RD][New PE] Sprint 23 | Y74: [Dev][RD][New PE] Sprint 24
A75: Sub-task | B75: DPE-496 | C75: 53465 | D75: Create test case | E75: Plai Thanaporn Rimnong-ang | F75: 62c2a5acefb17d6ce62e41bf | G75: Aom: Pornsawan Polnyiem | H75: 5d2ed694a666040c85096e17 | I75: Medium | J75: Done | L75: 28/Apr/26 3:44 PM | M75: 29/Apr/26 5:35 PM | V75: [Dev][RD][New PE] Sprint 21 | W75: [Dev][RD][New PE] Sprint 22 | X75: [Dev][RD][New PE] Sprint 23 | Y75: [Dev][RD][New PE] Sprint 24
A76: Bug | B76: DEVRDSUP-564 | C76: 53463 | D76: [SUP-655][SUB][OfficerApp] BTS admin reported that 1 of the voucher couldn't be mark used, A920 displayed "Usage card is missing" 27/04/2026. | E76: Aom: Pornsawan Polnyiem | F76: 5d2ed694a666040c85096e17 | G76: Abhinaf Singh | H76: 712020:a81c99dd-d5cd-44bd-950a-32f4ff7d56ac | I76: Low | J76: Open | L76: 28/Apr/26 3:20 PM | M76: 15/May/26 9:32 AM | N76: 19/May/26 12:00 AM | P76: a920 | Q76: bts | R76: OfficerApp | S76: prod-issue | T76: sub | V76: [Dev][All Project] Sprint 24
A77: Story | B77: DPE-493 | C77: 53456 | D77: [Dev][RD][SSO-User] Update User Properties on Termination | E77: Mai:Sateta Abvanawong | F77: 64000e4f15d668edd8edc7ea | G77: Aom: Pornsawan Polnyiem | H77: 5d2ed694a666040c85096e17 | I77: Medium | J77: Ready To Test | L77: 28/Apr/26 2:15 PM | M77: 14/May/26 1:43 PM | N77: 15/May/26 12:00 AM | O77: 2 | P77: sso-user | U77: 14400 | V77: [Dev][RD][New PE] Sprint 24
A78: Story | B78: DPE-492 | C78: 53440 | D78: Dev][RD][REM] Implement Schema Versioning for Redeemed Transaction | E78: Nim : muthita munmueang | F78: 712020:e80312b7-b5b0-43e8-b198-3d8fce4532bb | G78: Aom: Pornsawan Polnyiem | H78: 5d2ed694a666040c85096e17 | I78: Medium | J78: Ready To Test | L78: 28/Apr/26 9:24 AM | M78: 06/May/26 10:00 AM | N78: 30/Apr/26 12:00 AM | O78: 3 | V78: [Dev][RD][New PE] Sprint 23 | W78: [Dev][RD][New PE] Sprint 24
A79: Story | B79: DPE-491 | C79: 53439 | D79: [Dev][RD][PE Middleware] Refactor OfferRepository: Consolidate GetOffer Methods into Generic Function | E79: Moss : Kittapath Sangvikukit | F79: 712020:b33baa03-2b29-4662-9923-dbdc2bbf980d | G79: Jack: Warin Kesorn | H79: 61a98e8e744c4d00693281d1 | I79: Medium | J79: Ready To Test | L79: 28/Apr/26 8:49 AM | M79: 06/May/26 10:00 AM | N79: 30/Apr/26 12:00 AM | O79: 5 | P79: point-engine-proxy | V79: [Dev][RD][New PE] Sprint 23 | W79: [Dev][RD][New PE] Sprint 24
A80: Sub-task | B80: DPE-486 | C80: 53397 | D80: [QA] Test execution STG | G80: Pueng Prachpreeya | H80: 642a5328f8bc2116accac530 | I80: Medium | J80: To Do | L80: 25/Apr/26 12:46 PM | M80: 25/Apr/26 12:46 PM | V80: [Dev][RD][New PE] Sprint 20 | W80: [Dev][RD][New PE] Sprint 21 | X80: [Dev][RD][New PE] Sprint 22 | Y80: [Dev][RD][New PE] Sprint 23 | Z80: [Dev][RD][New PE] Sprint 24
A81: Sub-task | B81: DPE-485 | C81: 53395 | D81: [QA] Test execution STG | G81: Pueng Prachpreeya | H81: 642a5328f8bc2116accac530 | I81: Medium | J81: To Do | L81: 25/Apr/26 12:46 PM | M81: 25/Apr/26 12:46 PM | V81: [Dev][RD][New PE] Sprint 20 | W81: [Dev][RD][New PE] Sprint 21 | X81: [Dev][RD][New PE] Sprint 22 | Y81: [Dev][RD][New PE] Sprint 23 | Z81: [Dev][RD][New PE] Sprint 24
A82: Sub-task | B82: DPE-484 | C82: 53393 | D82: [QA] Test execution STG | G82: Pueng Prachpreeya | H82: 642a5328f8bc2116accac530 | I82: Medium | J82: To Do | L82: 25/Apr/26 12:46 PM | M82: 25/Apr/26 12:46 PM | V82: [Dev][RD][New PE] Sprint 20 | W82: [Dev][RD][New PE] Sprint 21 | X82: [Dev][RD][New PE] Sprint 22 | Y82: [Dev][RD][New PE] Sprint 23 | Z82: [Dev][RD][New PE] Sprint 24
A83: Sub-task | B83: DPE-483 | C83: 53391 | D83: [QA] Create Sky Web Switch Account test cases | E83: Pueng Prachpreeya | F83: 642a5328f8bc2116accac530 | G83: Pueng Prachpreeya | H83: 642a5328f8bc2116accac530 | I83: Medium | J83: To Do | L83: 25/Apr/26 12:40 PM | M83: 25/Apr/26 12:44 PM | V83: [Dev][RD][New PE] Sprint 20 | W83: [Dev][RD][New PE] Sprint 21 | X83: [Dev][RD][New PE] Sprint 22 | Y83: [Dev][RD][New PE] Sprint 23 | Z83: [Dev][RD][New PE] Sprint 24
A84: Sub-task | B84: DPE-482 | C84: 53389 | D84: [QA] Create Sky API Switch account test cases | E84: Pueng Prachpreeya | F84: 642a5328f8bc2116accac530 | G84: Pueng Prachpreeya | H84: 642a5328f8bc2116accac530 | I84: Medium | J84: To Do | L84: 25/Apr/26 12:38 PM | M84: 25/Apr/26 12:43 PM | V84: [Dev][RD][New PE] Sprint 20 | W84: [Dev][RD][New PE] Sprint 21 | X84: [Dev][RD][New PE] Sprint 22 | Y84: [Dev][RD][New PE] Sprint 23 | Z84: [Dev][RD][New PE] Sprint 24
A85: Sub-task | B85: DPE-481 | C85: 53387 | D85: [QA] Create Sky API Reactivate test cases | E85: Pueng Prachpreeya | F85: 642a5328f8bc2116accac530 | G85: Pueng Prachpreeya | H85: 642a5328f8bc2116accac530 | I85: Medium | J85: To Do | L85: 25/Apr/26 12:38 PM | M85: 25/Apr/26 12:43 PM | V85: [Dev][RD][New PE] Sprint 20 | W85: [Dev][RD][New PE] Sprint 21 | X85: [Dev][RD][New PE] Sprint 22 | Y85: [Dev][RD][New PE] Sprint 23 | Z85: [Dev][RD][New PE] Sprint 24
A86: Sub-task | B86: DPE-480 | C86: 53385 | D86: [QA] Test execution STG | G86: Pueng Prachpreeya | H86: 642a5328f8bc2116accac530 | I86: Medium | J86: To Do | L86: 25/Apr/26 12:36 PM | M86: 25/Apr/26 12:36 PM | V86: [Dev][RD][New PE] Sprint 20 | W86: [Dev][RD][New PE] Sprint 21 | X86: [Dev][RD][New PE] Sprint 22 | Y86: [Dev][RD][New PE] Sprint 23 | Z86: [Dev][RD][New PE] Sprint 24
A87: Sub-task | B87: DPE-479 | C87: 53383 | D87: [QA] Create Sky API Register Member test cases | E87: Pueng Prachpreeya | F87: 642a5328f8bc2116accac530 | G87: Pueng Prachpreeya | H87: 642a5328f8bc2116accac530 | I87: Medium | J87: Done | L87: 25/Apr/26 12:35 PM | M87: 30/Apr/26 11:48 AM | V87: [Dev][RD][New PE] Sprint 20 | W87: [Dev][RD][New PE] Sprint 21 | X87: [Dev][RD][New PE] Sprint 22 | Y87: [Dev][RD][New PE] Sprint 23 | Z87: [Dev][RD][New PE] Sprint 24
A88: Story | B88: DPE-478 | C88: 53379 | D88: [Dev][RD][BFF] Improve mapping API response message for Redemption API | E88: Nim : muthita munmueang | F88: 712020:e80312b7-b5b0-43e8-b198-3d8fce4532bb | G88: Aom: Pornsawan Polnyiem | H88: 5d2ed694a666040c85096e17 | I88: High | J88: Ready To Test | L88: 24/Apr/26 7:25 PM | M88: 07/May/26 11:31 AM | N88: 30/Apr/26 12:00 AM | O88: 2 | V88: [Dev][RD][New PE] Sprint 23 | W88: [Dev][RD][New PE] Sprint 24
A89: Sub-task | B89: DPE-477 | C89: 53367 | D89: Test execution | E89: Plai Thanaporn Rimnong-ang | F89: 62c2a5acefb17d6ce62e41bf | G89: Aom: Pornsawan Polnyiem | H89: 5d2ed694a666040c85096e17 | I89: Medium | J89: In Progress | L89: 24/Apr/26 2:10 PM | M89: 14/May/26 3:25 PM | V89: [Dev][RD][New PE] Sprint 23 | W89: [Dev][RD][New PE] Sprint 24
A90: Sub-task | B90: DPE-476 | C90: 53365 | D90: Create test case | E90: Plai Thanaporn Rimnong-ang | F90: 62c2a5acefb17d6ce62e41bf | G90: Aom: Pornsawan Polnyiem | H90: 5d2ed694a666040c85096e17 | I90: Medium | J90: Done | L90: 24/Apr/26 2:10 PM | M90: 14/May/26 3:25 PM | V90: [Dev][RD][New PE] Sprint 23 | W90: [Dev][RD][New PE] Sprint 24
A91: Sub-task | B91: DPE-475 | C91: 53361 | D91: Test execution | E91: Plai Thanaporn Rimnong-ang | F91: 62c2a5acefb17d6ce62e41bf | G91: Jack: Warin Kesorn | H91: 61a98e8e744c4d00693281d1 | I91: Medium | J91: In Progress | L91: 24/Apr/26 11:39 AM | M91: 14/May/26 5:25 PM | V91: [Dev][RD][New PE] Sprint 23 | W91: [Dev][RD][New PE] Sprint 24
A92: Sub-task | B92: DPE-474 | C92: 53359 | D92: Create test case | E92: Plai Thanaporn Rimnong-ang | F92: 62c2a5acefb17d6ce62e41bf | G92: Jack: Warin Kesorn | H92: 61a98e8e744c4d00693281d1 | I92: Medium | J92: Done | L92: 24/Apr/26 11:39 AM | M92: 14/May/26 5:25 PM | V92: [Dev][RD][New PE] Sprint 23 | W92: [Dev][RD][New PE] Sprint 24
A93: Sub-task | B93: DPE-473 | C93: 53355 | D93: Test execution | E93: Plai Thanaporn Rimnong-ang | F93: 62c2a5acefb17d6ce62e41bf | G93: Jack: Warin Kesorn | H93: 61a98e8e744c4d00693281d1 | I93: Medium | J93: In Progress | L93: 24/Apr/26 10:57 AM | M93: 24/Apr/26 3:27 PM | V93: [Dev][RD][New PE] Sprint 23 | W93: [Dev][RD][New PE] Sprint 24
A94: Sub-task | B94: DPE-472 | C94: 53353 | D94: Create test case | E94: Plai Thanaporn Rimnong-ang | F94: 62c2a5acefb17d6ce62e41bf | G94: Jack: Warin Kesorn | H94: 61a98e8e744c4d00693281d1 | I94: Medium | J94: Done | L94: 24/Apr/26 10:57 AM | M94: 24/Apr/26 1:20 PM | V94: [Dev][RD][New PE] Sprint 23 | W94: [Dev][RD][New PE] Sprint 24
A95: Story | B95: DPE-470 | C95: 53336 | D95: [Dev][RD][BFF] Enhance mapping detail fields from offer name to offer display name | E95: Moss : Kittapath Sangvikukit | F95: 712020:b33baa03-2b29-4662-9923-dbdc2bbf980d | G95: Jack: Warin Kesorn | H95: 61a98e8e744c4d00693281d1 | I95: Medium | J95: Ready To Test | L95: 23/Apr/26 3:48 PM | M95: 14/May/26 5:34 PM | N95: 30/Apr/26 12:00 AM | O95: 1 | P95: BFF | U95: 7200 | V95: [Dev][RD][New PE] Sprint 23 | W95: [Dev][RD][New PE] Sprint 24
A96: Bug | B96: DEVRDSUP-556 | C96: 53335 | D96: [SUP-647][NBO][SUBSCRIPTION][REWARDS] - "Draft/ Inactive/ Active Rewards" check duplicate codes with "Expired Rewards" | E96: Aom: Pornsawan Polnyiem | F96: 5d2ed694a666040c85096e17 | G96: Abhinaf Singh | H96: 712020:a81c99dd-d5cd-44bd-950a-32f4ff7d56ac | I96: Medium | J96: Fixing | L96: 23/Apr/26 3:30 PM | M96: 15/May/26 9:32 AM | N96: 07/May/26 12:00 AM | P96: rem | Q96: sub | V96: [Dev][All Project] Sprint 24
A97: Story | B97: DPE-469 | C97: 53334 | D97: [Dev][RD][PE Middleware] Enhance Offer Name Fields Mapping to CleverTap | E97: Moss : Kittapath Sangvikukit | F97: 712020:b33baa03-2b29-4662-9923-dbdc2bbf980d | G97: Jack: Warin Kesorn | H97: 61a98e8e744c4d00693281d1 | I97: Medium | J97: Ready To Test | L97: 23/Apr/26 3:25 PM | M97: 14/May/26 3:59 PM | N97: 30/Apr/26 12:00 AM | O97: 2 | P97: point-engine-proxy | U97: 7200 | V97: [Dev][RD][New PE] Sprint 23 | W97: [Dev][RD][New PE] Sprint 24
A98: Story | B98: DPE-468 | C98: 53300 | D98: [Dev][RD][BOF] Improve product creation logic | E98: Arm:Worawat Chotipongchoawalit | F98: 712020:2195d849-5cdb-4ec8-866f-e82a3528bff7 | G98: Aom: Pornsawan Polnyiem | H98: 5d2ed694a666040c85096e17 | I98: Medium | J98: Done | L98: 22/Apr/26 3:51 PM | M98: 15/May/26 10:32 AM | N98: 30/Apr/26 12:00 AM | O98: 1 | V98: [Dev][RD][New PE] Sprint 23 | W98: [Dev][RD][New PE] Sprint 24
A99: Story | B99: DPE-467 | C99: 53291 | D99: [Dev][RD][goutil] Improve func get point history to support additional filtering | E99: Nim : muthita munmueang | F99: 712020:e80312b7-b5b0-43e8-b198-3d8fce4532bb | G99: Aom: Pornsawan Polnyiem | H99: 5d2ed694a666040c85096e17 | I99: Medium | J99: Ready to Staging | L99: 22/Apr/26 1:15 PM | M99: 13/May/26 10:42 AM | N99: 30/Apr/26 12:00 AM | O99: 1 | P99: No-QA | V99: [Dev][RD][New PE] Sprint 23 | W99: [Dev][RD][New PE] Sprint 24
A100: Story | B100: DPE-466 | C100: 53282 | D100: [Dev][RD][PE Proxy Scheduler] Enhance command for importing RC retail transactions#2 | E100: Arm:Worawat Chotipongchoawalit | F100: 712020:2195d849-5cdb-4ec8-866f-e82a3528bff7 | G100: Aom: Pornsawan Polnyiem | H100: 5d2ed694a666040c85096e17 | I100: Medium | J100: Ready To Test | L100: 22/Apr/26 10:06 AM | M100: 08/May/26 9:42 AM | N100: 23/Apr/26 12:00 AM | O100: 1 | V100: [Dev][RD][New PE] Sprint 23 | W100: [Dev][RD][New PE] Sprint 24
...

Sheet Summarize Sprint 23
A1: Column 1 | B1: Total Stories Point | C1: Total Manhour | D1: Point Done | E1: Manhour Done | F1: Note
A2: 9 Mar - 20 Mar
A3: Dev Resource Available | B3: 21 | C3: 444.5
A4: Meeting Planned | F4: Ref
A5: Additional Meeting | F5: Ref
A6: Deployment | C6: 2 | F6: 1 ครั้ง 1. 2 คน
A7: Development Sprint Total | B7: =SUM('Sprint 23'!O:O) -> 507 | C7: =ROUND(SUM('Sprint 23'!S:S)/3600,2) -> 775.83 | D7: =SUMIF('Sprint 23'!J:J, "Done", 'Sprint 23'!O:O) -> 94 | E7: =ROUND(SUMIF('Sprint 23'!J:J, "Done", 'Sprint 23'!S:S)/3600,2) -> 148.83
A9: Ad-hoc Mid Sprint | B9: 0 | C9: =IFERROR(__xludf.DUMMYFUNCTION("ROUND(IFERROR(SUM(FILTER('Sprint 23'!S:S, ('Sprint 23'!Q:Q = ""mid-sprint"")))/3600,0),2)"),0.0) -> 0 | D9: =IFERROR(__xludf.DUMMYFUNCTION("IFERROR(SUM(FILTER('Sprint 23'!O:O, (('Sprint 23'!J:J = ""Done"")) * ('Sprint 23'!Q:Q = ""mid-sprint""))),0)"),0.0) -> 0 | E9: =IFERROR(__xludf.DUMMYFUNCTION("ROUND(IFERROR(SUM(FILTER('Sprint 23'!S:S, (('Sprint 23'!J:J = ""Done"")) * ('Sprint 23'!P:P = ""mid-sprint"")))/3600,0),2)"),0.0) -> 0 | F9: 2 tasks
A10: Requirement changes after refinement? | B10: =IFERROR(__xludf.DUMMYFUNCTION("ROUND(IFERROR(SUM(FILTER('Sprint 23'!S:S, ('Sprint 23'!Q:Q = ""change-request"")))/3600,0),2)"),0.0) -> 0 | D10: =IFERROR(__xludf.DUMMYFUNCTION("IFERROR(SUM(FILTER('Sprint 23'!O:O, (('Sprint 23'!J:J = ""Done"")) * ('Sprint 23'!Q:Q = ""change-request""))),0)"),0.0) -> 0 | E10: =IFERROR(__xludf.DUMMYFUNCTION("ROUND(IFERROR(SUM(FILTER('Sprint 23'!S:S, (('Sprint 23'!J:J = ""Done"")) * ('Sprint 23'!Q:Q = ""change-request"")))/3600,0),2)"),0.0) -> 0 | F10: 0 tasks
A12: Aek | B12: =IFERROR(__xludf.DUMMYFUNCTION("IFERROR(SUM(FILTER('Sprint 23'!O:O, ('Sprint 23'!E:E = ""Aek:Atiphat Nanthachitvanich""))),0)"),22.0) -> 22 | C12: =IFERROR(__xludf.DUMMYFUNCTION("ROUND(IFERROR(SUM(FILTER('Sprint 23'!S:S, ('Sprint 23'!E:E = ""Aek:Atiphat Nanthachitvanich"")))/3600,0),2)"),57.67) -> 57.67 | D12: =IFERROR(__xludf.DUMMYFUNCTION("IFERROR(SUM(FILTER('Sprint 23'!O:O, (('Sprint 23'!J:J = ""Done"")) * ('Sprint 23'!E:E = ""Aek:Atiphat Nanthachitvanich""))),0)"),17.0) -> 17 | E12: =IFERROR(__xludf.DUMMYFUNCTION("ROUND(IFERROR(SUM(FILTER('Sprint 23'!S:S, (('Sprint 23'!J:J = ""Done"")) * ('Sprint 23'!E:E = ""Aek:Atiphat Nanthachitvanich"")))/3600,0),2)"),41.67) -> 41.67
A13: A | B13: =IFERROR(__xludf.DUMMYFUNCTION("IFERROR(SUM(FILTER('Sprint 23'!O:O, ('Sprint 23'!E:E = ""A:Phongthorn""))),0)"),73.0) -> 73 | C13: =IFERROR(__xludf.DUMMYFUNCTION("ROUND(IFERROR(SUM(FILTER('Sprint 23'!S:S, ('Sprint 23'!E:E = ""A:Phongthorn"")))/3600,0),2)"),202.0) -> 202 | D13: =IFERROR(__xludf.DUMMYFUNCTION("IFERROR(SUM(FILTER('Sprint 23'!O:O, (('Sprint 23'!J:J = ""Done"")) * ('Sprint 23'!E:E = ""A:Phongthorn""))),0)"),13.0) -> 13 | E13: =IFERROR(__xludf.DUMMYFUNCTION("ROUND(IFERROR(SUM(FILTER('Sprint 23'!S:S, (('Sprint 23'!J:J = ""Done"")) * ('Sprint 23'!E:E = ""A:Phongthorn"")))/3600,0),2)"),36.0) -> 36
A14: Aom | B14: =IFERROR(__xludf.DUMMYFUNCTION("IFERROR(SUM(FILTER('Sprint 23'!O:O, ('Sprint 23'!E:E = ""Aom: Pornsawan Polnyiem""))),0)"),33.0) -> 33 | C14: =IFERROR(__xludf.DUMMYFUNCTION("ROUND(IFERROR(SUM(FILTER('Sprint 23'!S:S, ('Sprint 23'!E:E = ""Aom: Pornsawan Polnyiem"")))/3600,0),2)"),3.17) -> 3.17 | D14: =IFERROR(__xludf.DUMMYFUNCTION("IFERROR(SUM(FILTER('Sprint 23'!O:O, (('Sprint 23'!J:J = ""Done"")) * ('Sprint 23'!E:E = ""Aom: Pornsawan Polnyiem""))),0)"),5.0) -> 5 | E14: =IFERROR(__xludf.DUMMYFUNCTION("ROUND(IFERROR(SUM(FILTER('Sprint 23'!S:S, (('Sprint 23'!J:J = ""Done"")) * ('Sprint 23'!E:E = ""Aom: Pornsawan Polnyiem"")))/3600,0),2)"),3.17) -> 3.17
A15: Zan | B15: =IFERROR(__xludf.DUMMYFUNCTION("IFERROR(SUM(FILTER('Sprint 23'!O:O, ('Sprint 23'!E:E = ""Zan : Isarapong Bulan""))),0)"),27.0) -> 27 | C15: =IFERROR(__xludf.DUMMYFUNCTION("ROUND(IFERROR(SUM(FILTER('Sprint 23'!S:S, ('Sprint 23'!E:E = ""Zan : Isarapong Bulan"")))/3600,0),2)"),0.0) -> 0 | D15: =IFERROR(__xludf.DUMMYFUNCTION("IFERROR(SUM(FILTER('Sprint 23'!O:O, (('Sprint 23'!J:J = ""Done"")) * ('Sprint 23'!E:E = ""Zan : Isarapong Bulan""))),0)"),14.0) -> 14 | E15: =IFERROR(__xludf.DUMMYFUNCTION("ROUND(IFERROR(SUM(FILTER('Sprint 23'!S:S, (('Sprint 23'!J:J = ""Done"")) * ('Sprint 23'!E:E = ""Zan : Isarapong Bulan"")))/3600,0),2)"),0.0) -> 0
A16: Mai | B16: =IFERROR(__xludf.DUMMYFUNCTION("IFERROR(SUM(FILTER('Sprint 23'!O:O, ('Sprint 23'!E:E = ""Mai:Sateta Abvanawong""))),0)"),75.0) -> 75 | C16: =IFERROR(__xludf.DUMMYFUNCTION("ROUND(IFERROR(SUM(FILTER('Sprint 23'!S:S, ('Sprint 23'!E:E = ""Mai:Sateta Abvanawong"")))/3600,0),2)"),150.0) -> 150 | D16: =IFERROR(__xludf.DUMMYFUNCTION("IFERROR(SUM(FILTER('Sprint 23'!O:O, (('Sprint 23'!J:J = ""Done"")) * ('Sprint 23'!E:E = ""Mai:Sateta Abvanawong""))),0)"),9.0) -> 9 | E16: =IFERROR(__xludf.DUMMYFUNCTION("ROUND(IFERROR(SUM(FILTER('Sprint 23'!S:S, (('Sprint 23'!J:J = ""Done"")) * ('Sprint 23'!E:E = ""Mai:Sateta Abvanawong""))),0)/3600,2)"),8.0) -> 8
A17: Mac | B17: =IFERROR(__xludf.DUMMYFUNCTION("IFERROR(SUM(FILTER('Sprint 23'!O:O, ('Sprint 23'!E:E = ""Mac: Jarupong Pawichpongkul""))),0)"),82.0) -> 82 | C17: =IFERROR(__xludf.DUMMYFUNCTION("ROUND(IFERROR(SUM(FILTER('Sprint 23'!S:S, ('Sprint 23'!E:E = ""Mac: Jarupong Pawichpongkul"")))/3600,0),2)"),181.0) -> 181 | D17: =IFERROR(__xludf.DUMMYFUNCTION("IFERROR(SUM(FILTER('Sprint 23'!O:O, (('Sprint 23'!J:J = ""Done"")) * ('Sprint 23'!E:E = ""Mac: Jarupong Pawichpongkul""))),0)"),4.0) -> 4 | E17: =IFERROR(__xludf.DUMMYFUNCTION("ROUND(IFERROR(SUM(FILTER('Sprint 23'!S:S, (('Sprint 23'!J:J = ""Done"")) * ('Sprint 23'!E:E = ""Mac: Jarupong Pawichpongkul"")))/3600,0),2)"),0.0) -> 0
A18: Mos | B18: =IFERROR(__xludf.DUMMYFUNCTION("IFERROR(SUM(FILTER('Sprint 23'!O:O, ('Sprint 23'!E:E = ""Moss : Kittapath Sangvikukit""))),0)"),62.0) -> 62 | C18: =IFERROR(__xludf.DUMMYFUNCTION("ROUND(IFERROR(SUM(FILTER('Sprint 23'!S:S, ('Sprint 23'!E:E = ""Moss : Kittapath Sangvikukit"")))/3600,0),2)"),78.0) -> 78 | D18: =IFERROR(__xludf.DUMMYFUNCTION("IFERROR(SUM(FILTER('Sprint 23'!O:O, (('Sprint 23'!J:J = ""Done"")) * ('Sprint 23'!E:E = ""Moss : Kittapath Sangvikukit""))),0)"),13.0) -> 13 | E18: =IFERROR(__xludf.DUMMYFUNCTION("ROUND(IFERROR(SUM(FILTER('Sprint 23'!S:S, (('Sprint 23'!J:J = ""Done"")) * ('Sprint 23'!E:E = ""Moss : Kittapath Sangvikukit"")))/3600,0),2)"),28.0) -> 28
A19: Jack | B19: =IFERROR(__xludf.DUMMYFUNCTION("IFERROR(SUM(FILTER('Sprint 23'!O:O, ('Sprint 23'!E:E = ""Jack: Warin Kesorn""))),0)"),11.0) -> 11 | C19: =IFERROR(__xludf.DUMMYFUNCTION("ROUND(IFERROR(SUM(FILTER('Sprint 23'!S:S, ('Sprint 23'!E:E = ""Jack: Warin Kesorn"")))/3600,0),2)"),0.0) -> 0 | D19: =IFERROR(__xludf.DUMMYFUNCTION("IFERROR(SUM(FILTER('Sprint 23'!O:O, (('Sprint 23'!J:J = ""Done"")) * ('Sprint 23'!E:E = ""Jack: Warin Kesorn""))),0)"),11.0) -> 11 | E19: =IFERROR(__xludf.DUMMYFUNCTION("ROUND(IFERROR(SUM(FILTER('Sprint 23'!S:S, (('Sprint 23'!J:J = ""Done"")) * ('Sprint 23'!E:E = ""Jack: Warin Kesorn"")))/3600,0),2)"),0.0) -> 0
A20: Nim | B20: =IFERROR(__xludf.DUMMYFUNCTION("IFERROR(SUM(FILTER('Sprint 23'!O:O, ('Sprint 23'!E:E = ""Nim : muthita munmueang""))),0)"),59.0) -> 59 | C20: =IFERROR(__xludf.DUMMYFUNCTION("ROUND(IFERROR(SUM(FILTER('Sprint 23'!S:S, ('Sprint 23'!E:E = ""Nim : muthita munmueang"")))/3600,0),2)"),104.0) -> 104 | D20: =IFERROR(__xludf.DUMMYFUNCTION("IFERROR(SUM(FILTER('Sprint 23'!O:O, (('Sprint 23'!J:J = ""Done"")) * ('Sprint 23'!E:E = ""Nim : muthita munmueang""))),0)"),3.0) -> 3 | E20: =IFERROR(__xludf.DUMMYFUNCTION("ROUND(IFERROR(SUM(FILTER('Sprint 23'!S:S, (('Sprint 23'!J:J = ""Done"")) * ('Sprint 23'!E:E = ""Nim : muthita munmueang"")))/3600,0),2)"),32.0) -> 32
A21: Arm | B21: =IFERROR(__xludf.DUMMYFUNCTION("IFERROR(SUM(FILTER('Sprint 23'!O:O, ('Sprint 23'!E:E = ""Arm:Worawat Chotipongchoawalit""))),0)"),63.0) -> 63 | C21: =IFERROR(__xludf.DUMMYFUNCTION("ROUND(IFERROR(SUM(FILTER('Sprint 23'!S:S, ('Sprint 23'!E:E = ""Arm:Worawat Chotipongchoawalit"")))/3600,0),2)"),0.0) -> 0 | D21: =IFERROR(__xludf.DUMMYFUNCTION("IFERROR(SUM(FILTER('Sprint 23'!O:O, (('Sprint 23'!J:J = ""Done"")) * ('Sprint 23'!E:E = ""Arm:Worawat Chotipongchoawalit""))),0)"),5.0) -> 5 | E21: =IFERROR(__xludf.DUMMYFUNCTION("ROUND(IFERROR(SUM(FILTER('Sprint 23'!S:S, (('Sprint 23'!J:J = ""Done"")) * ('Sprint 23'!E:E = ""Arm:Worawat Chotipongchoawalit"")))/3600,0),2)"),0.0) -> 0
B25: System Architech | F25: Permanent Dev. | I25: Contract | J25: Outsource
A26: Projects (Stories Points) | B26: Aek | C26: Zan | D26: Aom | E26: Jack | F26: A | G26: Mac | H26: Mai | I26: Arm | J26: Mos | K26: Nim

Sheet Sprint 23
A1: Issue Type | B1: Issue key | C1: Issue id | D1: Summary | E1: Assignee | F1: Assignee Id | G1: Reporter | H1: Reporter Id | I1: Priority | J1: Status | K1: Resolution | L1: Created | M1: Updated | N1: Due date | O1: Custom field (Story Points) | P1: Labels | Q1: Labels | R1: Labels | S1: Original estimate | T1: Sprint | U1: Sprint | V1: Sprint | W1: Sprint | X1: Sprint | Y1: Sprint | Z1: Sprint | AA1: Sprint | AB1: Sprint | AC1: Sprint
A2: Sub-task | B2: DRST-94 | C2: 53577 | D2: [QA] Test Execution - UAT | E2: Max (QA) : Surawut Sae-nim | F2: 62d4e007098e73c4e5ee0d8d | G2: Max (QA) : Surawut Sae-nim | H2: 62d4e007098e73c4e5ee0d8d | I2: Medium | J2: To Do | L2: 30/Apr/26 5:35 PM | M2: 30/Apr/26 5:35 PM | T2: [Dev RD][VIMI Termi] Sprint 20 | U2: [Dev RD][VIMI Termi] Sprint 21 | V2: [Dev RD][VIMI Termi] Sprint 22 | W2: [Dev RD][VIMI Termi] Sprint 23
A3: Sub-task | B3: DRST-93 | C3: 53575 | D3: [QA] Test Execution - STG | E3: Max (QA) : Surawut Sae-nim | F3: 62d4e007098e73c4e5ee0d8d | G3: Max (QA) : Surawut Sae-nim | H3: 62d4e007098e73c4e5ee0d8d | I3: Medium | J3: Done | L3: 30/Apr/26 5:31 PM | M3: 30/Apr/26 5:34 PM | T3: [Dev RD][VIMI Termi] Sprint 20 | U3: [Dev RD][VIMI Termi] Sprint 21 | V3: [Dev RD][VIMI Termi] Sprint 22 | W3: [Dev RD][VIMI Termi] Sprint 23
A4: Story | B4: RDAPS-457 | C4: 53555 | D4: [SA][RD] Task preparation #24 | E4: Zan : Isarapong Bulan | F4: 5d4814e9da0c4d0c789a4bb7 | G4: Zan : Isarapong Bulan | H4: 5d4814e9da0c4d0c789a4bb7 | I4: Medium | J4: To Do | L4: 30/Apr/26 9:59 AM | M4: 30/Apr/26 9:59 AM | O4: 8 | T4: [Dev][All Project] Sprint 23
A5: Story | B5: RDAPS-455 | C5: 53517 | D5: [SA][RD] PayPoint meeting | E5: Zan : Isarapong Bulan | F5: 5d4814e9da0c4d0c789a4bb7 | G5: Zan : Isarapong Bulan | H5: 5d4814e9da0c4d0c789a4bb7 | I5: Medium | J5: Done | L5: 29/Apr/26 2:59 PM | M5: 30/Apr/26 9:58 AM | O5: 1 | T5: [Dev][All Project] Sprint 23
A6: Story | B6: DPE-505 | C6: 53504 | D6: [Dev][RD][PEP] Update golang version | E6: A:Phongthorn | F6: 5b3c867ae263df2dc32f7e35 | G6: Aom: Pornsawan Polnyiem | H6: 5d2ed694a666040c85096e17 | I6: Medium | J6: In Progress | L6: 29/Apr/26 11:02 AM | M6: 30/Apr/26 10:57 AM | N6: 05/May/26 12:00 AM | O6: 3 | S6: 28800 | T6: [Dev][RD][New PE] Sprint 23
A7: Story | B7: DPE-504 | C7: 53501 | D7: [Dev][RD] Provide credential information | E7: Aom: Pornsawan Polnyiem | F7: 5d2ed694a666040c85096e17 | G7: Aom: Pornsawan Polnyiem | H7: 5d2ed694a666040c85096e17 | I7: Medium | J7: Done | L7: 29/Apr/26 10:23 AM | M7: 30/Apr/26 3:19 PM | O7: 1 | T7: [Dev][RD][New PE] Sprint 23
A8: Sub-task | B8: DEVRDCT-370 | C8: 53488 | D8: [QA] Check CT catalogs (UAT) | E8: Pueng Prachpreeya | F8: 642a5328f8bc2116accac530 | G8: Pueng Prachpreeya | H8: 642a5328f8bc2116accac530 | I8: Medium | J8: Done | L8: 28/Apr/26 6:39 PM | M8: 28/Apr/26 8:15 PM | T8: [Dev][RD][CT] Sprint 23
A9: Sub-task | B9: DPE-503 | C9: 53479 | D9: Test execution | E9: Plai Thanaporn Rimnong-ang | F9: 62c2a5acefb17d6ce62e41bf | G9: Aom: Pornsawan Polnyiem | H9: 5d2ed694a666040c85096e17 | I9: Medium | J9: To Do | L9: 28/Apr/26 3:44 PM | M9: 28/Apr/26 3:44 PM | T9: [Dev][RD][New PE] Sprint 21 | U9: [Dev][RD][New PE] Sprint 22 | V9: [Dev][RD][New PE] Sprint 23
A10: Sub-task | B10: DPE-502 | C10: 53477 | D10: Create test case | E10: Plai Thanaporn Rimnong-ang | F10: 62c2a5acefb17d6ce62e41bf | G10: Aom: Pornsawan Polnyiem | H10: 5d2ed694a666040c85096e17 | I10: Medium | J10: To Do | L10: 28/Apr/26 3:44 PM | M10: 28/Apr/26 3:44 PM | T10: [Dev][RD][New PE] Sprint 21 | U10: [Dev][RD][New PE] Sprint 22 | V10: [Dev][RD][New PE] Sprint 23
A11: Sub-task | B11: DPE-501 | C11: 53475 | D11: Test execution | E11: Plai Thanaporn Rimnong-ang | F11: 62c2a5acefb17d6ce62e41bf | G11: Aom: Pornsawan Polnyiem | H11: 5d2ed694a666040c85096e17 | I11: Medium | J11: To Do | L11: 28/Apr/26 3:44 PM | M11: 28/Apr/26 3:44 PM | T11: [Dev][RD][New PE] Sprint 21 | U11: [Dev][RD][New PE] Sprint 22 | V11: [Dev][RD][New PE] Sprint 23
A12: Sub-task | B12: DPE-500 | C12: 53473 | D12: Create test case | E12: Plai Thanaporn Rimnong-ang | F12: 62c2a5acefb17d6ce62e41bf | G12: Aom: Pornsawan Polnyiem | H12: 5d2ed694a666040c85096e17 | I12: Medium | J12: To Do | L12: 28/Apr/26 3:44 PM | M12: 28/Apr/26 3:44 PM | T12: [Dev][RD][New PE] Sprint 21 | U12: [Dev][RD][New PE] Sprint 22 | V12: [Dev][RD][New PE] Sprint 23
A13: Sub-task | B13: DPE-499 | C13: 53471 | D13: Test execution | E13: Plai Thanaporn Rimnong-ang | F13: 62c2a5acefb17d6ce62e41bf | G13: Aom: Pornsawan Polnyiem | H13: 5d2ed694a666040c85096e17 | I13: Medium | J13: To Do | L13: 28/Apr/26 3:44 PM | M13: 28/Apr/26 3:44 PM | T13: [Dev][RD][New PE] Sprint 21 | U13: [Dev][RD][New PE] Sprint 22 | V13: [Dev][RD][New PE] Sprint 23
A14: Sub-task | B14: DPE-498 | C14: 53469 | D14: Create test case | E14: Plai Thanaporn Rimnong-ang | F14: 62c2a5acefb17d6ce62e41bf | G14: Aom: Pornsawan Polnyiem | H14: 5d2ed694a666040c85096e17 | I14: Medium | J14: To Do | L14: 28/Apr/26 3:44 PM | M14: 28/Apr/26 3:44 PM | T14: [Dev][RD][New PE] Sprint 21 | U14: [Dev][RD][New PE] Sprint 22 | V14: [Dev][RD][New PE] Sprint 23
A15: Sub-task | B15: DPE-497 | C15: 53467 | D15: Test execution | E15: Plai Thanaporn Rimnong-ang | F15: 62c2a5acefb17d6ce62e41bf | G15: Aom: Pornsawan Polnyiem | H15: 5d2ed694a666040c85096e17 | I15: Medium | J15: To Do | L15: 28/Apr/26 3:44 PM | M15: 28/Apr/26 3:44 PM | T15: [Dev][RD][New PE] Sprint 21 | U15: [Dev][RD][New PE] Sprint 22 | V15: [Dev][RD][New PE] Sprint 23
A16: Sub-task | B16: DPE-496 | C16: 53465 | D16: Create test case | E16: Plai Thanaporn Rimnong-ang | F16: 62c2a5acefb17d6ce62e41bf | G16: Aom: Pornsawan Polnyiem | H16: 5d2ed694a666040c85096e17 | I16: Medium | J16: Done | L16: 28/Apr/26 3:44 PM | M16: 29/Apr/26 5:35 PM | T16: [Dev][RD][New PE] Sprint 21 | U16: [Dev][RD][New PE] Sprint 22 | V16: [Dev][RD][New PE] Sprint 23
A17: Sub-task | B17: DPE-495 | C17: 53462 | D17: Test execution | E17: Plai Thanaporn Rimnong-ang | F17: 62c2a5acefb17d6ce62e41bf | G17: Aom: Pornsawan Polnyiem | H17: 5d2ed694a666040c85096e17 | I17: Medium | J17: Done | L17: 28/Apr/26 2:45 PM | M17: 28/Apr/26 2:45 PM | T17: [Dev][RD][New PE] Sprint 22 | U17: [Dev][RD][New PE] Sprint 23
A18: Sub-task | B18: DPE-494 | C18: 53460 | D18: Create test case | E18: Plai Thanaporn Rimnong-ang | F18: 62c2a5acefb17d6ce62e41bf | G18: Aom: Pornsawan Polnyiem | H18: 5d2ed694a666040c85096e17 | I18: Medium | J18: Done | L18: 28/Apr/26 2:45 PM | M18: 28/Apr/26 2:45 PM | T18: [Dev][RD][New PE] Sprint 22 | U18: [Dev][RD][New PE] Sprint 23
A19: Story | B19: DEVRDSUP-562 | C19: 53452 | D19: [SUP-654]SUB : Disable Credit/Debit Card Payment for BBL Package (MAY2026 Package) | E19: Aom: Pornsawan Polnyiem | F19: 5d2ed694a666040c85096e17 | G19: Abhinaf Singh | H19: 712020:a81c99dd-d5cd-44bd-950a-32f4ff7d56ac | I19: Medium | J19: Done | L19: 28/Apr/26 1:43 PM | M19: 29/Apr/26 10:39 AM | N19: 30/Apr/26 12:00 AM | O19: 1 | P19: BURequest | Q19: sub | T19: [Dev][All Project] Sprint 23
A20: Story | B20: DPE-492 | C20: 53440 | D20: Dev][RD][REM] Implement Schema Versioning for Redeemed Transaction | E20: Nim : muthita munmueang | F20: 712020:e80312b7-b5b0-43e8-b198-3d8fce4532bb | G20: Aom: Pornsawan Polnyiem | H20: 5d2ed694a666040c85096e17 | I20: Medium | J20: Ready To Test | L20: 28/Apr/26 9:24 AM | M20: 30/Apr/26 9:18 AM | N20: 30/Apr/26 12:00 AM | O20: 3 | T20: [Dev][RD][New PE] Sprint 23
